Workbook

Sheet ИЗ ОСНОВЫ НОМЕНКЛАТУР
A1: КАТЕГОРИЯ | B1: КАТ-2 | C1: ПОДКАТЕГОРИЯ | D1: Номенклатура | E1: КАТЕГОРИЯ | F1: КАТ-2
G2: price | H2: abc
A3: Кромочные материалы | E3: Кромочные материалы | G3: #N/A | H3: C
A4: Кромочные материалы | C4: Кромка ПВХ | E4: Кромочные материалы | G4: #N/A | H4: C
A5: Кромочные материалы | B5: Кромка ПВХ Китай | C5: Кромка ПВХ Китай | E5: Кромочные материалы | F5: Кромка ПВХ Китай | G5: #N/A | H5: C
A6: Кромочные материалы | B6: Кромка ПВХ Китай | C6: 19*0,8мм ПВХ | E6: Кромочные материалы | F6: Кромка ПВХ Китай | G6: #N/A | H6: C
A7: Кромочные материалы | B7: Кромка ПВХ Китай | C7: 19*0,8мм ПВХ | D7: 19*0,8мм ПВХ Белый AN | E7: Кромочные материалы | F7: Кромка ПВХ Китай | G7: 18.061539 | H7: A
A8: Кромочные материалы | B8: Кромка ПВХ Китай | C8: 19*0,8мм ПВХ | D8: 19*0,8мм ПВХ Дуб сонома AN | E8: Кромочные материалы | F8: Кромка ПВХ Китай | G8: 25.037059 | H8: A
A9: Кромочные материалы | B9: Кромка ПВХ Китай | C9: 19*0,8мм ПВХ | D9: 19*0,8мм ПВХ Дуб Вотан AN | E9: Кромочные материалы | F9: Кромка ПВХ Китай | G9: 26.14571 | H9: A
A10: Кромочные материалы | B10: Кромка ПВХ Китай | C10: 19*0,8мм ПВХ | D10: 19*0,8мм ПВХ Серый SJ | E10: Кромочные материалы | F10: Кромка ПВХ Китай | G10: 18.169597 | H10: A
A11: Кромочные материалы | B11: Кромка ПВХ Китай | C11: 19*0,8мм ПВХ | D11: 19*0,8мм ПВХ Тэффи SJ | E11: Кромочные материалы | F11: Кромка ПВХ Китай | G11: 17.758084 | H11: A
A12: Кромочные материалы | B12: Кромка ПВХ Китай | C12: 19*0,8мм ПВХ | D12: 19*0,8мм ПВХ Тэффи AN | E12: Кромочные материалы | F12: Кромка ПВХ Китай | G12: 21.594333 | H12: A
A13: Кромочные материалы | B13: Кромка ПВХ Китай | C13: 19*0,8мм ПВХ | D13: 19*0,8мм ПВХ Черный AN | E13: Кромочные материалы | F13: Кромка ПВХ Китай | G13: 18.815736 | H13: A
A14: Кромочные материалы | B14: Кромка ПВХ Китай | C14: 19*0,8мм ПВХ | D14: 19*0,8мм ПВХ Белый (Гладкий) AN | E14: Кромочные материалы | F14: Кромка ПВХ Китай | G14: 22.252896 | H14: A
A15: Кромочные материалы | B15: Кромка ПВХ Китай | C15: 19*0,8мм ПВХ | D15: 19*0,8мм ПВХ Вулканический серый AN | E15: Кромочные материалы | F15: Кромка ПВХ Китай | G15: 23.109631 | H15: A
A16: Кромочные материалы | B16: Кромка ПВХ Китай | C16: 19*0,8мм ПВХ | D16: 19*0,8мм ПВХ Антрацит AN | E16: Кромочные материалы | F16: Кромка ПВХ Китай | G16: 19.798543 | H16: A
A17: Кромочные материалы | B17: Кромка ПВХ Китай | C17: 19*0,8мм ПВХ | D17: 19*0,8мм ПВХ Ясень шимо светлый AN | E17: Кромочные материалы | F17: Кромка ПВХ Китай | G17: 25.043404 | H17: A
A18: Кромочные материалы | B18: Кромка ПВХ Китай | C18: 19*0,8мм ПВХ | D18: 19*0,8мм ПВХ Серый AN | E18: Кромочные материалы | F18: Кромка ПВХ Китай | G18: 20.563563 | H18: A
... A213: Кромочные материалы | B213: Кромка ПВХ Китай | C213: 19*0,8мм ПВХ | D213: 19*0,8мм ПВХ Ена AN | E213: Кромочные материалы | F213: Кромка ПВХ Китай | G213: 71.517488 | H213: C
A214: Кромочные материалы | B214: Кромка ПВХ Китай | C214: 19*1,5мм ПВХ | E214: Кромочные материалы | F214: Кромка ПВХ Китай | G214: #N/A | H214: C
A215: Кромочные материалы | B215: Кромка ПВХ Китай | D215: 19*1,5мм ПВХ Белый AN | E215: Кромочные материалы | F215: Кромка ПВХ Китай | G215: 37.480355 | H215: A
A216: Кромочные материалы | B216: Кромка ПВХ Китай | D216: 19*1,5мм ПВХ Ясень шимо светлый SJ | E216: Кромочные материалы | F216: Кромка ПВХ Китай | G216: 37.117488 | H216: A
A217: Кромочные материалы | B217: Кромка ПВХ Китай | D217: 19*1,5мм ПВХ Дуб вотан AN | E217: Кромочные материалы | F217: Кромка ПВХ Китай | G217: 42.737958 | H217: A
A218: Кромочные материалы | B218: Кромка ПВХ Китай | D218: 19*1,5мм ПВХ Ясень шимо светлый AN | E218: Кромочные материалы | F218: Кромка ПВХ Китай | G218: 43.848085 | H218: A
A219: Кромочные материалы | B219: Кромка ПВХ Китай | D219: 19*1,5мм ПВХ Бежевый AN | E219: Кромочные материалы | F219: Кромка ПВХ Китай | G219: 44.268372 | H219: A
A220: Кромочные материалы | B220: Кромка ПВХ Китай | D220: 19*1,5мм ПВХ Ясень шимо темный AN | E220: Кромочные материалы | F220: Кромка ПВХ Китай | G220: 48.091197 | H220: A
A221: Кромочные материалы | B221: Кромка ПВХ Китай | D221: 19*1,5мм ПВХ Дуб Сонома AN | E221: Кромочные материалы | F221: Кромка ПВХ Китай | G221: 46.496593 | H221: A
A222: Кромочные материалы | B222: Кромка ПВХ Китай | D222: 19*1,5мм ПВХ Ясень шимо темный SJ | E222: Кромочные материалы | F222: Кромка ПВХ Китай | G222: 42.618154 | H222: A
A223: Кромочные материалы | B223: Кромка ПВХ Китай | D223: 19*1,5мм ПВХ Серый AN | E223: Кромочные материалы | F223: Кромка ПВХ Китай | G223: 38.867261 | H223: A
A224: Кромочные материалы | B224: Кромка ПВХ Китай | D224: 19*1,5мм ПВХ Дуб сонома SJ | E224: Кромочные материалы | F224: Кромка ПВХ Китай | G224: 41.768855 | H224: A
A225: Кромочные материалы | B225: Кромка ПВХ Китай | D225: 19*1,5мм ПВХ Антрацит AN | E225: Кромочные материалы | F225: Кромка ПВХ Китай | G225: 39.1291 | H225: B
A226: Кромочные материалы | B226: Кромка ПВХ Китай | D226: 19*1,5мм ПВХ Алюминий AN | E226: Кромочные материалы | F226: Кромка ПВХ Китай | G226: 49.389295 | H226: B
... A262: Кромочные материалы | B262: Кромка ПВХ Китай | D262: 19*1,5мм ПВХ Дуб честерфилд AN | E262: Кромочные материалы | F262: Кромка ПВХ Китай | G262: 51.0748 | H262: C
A263: Кромочные материалы | B263: Кромка ПВХ Китай | C263: 36*1,5мм ПВХ | E263: Кромочные материалы | F263: Кромка ПВХ Китай | G263: #N/A | H263: C
A264: Кромочные материалы | B264: Кромка ПВХ Китай | D264: 36*1,5мм ПВХ Белый AN | E264: Кромочные материалы | F264: Кромка ПВХ Китай | G264: 68.679877 | H264: A
A265: Кромочные материалы | B265: Кромка ПВХ Китай | D265: 36*1,5мм ПВХ Дуб Вотан AN | E265: Кромочные материалы | F265: Кромка ПВХ Китай | G265: 82.057037 | H265: B
A266: Кромочные материалы | B266: Кромка ПВХ Китай | D266: 36*1,5мм ПВХ Дуб Сонома AN | E266: Кромочные материалы | F266: Кромка ПВХ Китай | G266: 89.909067 | H266: B
A267: Кромочные материалы | B267: Кромка ПВХ Китай | D267: 36*1,5мм ПВХ Ясень шимо светлый AN | E267: Кромочные материалы | F267: Кромка ПВХ Китай | G267: 92.001398 | H267: B
A268: Кромочные материалы | B268: Кромка ПВХ Китай | D268: 36*1,5мм ПВХ Белый SJ | E268: Кромочные материалы | F268: Кромка ПВХ Китай | G268: 62.673169 | H268: B
A269: Кромочные материалы | B269: Кромка ПВХ Китай | D269: 36*1,5мм ПВХ Черный AN | E269: Кромочные материалы | F269: Кромка ПВХ Китай | G269: 82.680723 | H269: B
A270: Кромочные материалы | B270: Кромка ПВХ Китай | D270: 36*1,5мм ПВХ Дуб Вотан SJ | E270: Кромочные материалы | F270: Кромка ПВХ Китай | G270: 74.832637 | H270: B
A271: Кромочные материалы | B271: Кромка ПВХ Китай | D271: 36*1,5мм ПВХ Серый AN | E271: Кромочные материалы | F271: Кромка ПВХ Китай | G271: 76.458278 | H271: B
A272: Кромочные материалы | B272: Кромка ПВХ Китай | D272: 36*1,5мм ПВХ Тэффи AN | E272: Кромочные материалы | F272: Кромка ПВХ Китай | G272: 76.480508 | H272: B
A273: Кромочные материалы | B273: Кромка ПВХ Китай | D273: 36*1,5мм ПВХ Антрацит AN | E273: Кромочные материалы | F273: Кромка ПВХ Китай | G273: 79.237117 | H273: B
A274: Кромочные материалы | B274: Кромка ПВХ Китай | D274: 36*1,5мм ПВХ Белый гладкий AN | E274: Кромочные материалы | F274: Кромка ПВХ Китай | G274: 79.83502 | H274: B
A275: Кромочные материалы | B275: Кромка ПВХ Китай | D275: 36*1,5мм ПВХ Гикори Джексон светлый AN | E275: Кромочные материалы | F275: Кромка ПВХ Китай | G275: 83.517702 | H275: B
... A355: Кромочные материалы | B355: Кромка ПВХ Китай | D355: 36*1,5мм ПВХ Серенити SJ | E355: Кромочные материалы | F355: Кромка ПВХ Китай | G355: 65.7 | H355: C
A356: Кромочные материалы | B356: Кромка ПВХ Китай | C356: 19*1,0мм ПВХ | E356: Кромочные материалы | F356: Кромка ПВХ Китай | G356: #N/A | H356: C
A357: Кромочные материалы | B357: Кромка ПВХ Китай | D357: 19*1мм ПВХ Дуб Вотан AN | E357: Кромочные материалы | F357: Кромка ПВХ Китай | G357: 33.781798 | H357: A
A358: Кромочные материалы | B358: Кромка ПВХ Китай | D358: 19*1мм ПВХ Белый AN | E358: Кромочные материалы | F358: Кромка ПВХ Китай | G358: 24.110025 | H358: A
A359: Кромочные материалы | B359: Кромка ПВХ Китай | D359: 19*1мм ПВХ Белый (Гладкий) AN | E359: Кромочные материалы | F359: Кромка ПВХ Китай | G359: 26.386865 | H359: A
A360: Кромочные материалы | B360: Кромка ПВХ Китай | D360: 19*1мм ПВХ Дуб сонома AN | E360: Кромочные материалы | F360: Кромка ПВХ Китай | G360: 32.206972 | H360: A
A361: Кромочные материалы | B361: Кромка ПВХ Китай | D361: 19*1мм ПВХ Имбирь AN | E361: Кромочные материалы | F361: Кромка ПВХ Китай | G361: 25.891529 | H361: B
A362: Кромочные материалы | B362: Кромка ПВХ Китай | D362: 19*1мм ПВХ Ясень шимо светлый AN | E362: Кромочные материалы | F362: Кромка ПВХ Китай | G362: 32.666281 | H362: B
A363: Кромочные материалы | B363: Кромка ПВХ Китай | D363: 19*1мм ПВХ Серый AN | E363: Кромочные материалы | F363: Кромка ПВХ Китай | G363: 26.25701 | H363: B
A364: Кромочные материалы | B364: Кромка ПВХ Китай | D364: 19*1мм ПВХ Выбеленное дерево AN | E364: Кромочные материалы | F364: Кромка ПВХ Китай | G364: 32.292085 | H364: B
A365: Кромочные материалы | B365: Кромка ПВХ Китай | D365: 19*1мм ПВХ Анкор белый AN | E365: Кромочные материалы | F365: Кромка ПВХ Китай | G365: 32.152758 | H365: B
A366: Кромочные материалы | B366: Кромка ПВХ Китай | D366: 19*1мм ПВХ Черный AN | E366: Кромочные материалы | F366: Кромка ПВХ Китай | G366: 26.239936 | H366: B
A367: Кромочные материалы | B367: Кромка ПВХ Китай | D367: 19*1мм ПВХ Антрацит AN | E367: Кромочные материалы | F367: Кромка ПВХ Китай | G367: 24.385717 | H367: C
A368: Кромочные материалы | B368: Кромка ПВХ Китай | D368: 19*1мм ПВХ Анкор светлый AN | E368: Кромочные материалы | F368: Кромка ПВХ Китай | G368: 32.150823 | H368: C
... A383: Кромочные материалы | B383: Кромка ПВХ Китай | D383: 19*1мм ПВХ Серый SJ | E383: Кромочные материалы | F383: Кромка ПВХ Китай | G383: 22.6 | H383: B
A384: Кромочные материалы | B384: Кромка ПВХ Китай | C384: 45*1,0мм ПВХ | E384: Кромочные материалы | F384: Кромка ПВХ Китай | G384: #N/A | H384: C
A385: Кромочные материалы | B385: Кромка ПВХ Китай | D385: 45*1мм ПВХ Белый AN | E385: Кромочные материалы | F385: Кромка ПВХ Китай | G385: 66.336444 | H385: B
A386: Кромочные материалы | B386: Кромка ПВХ Китай | D386: 45*1мм ПВХ Дуб вотан AN | E386: Кромочные материалы | F386: Кромка ПВХ Китай | G386: 84.761497 | H386: C
A387: Кромочные материалы | B387: Кромка ПВХ Китай | D387: 45*1мм ПВХ Дуб сонома AN | E387: Кромочные материалы | F387: Кромка ПВХ Китай | G387: 88.835128 | H387: C
A388: Кромочные материалы | B388: Кромка ПВХ Китай | D388: 45*1мм ПВХ Черный AN | E388: Кромочные материалы | F388: Кромка ПВХ Китай | G388: 69.492204 | H388: C
A389: Кромочные материалы | B389: Кромка ПВХ Китай | D389: 45*1мм ПВХ Белый глянец AN | E389: Кромочные материалы | F389: Кромка ПВХ Китай | G389: 83.80815 | H389: C
A390: Кромочные материалы | B390: Кромка ПВХ Китай | D390: 45*1мм ПВХ Черный глянец AN | E390: Кромочные материалы | F390: Кромка ПВХ Китай | G390: 68.198052 | H390: C
A391: Кромочные материалы | B391: Кромка ПВХ Китай | D391: 45*1мм ПВХ Серый AN | E391: Кромочные материалы | F391: Кромка ПВХ Китай | G391: 80.906161 | H391: C
A392: Кромочные материалы | B392: Кромка ПВХ Китай | D392: 45*1мм ПВХ Бежевый AN | E392: Кромочные материалы | F392: Кромка ПВХ Китай | G392: 65.92895 | H392: C
A393: Кромочные материалы | B393: Кромка ПВХ Китай | D393: 45*1мм ПВХ Дуб сонома SJ | E393: Кромочные материалы | F393: Кромка ПВХ Китай | G393: 67.436097 | H393: C
A394: Кромочные материалы | B394: Кромка ПВХ Китай | D394: 45*1мм ПВХ Алюминий AN | E394: Кромочные материалы | F394: Кромка ПВХ Китай | G394: 102.16399 | H394: C
A395: Кромочные материалы | B395: Кромка ПВХ Китай | C395: 19*0,4мм ПВХ | E395: Кромочные материалы | F395: Кромка ПВХ Китай | G395: #N/A | H395: C
A396: Кромочные материалы | B396: Кромка ПВХ Китай | D396: 19*0,4мм ПВХ Белый AN | E396: Кромочные материалы | F396: Кромка ПВХ Китай | G396: 11.854472 | H396: A
A397: Кромочные материалы | B397: Кромка ПВХ Китай | D397: 19*0,4мм ПВХ Белый SJ | E397: Кромочные материалы | F397: Кромка ПВХ Китай | G397: 9.3904509 | H397: A
A398: Кромочные материалы | B398: Кромка ПВХ Китай | D398: 19*0,4мм ПВХ Дуб сонома AN | E398: Кромочные материалы | F398: Кромка ПВХ Китай | G398: 18.910628 | H398: B
A399: Кромочные материалы | B399: Кромка ПВХ Китай | D399: 19*0,4мм ПВХ Серый AN | E399: Кромочные материалы | F399: Кромка ПВХ Китай | G399: 11.9939 | H399: A
A400: Кромочные материалы | B400: Кромка ПВХ Китай | D400: 19*0,4мм ПВХ Черный SJ | E400: Кромочные материалы | F400: Кромка ПВХ Китай | G400: 9.7 | H400: B
A401: Кромочные материалы | B401: Кромка ПВХ Китай | D401: 19*0,4мм ПВХ Дуб Вотан AN | E401: Кромочные материалы | F401: Кромка ПВХ Китай | G401: 18.106667 | H401: C
A402: Кромочные материалы | B402: Кромка ПВХ Китай | D402: 19*0,4мм ПВХ Крем AN | E402: Кромочные материалы | F402: Кромка ПВХ Китай | G402: 10.610027 | H402: C
A403: Кромочные материалы | B403: Кромка ПВХ Китай | D403: 19*0,4мм ПВХ Венге AN | E403: Кромочные материалы | F403: Кромка ПВХ Китай | G403: 17.215201 | H403: C
A404: Кромочные материалы | B404: Кромка ПВХ Китай | D404: 19*0,4мм ПВХ Антрацит AN | E404: Кромочные материалы | F404: Кромка ПВХ Китай | G404: 11.281404 | H404: C
A405: Кромочные материалы | B405: Кромка ПВХ Китай | D405: 19*0,4мм ПВХ Ночь экко AN | E405: Кромочные материалы | F405: Кромка ПВХ Китай | G405: 17.22025 | H405: C
A406: Кромочные материалы | B406: Кромка ПВХ Китай | D406: 19*0,4мм ПВХ Дуб млечный AN | E406: Кромочные материалы | F406: Кромка ПВХ Китай | G406: 16.26 | H406: C
A407: Кромочные материалы | B407: Кромка ПВХ Китай | D407: 19*0,4мм ПВХ Ясень шимо светлый AN | E407: Кромочные материалы | F407: Кромка ПВХ Китай | G407: 18.89 | H407: C
... A410: Кромочные материалы | B410: Кромка ПВХ Китай | D410: 19*0,4мм ПВХ Выбеленное дерево AN | E410: Кромочные материалы | F410: Кромка ПВХ Китай | G410: 17.743178 | H410: C
A411: Кромочные материалы | B411: Кромка ПВХ Китай | C411: 22*1,0мм ПВХ | E411: Кромочные материалы | F411: Кромка ПВХ Китай | G411: #N/A | H411: C
A412: Кромочные материалы | B412: Кромка ПВХ Китай | D412: 22*1мм ПВХ Белый глянец AN | E412: Кромочные материалы | F412: Кромка ПВХ Китай | G412: 41.931595 | H412: B
A413: Кромочные материалы | B413: Кромка ПВХ Китай | C413: 45*1,5мм ПВХ | E413: Кромочные материалы | F413: Кромка ПВХ Китай | G413: #N/A | H413: C
A414: Кромочные материалы | B414: Кромка ПВХ Китай | D414: 45*1,5мм ПВХ Дуб вотан AN | E414: Кромочные материалы | F414: Кромка ПВХ Китай | G414: 119.26512 | H414: C
A415: Кромочные материалы | B415: Кромка ПВХ Китай | D415: 45*1,5мм ПВХ Белый SJ | E415: Кромочные материалы | F415: Кромка ПВХ Китай | G415: 81.654416 | H415: C
A416: Кромочные материалы | B416: Кромка ПВХ Китай | D416: 45*1,5мм ПВХ Черный AN | E416: Кромочные материалы | F416: Кромка ПВХ Китай | G416: 102.92517 | H416: C
A417: Кромочные материалы | B417: Кромка ПВХ Китай | D417: 45*1,5мм ПВХ Белый AN | E417: Кромочные материалы | F417: Кромка ПВХ Китай | G417: 102.59932 | H417: C
A418: Кромочные материалы | B418: Кромка ПВХ Китай | D418: 45*1,5мм ПВХ Серый AN | E418: Кромочные материалы | F418: Кромка ПВХ Китай | G418: 100.275 | H418: C
A419: Кромочные материалы | B419: Кромка ПВХ Китай | D419: 45*1,5мм ПВХ Дуб сонома AN | E419: Кромочные материалы | F419: Кромка ПВХ Китай | G419: 117.10608 | H419: C
A420: Кромочные материалы | B420: Кромка ПВХ Китай | D420: 45*1,5мм ПВХ Алюминий AN | E420: Кромочные материалы | F420: Кромка ПВХ Китай | G420: 126.47417 | H420: C
A421: Кромочные материалы | B421: Кромка ПВХ Китай | C421: 36*1,0мм ПВХ | E421: Кромочные материалы | F421: Кромка ПВХ Китай | G421: #N/A | H421: C
A422: Кромочные материалы | B422: Кромка ПВХ Китай | D422: 36*1мм ПВХ Дуб Вотан SJ | E422: Кромочные материалы | F422: Кромка ПВХ Китай | G422: 59 | H422: C
A423: Кромочные материалы | B423: Кромка ПВХ Китай | D423: 36*1мм ПВХ Белый SJ | E423: Кромочные материалы | F423: Кромка ПВХ Китай | G423: 45.604167 | H423: C
A424: Кромочные материалы | B424: Кромка ПВХ Китай | D424: 36*1мм ПВХ Дуб Сонома SJ | E424: Кромочные материалы | F424: Кромка ПВХ Китай | G424: 59.54249 | H424: C
...

Sheet ОСТАТКИ
A1: Номенклатура | D1: 4 Склад фурнитуры АЗМ Шымкент "Овощная база" | E1: 6 Склад фурнитуры "Овощная база" Магазин | G1: АО Склад Фурнитура TRADE | I1: База Склад Фурнитура Комплект | J1: Барыс Склад Фурнитура TRADE | K1: Казыбаева Склад Фурнитура TRADE | L1: Магазин фурнитуры | M1: склад фурнитура № 1 | N1: ТД Казыбаева ФУРНИТУРА магазин | O1: Итого | T1: 4 Склад фурнитуры АЗМ Шымкент "Овощная база" | U1: 6 Склад фурнитуры "Овощная база" Магазин | W1: АО Склад Фурнитура TRADE | Y1: База Склад Фурнитура Комплект | Z1: Барыс Склад Фурнитура TRADE | AA1: Казыбаева Склад Фурнитура TRADE | AB1: Магазин фурнитуры | AC1: склад фурнитура № 1 | AD1: ТД Казыбаева ФУРНИТУРА магазин
A3: =A1=A5 -> TRUE | B3: =B1=B5 -> TRUE | C3: =C1=C5 -> TRUE | D3: =D1=D5 -> TRUE | E3: =E1=E5 -> TRUE | F3: =F1=F5 -> TRUE | G3: =G1=G5 -> TRUE | H3: =H1=H5 -> TRUE | ... O3: =O1=O5 -> TRUE | T3: =T1=T5 -> TRUE | U3: =U1=U5 -> TRUE | V3: =V1=V5 -> TRUE | W3: =W1=W5 -> TRUE | X3: =X1=X5 -> TRUE | Y3: =Y1=Y5 -> TRUE | Z3: =Z1=Z5 -> TRUE | AA3: =AA1=AA5 -> TRUE | ... AD3: =AD1=AD5 -> TRUE
T4: сумм остатков
A5: Номенклатура | D5: 4 Склад фурнитуры АЗМ Шымкент "Овощная база" | E5: 6 Склад фурнитуры "Овощная база" Магазин | G5: АО Склад Фурнитура TRADE | I5: База Склад Фурнитура Комплект | J5: Барыс Склад Фурнитура TRADE | K5: Казыбаева Склад Фурнитура TRADE | L5: Магазин фурнитуры | M5: склад фурнитура № 1 | N5: ТД Казыбаева ФУРНИТУРА магазин | O5: Итого | T5: 4 Склад фурнитуры АЗМ Шымкент "Овощная база" | U5: 6 Склад фурнитуры "Овощная база" Магазин | W5: АО Склад Фурнитура TRADE | Y5: База Склад Фурнитура Комплект | Z5: Барыс Склад Фурнитура TRADE | AA5: Казыбаева Склад Фурнитура TRADE | AB5: Магазин фурнитуры | AC5: склад фурнитура № 1 | AD5: ТД Казыбаева ФУРНИТУРА магазин | AE5: тотал ост по СС
D6: Количество | E6: Количество | G6: Количество | I6: Количество | J6: Количество | K6: Количество | L6: Количество | M6: Количество | N6: Количество | O6: Количество | T6: Количество | U6: Количество | W6: Количество | Y6: Количество | Z6: Количество | AA6: Количество | AB6: Количество | AC6: Количество | AD6: Количество
D7: Конечный остаток | E7: Конечный остаток | G7: Конечный остаток | I7: Конечный остаток | J7: Конечный остаток | K7: Конечный остаток | L7: Конечный остаток | M7: Конечный остаток | N7: Конечный остаток | O7: Конечный остаток | P7: КАТ | Q7: КАТ-2 | R7: ЦЕНА | S7: ABC | T7: Конечный остаток | U7: Конечный остаток | W7: Конечный остаток | Y7: Конечный остаток | Z7: Конечный остаток | AA7: Конечный остаток | AB7: Конечный остаток | AC7: Конечный остаток | AD7: Конечный остаток
A8: 1,5*25мм Венге цаво 3354 PR | J8: 180 | K8: 300 | O8: 480 | P8: =VLOOKUP(A8,'ИЗ ОСНОВЫ НОМЕНКЛАТУР'!D:E,2,0) -> Кромочные материалы | Q8: =VLOOKUP(A8,'ИЗ ОСНОВЫ НОМЕНКЛАТУР'!D:F,3,0) -> Кромка ПВХ Россия | R8: =VLOOKUP(A:A,'ИЗ ОСНОВЫ НОМЕНКЛАТУР'!D:G,4,0) -> 72.831 | S8: =VLOOKUP(A:A,'ИЗ ОСНОВЫ НОМЕНКЛАТУР'!D:H,5,0) -> C | T8: =$R8*D8 -> 0 | U8: =$R8*E8 -> 0 | V8: =$R8*F8 -> 0 | W8: =$R8*G8 -> 0 | X8: =$R8*H8 -> 0 | Y8: =$R8*I8 -> 0 | Z8: =$R8*J8 -> 13109.58 | AA8: =$R8*K8 -> 21849.3 | ... AD8: =$R8*N8 -> 0 | AE8: =SUM(T8:AD8) -> 34958.88
A9: 1,5*25мм Дуб белый Craft К001 | J9: 168 | O9: 168 | P9: =VLOOKUP(A9,'ИЗ ОСНОВЫ НОМЕНКЛАТУР'!D:E,2,0) -> Кромочные материалы | Q9: =VLOOKUP(A9,'ИЗ ОСНОВЫ НОМЕНКЛАТУР'!D:F,3,0) -> Кромка ПВХ Россия | R9: =VLOOKUP(A:A,'ИЗ ОСНОВЫ НОМЕНКЛАТУР'!D:G,4,0) -> 72.428571 | S9: =VLOOKUP(A:A,'ИЗ ОСНОВЫ НОМЕНКЛАТУР'!D:H,5,0) -> C | T9: =$R9*D9 -> 0 | U9: =$R9*E9 -> 0 | V9: =$R9*F9 -> 0 | W9: =$R9*G9 -> 0 | X9: =$R9*H9 -> 0 | Y9: =$R9*I9 -> 0 | Z9: =$R9*J9 -> 12168 | AA9: =$R9*K9 -> 0 | ... AD9: =$R9*N9 -> 0 | AE9: =SUM(T9:AD9) -> 12168
A10: 1,5*25мм Дуб Венге 6495 PR | J10: 300 | K10: 600 | O10: 900 | P10: =VLOOKUP(A10,'ИЗ ОСНОВЫ НОМЕНКЛАТУР'!D:E,2,0) -> Кромочные материалы | Q10: =VLOOKUP(A10,'ИЗ ОСНОВЫ НОМЕНКЛАТУР'!D:F,3,0) -> Кромка ПВХ Россия | R10: =VLOOKUP(A:A,'ИЗ ОСНОВЫ НОМЕНКЛАТУР'!D:G,4,0) -> 72.634444 | S10: =VLOOKUP(A:A,'ИЗ ОСНОВЫ НОМЕНКЛАТУР'!D:H,5,0) -> C | T10: =$R10*D10 -> 0 | U10: =$R10*E10 -> 0 | V10: =$R10*F10 -> 0 | W10: =$R10*G10 -> 0 | X10: =$R10*H10 -> 0 | Y10: =$R10*I10 -> 0 | Z10: =$R10*J10 -> 21790.333 | AA10: =$R10*K10 -> 43580.667 | ... AD10: =$R10*N10 -> 0 | AE10: =SUM(T10:AD10) -> 65371
A11: 1,5*25мм Дуб золотой Craft К003 PW | J11: 300 | O11: 300 | P11: =VLOOKUP(A11,'ИЗ ОСНОВЫ НОМЕНКЛАТУР'!D:E,2,0) -> Кромочные материалы | Q11: =VLOOKUP(A11,'ИЗ ОСНОВЫ НОМЕНКЛАТУР'!D:F,3,0) -> Кромка ПВХ Россия | R11: =VLOOKUP(A:A,'ИЗ ОСНОВЫ НОМЕНКЛАТУР'!D:G,4,0) -> 83.213333 | S11: =VLOOKUP(A:A,'ИЗ ОСНОВЫ НОМЕНКЛАТУР'!D:H,5,0) -> C | T11: =$R11*D11 -> 0 | U11: =$R11*E11 -> 0 | V11: =$R11*F11 -> 0 | W11: =$R11*G11 -> 0 | X11: =$R11*H11 -> 0 | Y11: =$R11*I11 -> 0 | Z11: =$R11*J11 -> 24964 | AA11: =$R11*K11 -> 0 | ... AD11: =$R11*N11 -> 0 | AE11: =SUM(T11:AD11) -> 24964
A12: 1,5*25мм Дуб молочный 8622 PR | K12: 400 | O12: 400 | P12: =VLOOKUP(A12,'ИЗ ОСНОВЫ НОМЕНКЛАТУР'!D:E,2,0) -> Кромочные материалы | Q12: =VLOOKUP(A12,'ИЗ ОСНОВЫ НОМЕНКЛАТУР'!D:F,3,0) -> Кромка ПВХ Россия | R12: =VLOOKUP(A:A,'ИЗ ОСНОВЫ НОМЕНКЛАТУР'!D:G,4,0) -> 83.2125 | S12: =VLOOKUP(A:A,'ИЗ ОСНОВЫ НОМЕНКЛАТУР'!D:H,5,0) -> C | T12: =$R12*D12 -> 0 | U12: =$R12*E12 -> 0 | V12: =$R12*F12 -> 0 | W12: =$R12*G12 -> 0 | X12: =$R12*H12 -> 0 | Y12: =$R12*I12 -> 0 | Z12: =$R12*J12 -> 0 | AA12: =$R12*K12 -> 33285 | ... AD12: =$R12*N12 -> 0 | AE12: =SUM(T12:AD12) -> 33285
A13: 1,5*25мм Дуб Сонома светлый 3660 PR | J13: 300 | K13: 600 | O13: 900 | P13: =VLOOKUP(A13,'ИЗ ОСНОВЫ НОМЕНКЛАТУР'!D:E,2,0) -> Кромочные материалы | Q13: =VLOOKUP(A13,'ИЗ ОСНОВЫ НОМЕНКЛАТУР'!D:F,3,0) -> Кромка ПВХ Россия | R13: =VLOOKUP(A:A,'ИЗ ОСНОВЫ НОМЕНКЛАТУР'!D:G,4,0) -> 83.212222 | S13: =VLOOKUP(A:A,'ИЗ ОСНОВЫ НОМЕНКЛАТУР'!D:H,5,0) -> C | T13: =$R13*D13 -> 0 | U13: =$R13*E13 -> 0 | V13: =$R13*F13 -> 0 | W13: =$R13*G13 -> 0 | X13: =$R13*H13 -> 0 | Y13: =$R13*I13 -> 0 | Z13: =$R13*J13 -> 24963.667 | AA13: =$R13*K13 -> 49927.333 | ... AD13: =$R13*N13 -> 0 | AE13: =SUM(T13:AD13) -> 74891
A14: 1,5*25мм Ясень анкор светлый 4780 PR | J14: 200 | O14: 200 | P14: =VLOOKUP(A14,'ИЗ ОСНОВЫ НОМЕНКЛАТУР'!D:E,2,0) -> Кромочные материалы | Q14: =VLOOKUP(A14,'ИЗ ОСНОВЫ НОМЕНКЛАТУР'!D:F,3,0) -> Кромка ПВХ Россия | R14: =VLOOKUP(A:A,'ИЗ ОСНОВЫ НОМЕНКЛАТУР'!D:G,4,0) -> 72.43 | S14: =VLOOKUP(A:A,'ИЗ ОСНОВЫ НОМЕНКЛАТУР'!D:H,5,0) -> C | T14: =$R14*D14 -> 0 | U14: =$R14*E14 -> 0 | V14: =$R14*F14 -> 0 | W14: =$R14*G14 -> 0 | X14: =$R14*H14 -> 0 | Y14: =$R14*I14 -> 0 | Z14: =$R14*J14 -> 14486 | AA14: =$R14*K14 -> 0 | ... AD14: =$R14*N14 -> 0 | AE14: =SUM(T14:AD14) -> 14486
A15: 1,5*25мм Ясень Анкор темный 4779 PR | K15: 600 | O15: 600 | P15: =VLOOKUP(A15,'ИЗ ОСНОВЫ НОМЕНКЛАТУР'!D:E,2,0) -> Кромочные материалы | Q15: =VLOOKUP(A15,'ИЗ ОСНОВЫ НОМЕНКЛАТУР'!D:F,3,0) -> Кромка ПВХ Россия | R15: =VLOOKUP(A:A,'ИЗ ОСНОВЫ НОМЕНКЛАТУР'!D:G,4,0) -> 69.646667 | S15: =VLOOKUP(A:A,'ИЗ ОСНОВЫ НОМЕНКЛАТУР'!D:H,5,0) -> C | T15: =$R15*D15 -> 0 | U15: =$R15*E15 -> 0 | V15: =$R15*F15 -> 0 | W15: =$R15*G15 -> 0 | X15: =$R15*H15 -> 0 | Y15: =$R15*I15 -> 0 | Z15: =$R15*J15 -> 0 | AA15: =$R15*K15 -> 41788 | ... AD15: =$R15*N15 -> 0 | AE15: =SUM(T15:AD15) -> 41788
A16: 19*0,4мм Atellier Темный 4299 SU | J16: 3000 | K16: 3800 | O16: 6800 | P16: =VLOOKUP(A16,'ИЗ ОСНОВЫ НОМЕНКЛАТУР'!D:E,2,0) -> Кромочные материалы | Q16: =VLOOKUP(A16,'ИЗ ОСНОВЫ НОМЕНКЛАТУР'!D:F,3,0) -> Кромка ПВХ Россия | R16: =VLOOKUP(A:A,'ИЗ ОСНОВЫ НОМЕНКЛАТУР'!D:G,4,0) -> 20.351 | S16: =VLOOKUP(A:A,'ИЗ ОСНОВЫ НОМЕНКЛАТУР'!D:H,5,0) -> C | T16: =$R16*D16 -> 0 | U16: =$R16*E16 -> 0 | V16: =$R16*F16 -> 0 | W16: =$R16*G16 -> 0 | X16: =$R16*H16 -> 0 | Y16: =$R16*I16 -> 0 | Z16: =$R16*J16 -> 61053 | AA16: =$R16*K16 -> 77333.8 | ... AD16: =$R16*N16 -> 0 | AE16: =SUM(T16:AD16) -> 138386.8
A17: 19*0,4мм Алюминий ПВХ MS | N17: 365 | O17: 365 | P17: =VLOOKUP(A17,'ИЗ ОСНОВЫ НОМЕНКЛАТУР'!D:E,2,0) -> Кромочные материалы | Q17: =VLOOKUP(A17,'ИЗ ОСНОВЫ НОМЕНКЛАТУР'!D:F,3,0) -> Распродажа кромка | R17: =VLOOKUP(A:A,'ИЗ ОСНОВЫ НОМЕНКЛАТУР'!D:G,4,0) -> 8.5061321 | S17: =VLOOKUP(A:A,'ИЗ ОСНОВЫ НОМЕНКЛАТУР'!D:H,5,0) -> C | T17: =$R17*D17 -> 0 | U17: =$R17*E17 -> 0 | V17: =$R17*F17 -> 0 | W17: =$R17*G17 -> 0 | X17: =$R17*H17 -> 0 | Y17: =$R17*I17 -> 0 | Z17: =$R17*J17 -> 0 | AA17: =$R17*K17 -> 0 | ... AD17: =$R17*N17 -> 3104.7382 | AE17: =SUM(T17:AD17) -> 3104.7382
A18: 19*0,4мм Артвуд светлый К083 SN | J18: 1800 | K18: 5000 | O18: 6800 | P18: =VLOOKUP(A18,'ИЗ ОСНОВЫ НОМЕНКЛАТУР'!D:E,2,0) -> Кромочные материалы | Q18: =VLOOKUP(A18,'ИЗ ОСНОВЫ НОМЕНКЛАТУР'!D:F,3,0) -> Кромка ПВХ Россия | R18: =VLOOKUP(A:A,'ИЗ ОСНОВЫ НОМЕНКЛАТУР'!D:G,4,0) -> 20.47785 | S18: =VLOOKUP(A:A,'ИЗ ОСНОВЫ НОМЕНКЛАТУР'!D:H,5,0) -> C | T18: =$R18*D18 -> 0 | U18: =$R18*E18 -> 0 | V18: =$R18*F18 -> 0 | W18: =$R18*G18 -> 0 | X18: =$R18*H18 -> 0 | Y18: =$R18*I18 -> 0 | Z18: =$R18*J18 -> 36860.13 | AA18: =$R18*K18 -> 102389.25 | ... AD18: =$R18*N18 -> 0 | AE18: =SUM(T18:AD18) -> 139249.38
A19: 19*0,4мм Артвуд темный К084 SN | J19: 600 | K19: 4000 | O19: 4600 | P19: =VLOOKUP(A19,'ИЗ ОСНОВЫ НОМЕНКЛАТУР'!D:E,2,0) -> Кромочные материалы | Q19: =VLOOKUP(A19,'ИЗ ОСНОВЫ НОМЕНКЛАТУР'!D:F,3,0) -> Кромка ПВХ Россия | R19: =VLOOKUP(A:A,'ИЗ ОСНОВЫ НОМЕНКЛАТУР'!D:G,4,0) -> 20.43345 | S19: =VLOOKUP(A:A,'ИЗ ОСНОВЫ НОМЕНКЛАТУР'!D:H,5,0) -> C | T19: =$R19*D19 -> 0 | U19: =$R19*E19 -> 0 | V19: =$R19*F19 -> 0 | W19: =$R19*G19 -> 0 | X19: =$R19*H19 -> 0 | Y19: =$R19*I19 -> 0 | Z19: =$R19*J19 -> 12260.07 | AA19: =$R19*K19 -> 81733.8 | ... AD19: =$R19*N19 -> 0 | AE19: =SUM(T19:AD19) -> 93993.87
A20: 19*0,4мм Зеленый Лайм 5519 BS | J20: 5400 | O20: 5400 | P20: =VLOOKUP(A20,'ИЗ ОСНОВЫ НОМЕНКЛАТУР'!D:E,2,0) -> Кромочные материалы | Q20: =VLOOKUP(A20,'ИЗ ОСНОВЫ НОМЕНКЛАТУР'!D:F,3,0) -> Кромка ПВХ Россия | R20: =VLOOKUP(A:A,'ИЗ ОСНОВЫ НОМЕНКЛАТУР'!D:G,4,0) -> 12.557 | S20: =VLOOKUP(A:A,'ИЗ ОСНОВЫ НОМЕНКЛАТУР'!D:H,5,0) -> C | T20: =$R20*D20 -> 0 | U20: =$R20*E20 -> 0 | V20: =$R20*F20 -> 0 | W20: =$R20*G20 -> 0 | X20: =$R20*H20 -> 0 | Y20: =$R20*I20 -> 0 | Z20: =$R20*J20 -> 67807.8 | AA20: =$R20*K20 -> 0 | ... AD20: =$R20*N20 -> 0 | AE20: =SUM(T20:AD20) -> 67807.8
A21: 19*0,4мм Клен Танзау 0375 PR | J21: 2200 | O21: 2200 | P21: =VLOOKUP(A21,'ИЗ ОСНОВЫ НОМЕНКЛАТУР'!D:E,2,0) -> Кромочные материалы | Q21: =VLOOKUP(A21,'ИЗ ОСНОВЫ НОМЕНКЛАТУР'!D:F,3,0) -> Кромка ПВХ Россия | R21: =VLOOKUP(A:A,'ИЗ ОСНОВЫ НОМЕНКЛАТУР'!D:G,4,0) -> 17.753 | S21: =VLOOKUP(A:A,'ИЗ ОСНОВЫ НОМЕНКЛАТУР'!D:H,5,0) -> C | T21: =$R21*D21 -> 0 | U21: =$R21*E21 -> 0 | V21: =$R21*F21 -> 0 | W21: =$R21*G21 -> 0 | X21: =$R21*H21 -> 0 | Y21: =$R21*I21 -> 0 | Z21: =$R21*J21 -> 39056.6 | AA21: =$R21*K21 -> 0 | ... AD21: =$R21*N21 -> 0 | AE21: =SUM(T21:AD21) -> 39056.6
A22: 19*0,4мм Королевский Синий 0125 PE | J22: 4600 | O22: 4600 | P22: =VLOOKUP(A22,'ИЗ ОСНОВЫ НОМЕНКЛАТУР'!D:E,2,0) -> Кромочные материалы | Q22: =VLOOKUP(A22,'ИЗ ОСНОВЫ НОМЕНКЛАТУР'!D:F,3,0) -> Кромка ПВХ Россия | R22: =VLOOKUP(A:A,'ИЗ ОСНОВЫ НОМЕНКЛАТУР'!D:G,4,0) -> 14.346957 | S22: =VLOOKUP(A:A,'ИЗ ОСНОВЫ НОМЕНКЛАТУР'!D:H,5,0) -> C | T22: =$R22*D22 -> 0 | U22: =$R22*E22 -> 0 | V22: =$R22*F22 -> 0 | W22: =$R22*G22 -> 0 | X22: =$R22*H22 -> 0 | Y22: =$R22*I22 -> 0 | Z22: =$R22*J22 -> 65996 | AA22: =$R22*K22 -> 0 | ... AD22: =$R22*N22 -> 0 | AE22: =SUM(T22:AD22) -> 65996
A23: 19*0,4мм Красный Чили 7113 PE | K23: 6800 | O23: 6800 | P23: =VLOOKUP(A23,'ИЗ ОСНОВЫ НОМЕНКЛАТУР'!D:E,2,0) -> Кромочные материалы | Q23: =VLOOKUP(A23,'ИЗ ОСНОВЫ НОМЕНКЛАТУР'!D:F,3,0) -> Кромка ПВХ Россия | R23: =VLOOKUP(A:A,'ИЗ ОСНОВЫ НОМЕНКЛАТУР'!D:G,4,0) -> 12.557 | S23: =VLOOKUP(A:A,'ИЗ ОСНОВЫ НОМЕНКЛАТУР'!D:H,5,0) -> C | T23: =$R23*D23 -> 0 | U23: =$R23*E23 -> 0 | V23: =$R23*F23 -> 0 | W23: =$R23*G23 -> 0 | X23: =$R23*H23 -> 0 | Y23: =$R23*I23 -> 0 | Z23: =$R23*J23 -> 0 | AA23: =$R23*K23 -> 85387.6 | ... AD23: =$R23*N23 -> 0 | AE23: =SUM(T23:AD23) -> 85387.6
A24: 19*0,4мм Оранжевый 0132 PE | J24: 3900 | O24: 3900 | P24: =VLOOKUP(A24,'ИЗ ОСНОВЫ НОМЕНКЛАТУР'!D:E,2,0) -> Кромочные материалы | Q24: =VLOOKUP(A24,'ИЗ ОСНОВЫ НОМЕНКЛАТУР'!D:F,3,0) -> Кромка ПВХ Россия | R24: =VLOOKUP(A:A,'ИЗ ОСНОВЫ НОМЕНКЛАТУР'!D:G,4,0) -> 12.557 | S24: =VLOOKUP(A:A,'ИЗ ОСНОВЫ НОМЕНКЛАТУР'!D:H,5,0) -> C | T24: =$R24*D24 -> 0 | U24: =$R24*E24 -> 0 | V24: =$R24*F24 -> 0 | W24: =$R24*G24 -> 0 | X24: =$R24*H24 -> 0 | Y24: =$R24*I24 -> 0 | Z24: =$R24*J24 -> 48972.3 | AA24: =$R24*K24 -> 0 | ... AD24: =$R24*N24 -> 0 | AE24: =SUM(T24:AD24) -> 48972.3
A25: 19*0,4мм Орех Гепланкт 5648 PR | J25: 5800 | K25: 6400 | O25: 12200 | P25: =VLOOKUP(A25,'ИЗ ОСНОВЫ НОМЕНКЛАТУР'!D:E,2,0) -> Кромочные материалы | Q25: =VLOOKUP(A25,'ИЗ ОСНОВЫ НОМЕНКЛАТУР'!D:F,3,0) -> Кромка ПВХ Россия | R25: =VLOOKUP(A:A,'ИЗ ОСНОВЫ НОМЕНКЛАТУР'!D:G,4,0) -> 17.720967 | S25: =VLOOKUP(A:A,'ИЗ ОСНОВЫ НОМЕНКЛАТУР'!D:H,5,0) -> C | T25: =$R25*D25 -> 0 | U25: =$R25*E25 -> 0 | V25: =$R25*F25 -> 0 | W25: =$R25*G25 -> 0 | X25: =$R25*H25 -> 0 | Y25: =$R25*I25 -> 0 | Z25: =$R25*J25 -> 102781.61 | AA25: =$R25*K25 -> 113414.19 | ... AD25: =$R25*N25 -> 0 | AE25: =SUM(T25:AD25) -> 216195.79
A26: 19*0,4мм Орех экко 9459 PR | J26: 4400 | O26: 4400 | P26: =VLOOKUP(A26,'ИЗ ОСНОВЫ НОМЕНКЛАТУР'!D:E,2,0) -> Кромочные материалы | Q26: =VLOOKUP(A26,'ИЗ ОСНОВЫ НОМЕНКЛАТУР'!D:F,3,0) -> Кромка ПВХ Россия | R26: =VLOOKUP(A:A,'ИЗ ОСНОВЫ НОМЕНКЛАТУР'!D:G,4,0) -> 20.283636 | S26: =VLOOKUP(A:A,'ИЗ ОСНОВЫ НОМЕНКЛАТУР'!D:H,5,0) -> C | T26: =$R26*D26 -> 0 | U26: =$R26*E26 -> 0 | V26: =$R26*F26 -> 0 | W26: =$R26*G26 -> 0 | X26: =$R26*H26 -> 0 | Y26: =$R26*I26 -> 0 | Z26: =$R26*J26 -> 89248 | AA26: =$R26*K26 -> 0 | ... AD26: =$R26*N26 -> 0 | AE26: =SUM(T26:AD26) -> 89248
A27: 19*0,4мм ПВХ Антрацит AN | N27: 21 | O27: 21 | P27: =VLOOKUP(A27,'ИЗ ОСНОВЫ НОМЕНКЛАТУР'!D:E,2,0) -> Кромочные материалы | Q27: =VLOOKUP(A27,'ИЗ ОСНОВЫ НОМЕНКЛАТУР'!D:F,3,0) -> Кромка ПВХ Китай | R27: =VLOOKUP(A:A,'ИЗ ОСНОВЫ НОМЕНКЛАТУР'!D:G,4,0) -> 11.281404 | S27: =VLOOKUP(A:A,'ИЗ ОСНОВЫ НОМЕНКЛАТУР'!D:H,5,0) -> C | T27: =$R27*D27 -> 0 | U27: =$R27*E27 -> 0 | V27: =$R27*F27 -> 0 | W27: =$R27*G27 -> 0 | X27: =$R27*H27 -> 0 | Y27: =$R27*I27 -> 0 | Z27: =$R27*J27 -> 0 | AA27: =$R27*K27 -> 0 | ... AD27: =$R27*N27 -> 236.90948 | AE27: =SUM(T27:AD27) -> 236.90948
A28: 19*0,4мм ПВХ Белый AN | N28: 61 | O28: 61 | P28: =VLOOKUP(A28,'ИЗ ОСНОВЫ НОМЕНКЛАТУР'!D:E,2,0) -> Кромочные материалы | Q28: =VLOOKUP(A28,'ИЗ ОСНОВЫ НОМЕНКЛАТУР'!D:F,3,0) -> Кромка ПВХ Китай | R28: =VLOOKUP(A:A,'ИЗ ОСНОВЫ НОМЕНКЛАТУР'!D:G,4,0) -> 11.854472 | S28: =VLOOKUP(A:A,'ИЗ ОСНОВЫ НОМЕНКЛАТУР'!D:H,5,0) -> A | T28: =$R28*D28 -> 0 | U28: =$R28*E28 -> 0 | V28: =$R28*F28 -> 0 | W28: =$R28*G28 -> 0 | X28: =$R28*H28 -> 0 | Y28: =$R28*I28 -> 0 | Z28: =$R28*J28 -> 0 | AA28: =$R28*K28 -> 0 | ... AD28: =$R28*N28 -> 723.12276 | AE28: =SUM(T28:AD28) -> 723.12276
A29: 19*0,4мм ПВХ Белый SD | I29: 284000 | J29: 2000 | K29: 8000 | O29: 294000 | P29: =VLOOKUP(A29,'ИЗ ОСНОВЫ НОМЕНКЛАТУР'!D:E,2,0) -> Кромочные материалы | Q29: =VLOOKUP(A29,'ИЗ ОСНОВЫ НОМЕНКЛАТУР'!D:F,3,0) -> Распродажа кромка | R29: =VLOOKUP(A:A,'ИЗ ОСНОВЫ НОМЕНКЛАТУР'!D:G,4,0) -> 10.5 | S29: =VLOOKUP(A:A,'ИЗ ОСНОВЫ НОМЕНКЛАТУР'!D:H,5,0) -> B | T29: =$R29*D29 -> 0 | U29: =$R29*E29 -> 0 | V29: =$R29*F29 -> 0 | W29: =$R29*G29 -> 0 | X29: =$R29*H29 -> 0 | Y29: =$R29*I29 -> 2982000 | Z29: =$R29*J29 -> 21000 | AA29: =$R29*K29 -> 84000 | ... AD29: =$R29*N29 -> 0 | AE29: =SUM(T29:AD29) -> 3087000
A30: 19*0,4мм ПВХ Белый SJ | J30: 29600 | K30: 13600 | N30: 999 | O30: 44199 | P30: =VLOOKUP(A30,'ИЗ ОСНОВЫ НОМЕНКЛАТУР'!D:E,2,0) -> Кромочные материалы | Q30: =VLOOKUP(A30,'ИЗ ОСНОВЫ НОМЕНКЛАТУР'!D:F,3,0) -> Кромка ПВХ Китай | R30: =VLOOKUP(A:A,'ИЗ ОСНОВЫ НОМЕНКЛАТУР'!D:G,4,0) -> 9.3904509 | S30: =VLOOKUP(A:A,'ИЗ ОСНОВЫ НОМЕНКЛАТУР'!D:H,5,0) -> A | T30: =$R30*D30 -> 0 | U30: =$R30*E30 -> 0 | V30: =$R30*F30 -> 0 | W30: =$R30*G30 -> 0 | X30: =$R30*H30 -> 0 | Y30: =$R30*I30 -> 0 | Z30: =$R30*J30 -> 277957.35 | AA30: =$R30*K30 -> 127710.13 | ... AD30: =$R30*N30 -> 9381.0605 | AE30: =SUM(T30:AD30) -> 415048.54
A31: 19*0,4мм ПВХ Бодега AN | J31: 3800 | O31: 3800 | P31: =VLOOKUP(A31,'ИЗ ОСНОВЫ НОМЕНКЛАТУР'!D:E,2,0) -> Кромочные материалы | Q31: =VLOOKUP(A31,'ИЗ ОСНОВЫ НОМЕНКЛАТУР'!D:F,3,0) -> Кромка ПВХ Китай | R31: =VLOOKUP(A:A,'ИЗ ОСНОВЫ НОМЕНКЛАТУР'!D:G,4,0) -> 19 | S31: =VLOOKUP(A:A,'ИЗ ОСНОВЫ НОМЕНКЛАТУР'!D:H,5,0) -> C | T31: =$R31*D31 -> 0 | U31: =$R31*E31 -> 0 | V31: =$R31*F31 -> 0 | W31: =$R31*G31 -> 0 | X31: =$R31*H31 -> 0 | Y31: =$R31*I31 -> 0 | Z31: =$R31*J31 -> 72200 | AA31: =$R31*K31 -> 0 | ... AD31: =$R31*N31 -> 0 | AE31: =SUM(T31:AD31) -> 72200
A32: 19*0,4мм ПВХ Бодега белая AN | K32: 3600 | N32: 996 | O32: 4596 | P32: =VLOOKUP(A32,'ИЗ ОСНОВЫ НОМЕНКЛАТУР'!D:E,2,0) -> Кромочные материалы | Q32: =VLOOKUP(A32,'ИЗ ОСНОВЫ НОМЕНКЛАТУР'!D:F,3,0) -> Кромка ПВХ Китай | R32: =VLOOKUP(A:A,'ИЗ ОСНОВЫ НОМЕНКЛАТУР'!D:G,4,0) -> 18.18 | S32: =VLOOKUP(A:A,'ИЗ ОСНОВЫ НОМЕНКЛАТУР'!D:H,5,0) -> C | T32: =$R32*D32 -> 0 | U32: =$R32*E32 -> 0 | V32: =$R32*F32 -> 0 | W32: =$R32*G32 -> 0 | X32: =$R32*H32 -> 0 | Y32: =$R32*I32 -> 0 | Z32: =$R32*J32 -> 0 | AA32: =$R32*K32 -> 65448 | ... AD32: =$R32*N32 -> 18107.28 | AE32: =SUM(T32:AD32) -> 83555.28
A33: 19*0,4мм ПВХ Венге AN | I33: 81000 | K33: 1650 | N33: 4491 | O33: 87141 | P33: =VLOOKUP(A33,'ИЗ ОСНОВЫ НОМЕНКЛАТУР'!D:E,2,0) -> Кромочные материалы | Q33: =VLOOKUP(A33,'ИЗ ОСНОВЫ НОМЕНКЛАТУР'!D:F,3,0) -> Кромка ПВХ Китай | R33: =VLOOKUP(A:A,'ИЗ ОСНОВЫ НОМЕНКЛАТУР'!D:G,4,0) -> 17.215201 | S33: =VLOOKUP(A:A,'ИЗ ОСНОВЫ НОМЕНКЛАТУР'!D:H,5,0) -> C | T33: =$R33*D33 -> 0 | U33: =$R33*E33 -> 0 | V33: =$R33*F33 -> 0 | W33: =$R33*G33 -> 0 | X33: =$R33*H33 -> 0 | Y33: =$R33*I33 -> 1394431.3 | Z33: =$R33*J33 -> 0 | AA33: =$R33*K33 -> 28405.082 | ... AD33: =$R33*N33 -> 77313.468 | AE33: =SUM(T33:AD33) -> 1500149.8
A34: 19*0,4мм ПВХ Венге SD | I34: 10000 | O34: 10000 | P34: =VLOOKUP(A34,'ИЗ ОСНОВЫ НОМЕНКЛАТУР'!D:E,2,0) -> Кромочные материалы | Q34: =VLOOKUP(A34,'ИЗ ОСНОВЫ НОМЕНКЛАТУР'!D:F,3,0) -> Распродажа кромка | R34: =VLOOKUP(A:A,'ИЗ ОСНОВЫ НОМЕНКЛАТУР'!D:G,4,0) -> 12.575 | S34: =VLOOKUP(A:A,'ИЗ ОСНОВЫ НОМЕНКЛАТУР'!D:H,5,0) -> C | T34: =$R34*D34 -> 0 | U34: =$R34*E34 -> 0 | V34: =$R34*F34 -> 0 | W34: =$R34*G34 -> 0 | X34: =$R34*H34 -> 0 | Y34: =$R34*I34 -> 125750 | Z34: =$R34*J34 -> 0 | AA34: =$R34*K34 -> 0 | ... AD34: =$R34*N34 -> 0 | AE34: =SUM(T34:AD34) -> 125750
A35: 19*0,4мм ПВХ Выбеленное дерево AN | I35: 46000 | J35: 14180 | K35: 4000 | O35: 64180 | P35: =VLOOKUP(A35,'ИЗ ОСНОВЫ НОМЕНКЛАТУР'!D:E,2,0) -> Кромочные материалы | Q35: =VLOOKUP(A35,'ИЗ ОСНОВЫ НОМЕНКЛАТУР'!D:F,3,0) -> Кромка ПВХ Китай | R35: =VLOOKUP(A:A,'ИЗ ОСНОВЫ НОМЕНКЛАТУР'!D:G,4,0) -> 17.743178 | S35: =VLOOKUP(A:A,'ИЗ ОСНОВЫ НОМЕНКЛАТУР'!D:H,5,0) -> C | T35: =$R35*D35 -> 0 | U35: =$R35*E35 -> 0 | V35: =$R35*F35 -> 0 | W35: =$R35*G35 -> 0 | X35: =$R35*H35 -> 0 | Y35: =$R35*I35 -> 816186.2 | Z35: =$R35*J35 -> 251598.27 | AA35: =$R35*K35 -> 70972.713 | ... AD35: =$R35*N35 -> 0 | AE35: =SUM(T35:AD35) -> 1138757.2
A36: 19*0,4мм ПВХ Выбеленное дерево SD | I36: 60000 | O36: 60000 | P36: =VLOOKUP(A36,'ИЗ ОСНОВЫ НОМЕНКЛАТУР'!D:E,2,0) -> Кромочные материалы | Q36: =VLOOKUP(A36,'ИЗ ОСНОВЫ НОМЕНКЛАТУР'!D:F,3,0) -> Распродажа кромка | R36: =VLOOKUP(A:A,'ИЗ ОСНОВЫ НОМЕНКЛАТУР'!D:G,4,0) -> 12.56255 | S36: =VLOOKUP(A:A,'ИЗ ОСНОВЫ НОМЕНКЛАТУР'!D:H,5,0) -> C | T36: =$R36*D36 -> 0 | U36: =$R36*E36 -> 0 | V36: =$R36*F36 -> 0 | W36: =$R36*G36 -> 0 | X36: =$R36*H36 -> 0 | Y36: =$R36*I36 -> 753753 | Z36: =$R36*J36 -> 0 | AA36: =$R36*K36 -> 0 | ... AD36: =$R36*N36 -> 0 | AE36: =SUM(T36:AD36) -> 753753
A37: 19*0,4мм ПВХ Вяз AN | I37: 17000 | O37: 17000 | P37: =VLOOKUP(A37,'ИЗ ОСНОВЫ НОМЕНКЛАТУР'!D:E,2,0) -> Кромочные материалы | Q37: =VLOOKUP(A37,'ИЗ ОСНОВЫ НОМЕНКЛАТУР'!D:F,3,0) -> Кромка ПВХ Китай | R37: =VLOOKUP(A:A,'ИЗ ОСНОВЫ НОМЕНКЛАТУР'!D:G,4,0) -> 15.540294 | S37: =VLOOKUP(A:A,'ИЗ ОСНОВЫ НОМЕНКЛАТУР'!D:H,5,0) -> C | T37: =$R37*D37 -> 0 | U37: =$R37*E37 -> 0 | V37: =$R37*F37 -> 0 | W37: =$R37*G37 -> 0 | X37: =$R37*H37 -> 0 | Y37: =$R37*I37 -> 264185 | Z37: =$R37*J37 -> 0 | AA37: =$R37*K37 -> 0 | ... AD37: =$R37*N37 -> 0 | AE37: =SUM(T37:AD37) -> 264185
A38: 19*0,4мм ПВХ Дуб Вотан AN | I38: 42000 | J38: 8000 | K38: 3600 | O38: 53600 | P38: =VLOOKUP(A38,'ИЗ ОСНОВЫ НОМЕНКЛАТУР'!D:E,2,0) -> Кромочные материалы | Q38: =VLOOKUP(A38,'ИЗ ОСНОВЫ НОМЕНКЛАТУР'!D:F,3,0) -> Кромка ПВХ Китай | R38: =VLOOKUP(A:A,'ИЗ ОСНОВЫ НОМЕНКЛАТУР'!D:G,4,0) -> 18.106667 | S38: =VLOOKUP(A:A,'ИЗ ОСНОВЫ НОМЕНКЛАТУР'!D:H,5,0) -> C | T38: =$R38*D38 -> 0 | U38: =$R38*E38 -> 0 | V38: =$R38*F38 -> 0 | W38: =$R38*G38 -> 0 | X38: =$R38*H38 -> 0 | Y38: =$R38*I38 -> 760480 | Z38: =$R38*J38 -> 144853.33 | AA38: =$R38*K38 -> 65184 | ... AD38: =$R38*N38 -> 0 | AE38: =SUM(T38:AD38) -> 970517.33
A39: 19*0,4мм ПВХ Дуб млечный AN | I39: 32000 | K39: 5000 | O39: 37000 | P39: =VLOOKUP(A39,'ИЗ ОСНОВЫ НОМЕНКЛАТУР'!D:E,2,0) -> Кромочные материалы | Q39: =VLOOKUP(A39,'ИЗ ОСНОВЫ НОМЕНКЛАТУР'!D:F,3,0) -> Кромка ПВХ Китай | R39: =VLOOKUP(A:A,'ИЗ ОСНОВЫ НОМЕНКЛАТУР'!D:G,4,0) -> 16.26 | S39: =VLOOKUP(A:A,'ИЗ ОСНОВЫ НОМЕНКЛАТУР'!D:H,5,0) -> C | T39: =$R39*D39 -> 0 | U39: =$R39*E39 -> 0 | V39: =$R39*F39 -> 0 | W39: =$R39*G39 -> 0 | X39: =$R39*H39 -> 0 | Y39: =$R39*I39 -> 520320 | Z39: =$R39*J39 -> 0 | AA39: =$R39*K39 -> 81300 | ... AD39: =$R39*N39 -> 0 | AE39: =SUM(T39:AD39) -> 601620
A40: 19*0,4мм ПВХ Дуб сонома AN | I40: 64000 | J40: 10000 | K40: 1600 | N40: 700 | O40: 76300 | P40: =VLOOKUP(A40,'ИЗ ОСНОВЫ НОМЕНКЛАТУР'!D:E,2,0) -> Кромочные материалы | Q40: =VLOOKUP(A40,'ИЗ ОСНОВЫ НОМЕНКЛАТУР'!D:F,3,0) -> Кромка ПВХ Китай | R40: =VLOOKUP(A:A,'ИЗ ОСНОВЫ НОМЕНКЛАТУР'!D:G,4,0) -> 18.910628 | S40: =VLOOKUP(A:A,'ИЗ ОСНОВЫ НОМЕНКЛАТУР'!D:H,5,0) -> B | T40: =$R40*D40 -> 0 | U40: =$R40*E40 -> 0 | V40: =$R40*F40 -> 0 | W40: =$R40*G40 -> 0 | X40: =$R40*H40 -> 0 | Y40: =$R40*I40 -> 1210280.2 | Z40: =$R40*J40 -> 189106.28 | AA40: =$R40*K40 -> 30257.005 | ... AD40: =$R40*N40 -> 13237.44 | AE40: =SUM(T40:AD40) -> 1442880.9
A41: 19*0,4мм ПВХ Красный AN | I41: 12000 | J41: 3600 | K41: 3000 | O41: 18600 | P41: =VLOOKUP(A41,'ИЗ ОСНОВЫ НОМЕНКЛАТУР'!D:E,2,0) -> Кромочные материалы | Q41: =VLOOKUP(A41,'ИЗ ОСНОВЫ НОМЕНКЛАТУР'!D:F,3,0) -> Кромка ПВХ Китай | R41: =VLOOKUP(A:A,'ИЗ ОСНОВЫ НОМЕНКЛАТУР'!D:G,4,0) -> 12.6111 | S41: =VLOOKUP(A:A,'ИЗ ОСНОВЫ НОМЕНКЛАТУР'!D:H,5,0) -> C | T41: =$R41*D41 -> 0 | U41: =$R41*E41 -> 0 | V41: =$R41*F41 -> 0 | W41: =$R41*G41 -> 0 | X41: =$R41*H41 -> 0 | Y41: =$R41*I41 -> 151333.2 | Z41: =$R41*J41 -> 45399.96 | AA41: =$R41*K41 -> 37833.3 | ... AD41: =$R41*N41 -> 0 | AE41: =SUM(T41:AD41) -> 234566.46
A42: 19*0,4мм ПВХ Красный MS | K42: 480 | O42: 480 | P42: =VLOOKUP(A42,'ИЗ ОСНОВЫ НОМЕНКЛАТУР'!D:E,2,0) -> Кромочные материалы | Q42: =VLOOKUP(A42,'ИЗ ОСНОВЫ НОМЕНКЛАТУР'!D:F,3,0) -> Распродажа кромка | R42: =VLOOKUP(A:A,'ИЗ ОСНОВЫ НОМЕНКЛАТУР'!D:G,4,0) -> 7.4342941 | S42: =VLOOKUP(A:A,'ИЗ ОСНОВЫ НОМЕНКЛАТУР'!D:H,5,0) -> C | T42: =$R42*D42 -> 0 | U42: =$R42*E42 -> 0 | V42: =$R42*F42 -> 0 | W42: =$R42*G42 -> 0 | X42: =$R42*H42 -> 0 | Y42: =$R42*I42 -> 0 | Z42: =$R42*J42 -> 0 | AA42: =$R42*K42 -> 3568.4612 | ... AD42: =$R42*N42 -> 0 | AE42: =SUM(T42:AD42) -> 3568.4612
A43: 19*0,4мм ПВХ Крем AN | I43: 118000 | J43: 53 | K43: 5800 | N43: 200 | O43: 124053 | P43: =VLOOKUP(A43,'ИЗ ОСНОВЫ НОМЕНКЛАТУР'!D:E,2,0) -> Кромочные материалы | Q43: =VLOOKUP(A43,'ИЗ ОСНОВЫ НОМЕНКЛАТУР'!D:F,3,0) -> Кромка ПВХ Китай | R43: =VLOOKUP(A:A,'ИЗ ОСНОВЫ НОМЕНКЛАТУР'!D:G,4,0) -> 10.610027 | S43: =VLOOKUP(A:A,'ИЗ ОСНОВЫ НОМЕНКЛАТУР'!D:H,5,0) -> C | T43: =$R43*D43 -> 0 | U43: =$R43*E43 -> 0 | V43: =$R43*F43 -> 0 | W43: =$R43*G43 -> 0 | X43: =$R43*H43 -> 0 | Y43: =$R43*I43 -> 1251983.2 | Z43: =$R43*J43 -> 562.33144 | AA43: =$R43*K43 -> 61538.157 | ... AD43: =$R43*N43 -> 2122.0054 | AE43: =SUM(T43:AD43) -> 1316205.7
A44: 19*0,4мм ПВХ Ночь экко AN | I44: 130000 | K44: 4800 | N44: 1400 | O44: 136200 | P44: =VLOOKUP(A44,'ИЗ ОСНОВЫ НОМЕНКЛАТУР'!D:E,2,0) -> Кромочные материалы | Q44: =VLOOKUP(A44,'ИЗ ОСНОВЫ НОМЕНКЛАТУР'!D:F,3,0) -> Кромка ПВХ Китай | R44: =VLOOKUP(A:A,'ИЗ ОСНОВЫ НОМЕНКЛАТУР'!D:G,4,0) -> 17.22025 | S44: =VLOOKUP(A:A,'ИЗ ОСНОВЫ НОМЕНКЛАТУР'!D:H,5,0) -> C | T44: =$R44*D44 -> 0 | U44: =$R44*E44 -> 0 | V44: =$R44*F44 -> 0 | W44: =$R44*G44 -> 0 | X44: =$R44*H44 -> 0 | Y44: =$R44*I44 -> 2238632.5 | Z44: =$R44*J44 -> 0 | AA44: =$R44*K44 -> 82657.2 | ... AD44: =$R44*N44 -> 24108.35 | AE44: =SUM(T44:AD44) -> 2345398.1
A45: 19*0,4мм ПВХ Ночь экко SD | I45: 10000 | O45: 10000 | P45: =VLOOKUP(A45,'ИЗ ОСНОВЫ НОМЕНКЛАТУР'!D:E,2,0) -> Кромочные материалы | Q45: =VLOOKUP(A45,'ИЗ ОСНОВЫ НОМЕНКЛАТУР'!D:F,3,0) -> Распродажа кромка | R45: =VLOOKUP(A:A,'ИЗ ОСНОВЫ НОМЕНКЛАТУР'!D:G,4,0) -> 12.575 | S45: =VLOOKUP(A:A,'ИЗ ОСНОВЫ НОМЕНКЛАТУР'!D:H,5,0) -> C | T45: =$R45*D45 -> 0 | U45: =$R45*E45 -> 0 | V45: =$R45*F45 -> 0 | W45: =$R45*G45 -> 0 | X45: =$R45*H45 -> 0 | Y45: =$R45*I45 -> 125750 | Z45: =$R45*J45 -> 0 | AA45: =$R45*K45 -> 0 | ... AD45: =$R45*N45 -> 0 | AE45: =SUM(T45:AD45) -> 125750
A46: 19*0,4мм ПВХ Серый AN | I46: 329000 | J46: 2000 | K46: 2400 | N46: 2155 | O46: 335555 | P46: =VLOOKUP(A46,'ИЗ ОСНОВЫ НОМЕНКЛАТУР'!D:E,2,0) -> Кромочные материалы | Q46: =VLOOKUP(A46,'ИЗ ОСНОВЫ НОМЕНКЛАТУР'!D:F,3,0) -> Кромка ПВХ Китай | R46: =VLOOKUP(A:A,'ИЗ ОСНОВЫ НОМЕНКЛАТУР'!D:G,4,0) -> 11.9939 | S46: =VLOOKUP(A:A,'ИЗ ОСНОВЫ НОМЕНКЛАТУР'!D:H,5,0) -> A | T46: =$R46*D46 -> 0 | U46: =$R46*E46 -> 0 | V46: =$R46*F46 -> 0 | W46: =$R46*G46 -> 0 | X46: =$R46*H46 -> 0 | Y46: =$R46*I46 -> 3945993.1 | Z46: =$R46*J46 -> 23987.8 | AA46: =$R46*K46 -> 28785.36 | ... AD46: =$R46*N46 -> 25846.855 | AE46: =SUM(T46:AD46) -> 4024613.1
A47: 19*0,4мм ПВХ Серый SD | I47: 52000 | O47: 52000 | P47: =VLOOKUP(A47,'ИЗ ОСНОВЫ НОМЕНКЛАТУР'!D:E,2,0) -> Кромочные материалы | Q47: =VLOOKUP(A47,'ИЗ ОСНОВЫ НОМЕНКЛАТУР'!D:F,3,0) -> Распродажа кромка | R47: =VLOOKUP(A:A,'ИЗ ОСНОВЫ НОМЕНКЛАТУР'!D:G,4,0) -> 10.353135 | S47: =VLOOKUP(A:A,'ИЗ ОСНОВЫ НОМЕНКЛАТУР'!D:H,5,0) -> C | T47: =$R47*D47 -> 0 | U47: =$R47*E47 -> 0 | V47: =$R47*F47 -> 0 | W47: =$R47*G47 -> 0 | X47: =$R47*H47 -> 0 | Y47: =$R47*I47 -> 538363 | Z47: =$R47*J47 -> 0 | AA47: =$R47*K47 -> 0 | ... AD47: =$R47*N47 -> 0 | AE47: =SUM(T47:AD47) -> 538363
A48: 19*0,4мм ПВХ Черный SJ | I48: 4000 | J48: 10000 | K48: 6000 | O48: 20000 | P48: =VLOOKUP(A48,'ИЗ ОСНОВЫ НОМЕНКЛАТУР'!D:E,2,0) -> Кромочные материалы | Q48: =VLOOKUP(A48,'ИЗ ОСНОВЫ НОМЕНКЛАТУР'!D:F,3,0) -> Кромка ПВХ Китай | R48: =VLOOKUP(A:A,'ИЗ ОСНОВЫ НОМЕНКЛАТУР'!D:G,4,0) -> 9.7 | S48: =VLOOKUP(A:A,'ИЗ ОСНОВЫ НОМЕНКЛАТУР'!D:H,5,0) -> B | T48: =$R48*D48 -> 0 | U48: =$R48*E48 -> 0 | V48: =$R48*F48 -> 0 | W48: =$R48*G48 -> 0 | X48: =$R48*H48 -> 0 | Y48: =$R48*I48 -> 38800 | Z48: =$R48*J48 -> 97000 | AA48: =$R48*K48 -> 58200 | ... AD48: =$R48*N48 -> 0 | AE48: =SUM(T48:AD48) -> 194000
A49: 19*0,4мм ПВХ Ясень шимо светлый AN | K49: 2000 | O49: 2000 | P49: =VLOOKUP(A49,'ИЗ ОСНОВЫ НОМЕНКЛАТУР'!D:E,2,0) -> Кромочные материалы | Q49: =VLOOKUP(A49,'ИЗ ОСНОВЫ НОМЕНКЛАТУР'!D:F,3,0) -> Кромка ПВХ Китай | R49: =VLOOKUP(A:A,'ИЗ ОСНОВЫ НОМЕНКЛАТУР'!D:G,4,0) -> 18.89 | S49: =VLOOKUP(A:A,'ИЗ ОСНОВЫ НОМЕНКЛАТУР'!D:H,5,0) -> C | T49: =$R49*D49 -> 0 | U49: =$R49*E49 -> 0 | V49: =$R49*F49 -> 0 | W49: =$R49*G49 -> 0 | X49: =$R49*H49 -> 0 | Y49: =$R49*I49 -> 0 | Z49: =$R49*J49 -> 0 | AA49: =$R49*K49 -> 37780 | ... AD49: =$R49*N49 -> 0 | AE49: =SUM(T49:AD49) -> 37780
A50: 19*0,4мм Солнечный свет 0134 PE | J50: 4600 | O50: 4600 | P50: =VLOOKUP(A50,'ИЗ ОСНОВЫ НОМЕНКЛАТУР'!D:E,2,0) -> Кромочные материалы | Q50: =VLOOKUP(A50,'ИЗ ОСНОВЫ НОМЕНКЛАТУР'!D:F,3,0) -> Кромка ПВХ Россия | R50: =VLOOKUP(A:A,'ИЗ ОСНОВЫ НОМЕНКЛАТУР'!D:G,4,0) -> 14.346957 | S50: =VLOOKUP(A:A,'ИЗ ОСНОВЫ НОМЕНКЛАТУР'!D:H,5,0) -> C | T50: =$R50*D50 -> 0 | U50: =$R50*E50 -> 0 | V50: =$R50*F50 -> 0 | W50: =$R50*G50 -> 0 | X50: =$R50*H50 -> 0 | Y50: =$R50*I50 -> 0 | Z50: =$R50*J50 -> 65996 | AA50: =$R50*K50 -> 0 | ... AD50: =$R50*N50 -> 0 | AE50: =SUM(T50:AD50) -> 65996
A51: 19*0,4мм Сосна Карельская 3888 SN | J51: 5400 | K51: 4000 | O51: 9400 | P51: =VLOOKUP(A51,'ИЗ ОСНОВЫ НОМЕНКЛАТУР'!D:E,2,0) -> Кромочные материалы | Q51: =VLOOKUP(A51,'ИЗ ОСНОВЫ НОМЕНКЛАТУР'!D:F,3,0) -> Кромка ПВХ Россия | R51: =VLOOKUP(A:A,'ИЗ ОСНОВЫ НОМЕНКЛАТУР'!D:G,4,0) -> 19.611556 | S51: =VLOOKUP(A:A,'ИЗ ОСНОВЫ НОМЕНКЛАТУР'!D:H,5,0) -> C | T51: =$R51*D51 -> 0 | U51: =$R51*E51 -> 0 | V51: =$R51*F51 -> 0 | W51: =$R51*G51 -> 0 | X51: =$R51*H51 -> 0 | Y51: =$R51*I51 -> 0 | Z51: =$R51*J51 -> 105902.4 | AA51: =$R51*K51 -> 78446.222 | ... AD51: =$R51*N51 -> 0 | AE51: =SUM(T51:AD51) -> 184348.62
A52: 19*0,4мм Ясень Анкор темный 4779 PR | J52: 14000 | O52: 14000 | P52: =VLOOKUP(A52,'ИЗ ОСНОВЫ НОМЕНКЛАТУР'!D:E,2,0) -> Кромочные материалы | Q52: =VLOOKUP(A52,'ИЗ ОСНОВЫ НОМЕНКЛАТУР'!D:F,3,0) -> Кромка ПВХ Россия | R52: =VLOOKUP(A:A,'ИЗ ОСНОВЫ НОМЕНКЛАТУР'!D:G,4,0) -> 20.2475 | S52: =VLOOKUP(A:A,'ИЗ ОСНОВЫ НОМЕНКЛАТУР'!D:H,5,0) -> C | T52: =$R52*D52 -> 0 | U52: =$R52*E52 -> 0 | V52: =$R52*F52 -> 0 | W52: =$R52*G52 -> 0 | X52: =$R52*H52 -> 0 | Y52: =$R52*I52 -> 0 | Z52: =$R52*J52 -> 283465 | AA52: =$R52*K52 -> 0 | ... AD52: =$R52*N52 -> 0 | AE52: =SUM(T52:AD52) -> 283465
A53: 19*0,8мм Артвуд темный К084 SN | K53: 400 | O53: 400 | P53: =VLOOKUP(A53,'ИЗ ОСНОВЫ НОМЕНКЛАТУР'!D:E,2,0) -> Кромочные материалы | Q53: =VLOOKUP(A53,'ИЗ ОСНОВЫ НОМЕНКЛАТУР'!D:F,3,0) -> Кромка ПВХ Россия | R53: =VLOOKUP(A:A,'ИЗ ОСНОВЫ НОМЕНКЛАТУР'!D:G,4,0) -> 34.345 | S53: =VLOOKUP(A:A,'ИЗ ОСНОВЫ НОМЕНКЛАТУР'!D:H,5,0) -> C | T53: =$R53*D53 -> 0 | U53: =$R53*E53 -> 0 | V53: =$R53*F53 -> 0 | W53: =$R53*G53 -> 0 | X53: =$R53*H53 -> 0 | Y53: =$R53*I53 -> 0 | Z53: =$R53*J53 -> 0 | AA53: =$R53*K53 -> 13738 | ... AD53: =$R53*N53 -> 0 | AE53: =SUM(T53:AD53) -> 13738
A54: 19*0,8мм Дуб Белфорт 3885 PR | D54: 840 | E54: 200 | J54: 105 | O54: 1145 | P54: =VLOOKUP(A54,'ИЗ ОСНОВЫ НОМЕНКЛАТУР'!D:E,2,0) -> Кромочные материалы | Q54: =VLOOKUP(A54,'ИЗ ОСНОВЫ НОМЕНКЛАТУР'!D:F,3,0) -> Кромка ПВХ Россия | R54: =VLOOKUP(A:A,'ИЗ ОСНОВЫ НОМЕНКЛАТУР'!D:G,4,0) -> 29.648941 | S54: =VLOOKUP(A:A,'ИЗ ОСНОВЫ НОМЕНКЛАТУР'!D:H,5,0) -> C | T54: =$R54*D54 -> 24905.111 | U54: =$R54*E54 -> 5929.7882 | V54: =$R54*F54 -> 0 | W54: =$R54*G54 -> 0 | X54: =$R54*H54 -> 0 | Y54: =$R54*I54 -> 0 | Z54: =$R54*J54 -> 3113.1388 | AA54: =$R54*K54 -> 0 | ... AD54: =$R54*N54 -> 0 | AE54: =SUM(T54:AD54) -> 33948.038
A55: 19*0,8мм Дуб серый Craft К002 | D55: 200 | J55: 1000 | K55: 800 | O55: 2000 | P55: =VLOOKUP(A55,'ИЗ ОСНОВЫ НОМЕНКЛАТУР'!D:E,2,0) -> Кромочные материалы | Q55: =VLOOKUP(A55,'ИЗ ОСНОВЫ НОМЕНКЛАТУР'!D:F,3,0) -> Кромка ПВХ Россия | R55: =VLOOKUP(A:A,'ИЗ ОСНОВЫ НОМЕНКЛАТУР'!D:G,4,0) -> 29.47 | S55: =VLOOKUP(A:A,'ИЗ ОСНОВЫ НОМЕНКЛАТУР'!D:H,5,0) -> C | T55: =$R55*D55 -> 5894 | U55: =$R55*E55 -> 0 | V55: =$R55*F55 -> 0 | W55: =$R55*G55 -> 0 | X55: =$R55*H55 -> 0 | Y55: =$R55*I55 -> 0 | Z55: =$R55*J55 -> 29470 | AA55: =$R55*K55 -> 23576 | ... AD55: =$R55*N55 -> 0 | AE55: =SUM(T55:AD55) -> 58940
A56: 19*0,8мм Карум ПВХ Турция | J56: 150 | O56: 150 | P56: =VLOOKUP(A56,'ИЗ ОСНОВЫ НОМЕНКЛАТУР'!D:E,2,0) -> Кромочные материалы | Q56: =VLOOKUP(A56,'ИЗ ОСНОВЫ НОМЕНКЛАТУР'!D:F,3,0) -> Кромка ПВХ Турция | R56: =VLOOKUP(A:A,'ИЗ ОСНОВЫ НОМЕНКЛАТУР'!D:G,4,0) -> 29.986667 | S56: =VLOOKUP(A:A,'ИЗ ОСНОВЫ НОМЕНКЛАТУР'!D:H,5,0) -> C | T56: =$R56*D56 -> 0 | U56: =$R56*E56 -> 0 | V56: =$R56*F56 -> 0 | W56: =$R56*G56 -> 0 | X56: =$R56*H56 -> 0 | Y56: =$R56*I56 -> 0 | Z56: =$R56*J56 -> 4498 | AA56: =$R56*K56 -> 0 | ... AD56: =$R56*N56 -> 0 | AE56: =SUM(T56:AD56) -> 4498
A57: 19*0,8мм Клен Танзау 0375 PR | J57: 248 | K57: 600 | O57: 848 | P57: =VLOOKUP(A57,'ИЗ ОСНОВЫ НОМЕНКЛАТУР'!D:E,2,0) -> Кромочные материалы | Q57: =VLOOKUP(A57,'ИЗ ОСНОВЫ НОМЕНКЛАТУР'!D:F,3,0) -> Кромка ПВХ Россия | R57: =VLOOKUP(A:A,'ИЗ ОСНОВЫ НОМЕНКЛАТУР'!D:G,4,0) -> 34.077273 | S57: =VLOOKUP(A:A,'ИЗ ОСНОВЫ НОМЕНКЛАТУР'!D:H,5,0) -> C | T57: =$R57*D57 -> 0 | U57: =$R57*E57 -> 0 | V57: =$R57*F57 -> 0 | W57: =$R57*G57 -> 0 | X57: =$R57*H57 -> 0 | Y57: =$R57*I57 -> 0 | Z57: =$R57*J57 -> 8451.1636 | AA57: =$R57*K57 -> 20446.364 | ... AD57: =$R57*N57 -> 0 | AE57: =SUM(T57:AD57) -> 28897.527
A58: 19*0,8мм Коко Бола 8995 SN | D58: 300 | E58: 400 | K58: 400 | O58: 1100 | P58: =VLOOKUP(A58,'ИЗ ОСНОВЫ НОМЕНКЛАТУР'!D:E,2,0) -> Кромочные материалы | Q58: =VLOOKUP(A58,'ИЗ ОСНОВЫ НОМЕНКЛАТУР'!D:F,3,0) -> Кромка ПВХ Россия | R58: =VLOOKUP(A:A,'ИЗ ОСНОВЫ НОМЕНКЛАТУР'!D:G,4,0) -> 29.47 | S58: =VLOOKUP(A:A,'ИЗ ОСНОВЫ НОМЕНКЛАТУР'!D:H,5,0) -> C | T58: =$R58*D58 -> 8841 | U58: =$R58*E58 -> 11788 | V58: =$R58*F58 -> 0 | W58: =$R58*G58 -> 0 | X58: =$R58*H58 -> 0 | Y58: =$R58*I58 -> 0 | Z58: =$R58*J58 -> 0 | AA58: =$R58*K58 -> 11788 | ... AD58: =$R58*N58 -> 0 | AE58: =SUM(T58:AD58) -> 32417
A59: 19*0,8мм Красный Чили 7113 PE | J59: 800 | O59: 800 | P59: =VLOOKUP(A59,'ИЗ ОСНОВЫ НОМЕНКЛАТУР'!D:E,2,0) -> Кромочные материалы | Q59: =VLOOKUP(A59,'ИЗ ОСНОВЫ НОМЕНКЛАТУР'!D:F,3,0) -> Кромка ПВХ Россия | R59: =VLOOKUP(A:A,'ИЗ ОСНОВЫ НОМЕНКЛАТУР'!D:G,4,0) -> 24.63875 | S59: =VLOOKUP(A:A,'ИЗ ОСНОВЫ НОМЕНКЛАТУР'!D:H,5,0) -> C | T59: =$R59*D59 -> 0 | U59: =$R59*E59 -> 0 | V59: =$R59*F59 -> 0 | W59: =$R59*G59 -> 0 | X59: =$R59*H59 -> 0 | Y59: =$R59*I59 -> 0 | Z59: =$R59*J59 -> 19711 | AA59: =$R59*K59 -> 0 | ... AD59: =$R59*N59 -> 0 | AE59: =SUM(T59:AD59) -> 19711
A60: 19*0,8мм Лен ПВХ Турция | J60: 2500 | O60: 2500 | P60: =VLOOKUP(A60,'ИЗ ОСНОВЫ НОМЕНКЛАТУР'!D:E,2,0) -> Кромочные материалы | Q60: =VLOOKUP(A60,'ИЗ ОСНОВЫ НОМЕНКЛАТУР'!D:F,3,0) -> Кромка ПВХ Турция | R60: =VLOOKUP(A:A,'ИЗ ОСНОВЫ НОМЕНКЛАТУР'!D:G,4,0) -> 16.327414 | S60: =VLOOKUP(A:A,'ИЗ ОСНОВЫ НОМЕНКЛАТУР'!D:H,5,0) -> B | T60: =$R60*D60 -> 0 | U60: =$R60*E60 -> 0 | V60: =$R60*F60 -> 0 | W60: =$R60*G60 -> 0 | X60: =$R60*H60 -> 0 | Y60: =$R60*I60 -> 0 | Z60: =$R60*J60 -> 40818.534 | AA60: =$R60*K60 -> 0 | ... AD60: =$R60*N60 -> 0 | AE60: =SUM(T60:AD60) -> 40818.534
A61: 19*0,8мм Орех Гепланкт 5648 PR | J61: 192 | O61: 192 | P61: =VLOOKUP(A61,'ИЗ ОСНОВЫ НОМЕНКЛАТУР'!D:E,2,0) -> Кромочные материалы | Q61: =VLOOKUP(A61,'ИЗ ОСНОВЫ НОМЕНКЛАТУР'!D:F,3,0) -> Кромка ПВХ Россия | R61: =VLOOKUP(A:A,'ИЗ ОСНОВЫ НОМЕНКЛАТУР'!D:G,4,0) -> 28.295 | S61: =VLOOKUP(A:A,'ИЗ ОСНОВЫ НОМЕНКЛАТУР'!D:H,5,0) -> C | T61: =$R61*D61 -> 0 | U61: =$R61*E61 -> 0 | V61: =$R61*F61 -> 0 | W61: =$R61*G61 -> 0 | X61: =$R61*H61 -> 0 | Y61: =$R61*I61 -> 0 | Z61: =$R61*J61 -> 5432.64 | AA61: =$R61*K61 -> 0 | ... AD61: =$R61*N61 -> 0 | AE61: =SUM(T61:AD61) -> 5432.64
A62: 19*0,8мм ПВХ Азул Оникс AN | J62: 784 | L62: 190 | M62: 600 | N62: 702 | O62: 2276 | P62: =VLOOKUP(A62,'ИЗ ОСНОВЫ НОМЕНКЛАТУР'!D:E,2,0) -> Кромочные материалы | Q62: =VLOOKUP(A62,'ИЗ ОСНОВЫ НОМЕНКЛАТУР'!D:F,3,0) -> Кромка ПВХ Китай | R62: =VLOOKUP(A:A,'ИЗ ОСНОВЫ НОМЕНКЛАТУР'!D:G,4,0) -> 26.13636 | S62: =VLOOKUP(A:A,'ИЗ ОСНОВЫ НОМЕНКЛАТУР'!D:H,5,0) -> B | T62: =$R62*D62 -> 0 | U62: =$R62*E62 -> 0 | V62: =$R62*F62 -> 0 | W62: =$R62*G62 -> 0 | X62: =$R62*H62 -> 0 | Y62: =$R62*I62 -> 0 | Z62: =$R62*J62 -> 20490.906 | AA62: =$R62*K62 -> 0 | ... AD62: =$R62*N62 -> 18347.725 | AE62: =SUM(T62:AD62) -> 59486.355
A63: 19*0,8мм ПВХ Азул Оникс SJ | I63: 9000 | J63: 1800 | K63: 2000 | O63: 12800 | P63: =VLOOKUP(A63,'ИЗ ОСНОВЫ НОМЕНКЛАТУР'!D:E,2,0) -> Кромочные материалы | Q63: =VLOOKUP(A63,'ИЗ ОСНОВЫ НОМЕНКЛАТУР'!D:F,3,0) -> Кромка ПВХ Китай | R63: =VLOOKUP(A:A,'ИЗ ОСНОВЫ НОМЕНКЛАТУР'!D:G,4,0) -> 24.9 | S63: =VLOOKUP(A:A,'ИЗ ОСНОВЫ НОМЕНКЛАТУР'!D:H,5,0) -> B | T63: =$R63*D63 -> 0 | U63: =$R63*E63 -> 0 | V63: =$R63*F63 -> 0 | W63: =$R63*G63 -> 0 | X63: =$R63*H63 -> 0 | Y63: =$R63*I63 -> 224100 | Z63: =$R63*J63 -> 44820 | AA63: =$R63*K63 -> 49800 | ... AD63: =$R63*N63 -> 0 | AE63: =SUM(T63:AD63) -> 318720
A64: 19*0,8мм ПВХ Айконик AN | J64: 742 | N64: 2878 | O64: 3620 | P64: =VLOOKUP(A64,'ИЗ ОСНОВЫ НОМЕНКЛАТУР'!D:E,2,0) -> Кромочные материалы | Q64: =VLOOKUP(A64,'ИЗ ОСНОВЫ НОМЕНКЛАТУР'!D:F,3,0) -> Кромка ПВХ Китай | R64: =VLOOKUP(A:A,'ИЗ ОСНОВЫ НОМЕНКЛАТУР'!D:G,4,0) -> 30.643361 | S64: =VLOOKUP(A:A,'ИЗ ОСНОВЫ НОМЕНКЛАТУР'!D:H,5,0) -> C | T64: =$R64*D64 -> 0 | U64: =$R64*E64 -> 0 | V64: =$R64*F64 -> 0 | W64: =$R64*G64 -> 0 | X64: =$R64*H64 -> 0 | Y64: =$R64*I64 -> 0 | Z64: =$R64*J64 -> 22737.374 | AA64: =$R64*K64 -> 0 | ... AD64: =$R64*N64 -> 88191.592 | AE64: =SUM(T64:AD64) -> 110928.97
A65: 19*0,8мм ПВХ Акация светлая AN | D65: 100 | E65: 200 | J65: 2203 | N65: 3837 | O65: 6340 | P65: =VLOOKUP(A65,'ИЗ ОСНОВЫ НОМЕНКЛАТУР'!D:E,2,0) -> Кромочные материалы | Q65: =VLOOKUP(A65,'ИЗ ОСНОВЫ НОМЕНКЛАТУР'!D:F,3,0) -> Кромка ПВХ Китай | R65: =VLOOKUP(A:A,'ИЗ ОСНОВЫ НОМЕНКЛАТУР'!D:G,4,0) -> 26.387424 | S65: =VLOOKUP(A:A,'ИЗ ОСНОВЫ НОМЕНКЛАТУР'!D:H,5,0) -> C | T65: =$R65*D65 -> 2638.7424 | U65: =$R65*E65 -> 5277.4848 | V65: =$R65*F65 -> 0 | W65: =$R65*G65 -> 0 | X65: =$R65*H65 -> 0 | Y65: =$R65*I65 -> 0 | Z65: =$R65*J65 -> 58131.495 | AA65: =$R65*K65 -> 0 | ... AD65: =$R65*N65 -> 101248.55 | AE65: =SUM(T65:AD65) -> 167296.27
A66: 19*0,8мм ПВХ Акация светлая SJ | I66: 2000 | O66: 2000 | P66: =VLOOKUP(A66,'ИЗ ОСНОВЫ НОМЕНКЛАТУР'!D:E,2,0) -> Кромочные материалы | Q66: =VLOOKUP(A66,'ИЗ ОСНОВЫ НОМЕНКЛАТУР'!D:F,3,0) -> Кромка ПВХ Китай | R66: =VLOOKUP(A:A,'ИЗ ОСНОВЫ НОМЕНКЛАТУР'!D:G,4,0) -> 24.3 | S66: =VLOOKUP(A:A,'ИЗ ОСНОВЫ НОМЕНКЛАТУР'!D:H,5,0) -> C | T66: =$R66*D66 -> 0 | U66: =$R66*E66 -> 0 | V66: =$R66*F66 -> 0 | W66: =$R66*G66 -> 0 | X66: =$R66*H66 -> 0 | Y66: =$R66*I66 -> 48600 | Z66: =$R66*J66 -> 0 | AA66: =$R66*K66 -> 0 | ... AD66: =$R66*N66 -> 0 | AE66: =SUM(T66:AD66) -> 48600
A67: 19*0,8мм ПВХ Аква AN | D67: 120 | E67: 200 | G67: 141 | N67: 723 | O67: 1184 | P67: =VLOOKUP(A67,'ИЗ ОСНОВЫ НОМЕНКЛАТУР'!D:E,2,0) -> Кромочные материалы | Q67: =VLOOKUP(A67,'ИЗ ОСНОВЫ НОМЕНКЛАТУР'!D:F,3,0) -> Кромка ПВХ Китай | R67: =VLOOKUP(A:A,'ИЗ ОСНОВЫ НОМЕНКЛАТУР'!D:G,4,0) -> 20.881263 | S67: =VLOOKUP(A:A,'ИЗ ОСНОВЫ НОМЕНКЛАТУР'!D:H,5,0) -> B | T67: =$R67*D67 -> 2505.7516 | U67: =$R67*E67 -> 4176.2526 | V67: =$R67*F67 -> 0 | W67: =$R67*G67 -> 2944.2581 | X67: =$R67*H67 -> 0 | Y67: =$R67*I67 -> 0 | Z67: =$R67*J67 -> 0 | AA67: =$R67*K67 -> 0 | ... AD67: =$R67*N67 -> 15097.153 | AE67: =SUM(T67:AD67) -> 24723.415
A68: 19*0,8мм ПВХ Аква SJ | I68: 1000 | J68: 1496 | K68: 2000 | L68: 192 | M68: 1600 | N68: 1404 | O68: 7692 | P68: =VLOOKUP(A68,'ИЗ ОСНОВЫ НОМЕНКЛАТУР'!D:E,2,0) -> Кромочные материалы | Q68: =VLOOKUP(A68,'ИЗ ОСНОВЫ НОМЕНКЛАТУР'!D:F,3,0) -> Кромка ПВХ Китай | R68: =VLOOKUP(A:A,'ИЗ ОСНОВЫ НОМЕНКЛАТУР'!D:G,4,0) -> 18.074044 | S68: =VLOOKUP(A:A,'ИЗ ОСНОВЫ НОМЕНКЛАТУР'!D:H,5,0) -> B | T68: =$R68*D68 -> 0 | U68: =$R68*E68 -> 0 | V68: =$R68*F68 -> 0 | W68: =$R68*G68 -> 0 | X68: =$R68*H68 -> 0 | Y68: =$R68*I68 -> 18074.044 | Z68: =$R68*J68 -> 27038.769 | AA68: =$R68*K68 -> 36148.087 | ... AD68: =$R68*N68 -> 25375.957 | AE68: =SUM(T68:AD68) -> 139025.54
A69: 19*0,8мм ПВХ Альфа AN | I69: 13000 | J69: 5769 | K69: 12000 | L69: 190 | M69: 600 | N69: 864 | O69: 32423 | P69: =VLOOKUP(A69,'ИЗ ОСНОВЫ НОМЕНКЛАТУР'!D:E,2,0) -> Кромочные материалы | Q69: =VLOOKUP(A69,'ИЗ ОСНОВЫ НОМЕНКЛАТУР'!D:F,3,0) -> Кромка ПВХ Китай | R69: =VLOOKUP(A:A,'ИЗ ОСНОВЫ НОМЕНКЛАТУР'!D:G,4,0) -> 29.773028 | S69: =VLOOKUP(A:A,'ИЗ ОСНОВЫ НОМЕНКЛАТУР'!D:H,5,0) -> C | T69: =$R69*D69 -> 0 | U69: =$R69*E69 -> 0 | V69: =$R69*F69 -> 0 | W69: =$R69*G69 -> 0 | X69: =$R69*H69 -> 0 | Y69: =$R69*I69 -> 387049.36 | Z69: =$R69*J69 -> 171760.6 | AA69: =$R69*K69 -> 357276.33 | ... AD69: =$R69*N69 -> 25723.896 | AE69: =SUM(T69:AD69) -> 965330.88
A70: 19*0,8мм ПВХ Алюминий AN | D70: 5002 | E70: 200 | G70: 1154 | I70: 25000 | J70: 4216 | K70: 19800 | L70: 193 | M70: 2400 | N70: 8043 | O70: 66008 | P70: =VLOOKUP(A70,'ИЗ ОСНОВЫ НОМЕНКЛАТУР'!D:E,2,0) -> Кромочные материалы | Q70: =VLOOKUP(A70,'ИЗ ОСНОВЫ НОМЕНКЛАТУР'!D:F,3,0) -> Кромка ПВХ Китай | R70: =VLOOKUP(A:A,'ИЗ ОСНОВЫ НОМЕНКЛАТУР'!D:G,4,0) -> 29.302648 | S70: =VLOOKUP(A:A,'ИЗ ОСНОВЫ НОМЕНКЛАТУР'!D:H,5,0) -> A | T70: =$R70*D70 -> 146571.85 | U70: =$R70*E70 -> 5860.5297 | V70: =$R70*F70 -> 0 | W70: =$R70*G70 -> 33815.256 | X70: =$R70*H70 -> 0 | Y70: =$R70*I70 -> 732566.21 | Z70: =$R70*J70 -> 123539.97 | AA70: =$R70*K70 -> 580192.44 | ... AD70: =$R70*N70 -> 235681.2 | AE70: =SUM(T70:AD70) -> 1934209.2
A71: 19*0,8мм ПВХ Алюминий SJ | I71: 10000 | O71: 10000 | P71: =VLOOKUP(A71,'ИЗ ОСНОВЫ НОМЕНКЛАТУР'!D:E,2,0) -> Кромочные материалы | Q71: =VLOOKUP(A71,'ИЗ ОСНОВЫ НОМЕНКЛАТУР'!D:F,3,0) -> Кромка ПВХ Китай | R71: =VLOOKUP(A:A,'ИЗ ОСНОВЫ НОМЕНКЛАТУР'!D:G,4,0) -> 24.3 | S71: =VLOOKUP(A:A,'ИЗ ОСНОВЫ НОМЕНКЛАТУР'!D:H,5,0) -> C | T71: =$R71*D71 -> 0 | U71: =$R71*E71 -> 0 | V71: =$R71*F71 -> 0 | W71: =$R71*G71 -> 0 | X71: =$R71*H71 -> 0 | Y71: =$R71*I71 -> 243000 | Z71: =$R71*J71 -> 0 | AA71: =$R71*K71 -> 0 | ... AD71: =$R71*N71 -> 0 | AE71: =SUM(T71:AD71) -> 243000
A72: 19*0,8мм ПВХ Алюминий серый SD | J72: 8300 | O72: 8300 | P72: =VLOOKUP(A72,'ИЗ ОСНОВЫ НОМЕНКЛАТУР'!D:E,2,0) -> Кромочные материалы | Q72: =VLOOKUP(A72,'ИЗ ОСНОВЫ НОМЕНКЛАТУР'!D:F,3,0) -> Распродажа кромка | R72: =VLOOKUP(A:A,'ИЗ ОСНОВЫ НОМЕНКЛАТУР'!D:G,4,0) -> 21 | S72: =VLOOKUP(A:A,'ИЗ ОСНОВЫ НОМЕНКЛАТУР'!D:H,5,0) -> C | T72: =$R72*D72 -> 0 | U72: =$R72*E72 -> 0 | V72: =$R72*F72 -> 0 | W72: =$R72*G72 -> 0 | X72: =$R72*H72 -> 0 | Y72: =$R72*I72 -> 0 | Z72: =$R72*J72 -> 174300 | AA72: =$R72*K72 -> 0 | ... AD72: =$R72*N72 -> 0 | AE72: =SUM(T72:AD72) -> 174300
A73: 19*0,8мм ПВХ Анкор белый AN | G73: 9 | J73: 8744 | N73: 10092 | O73: 18845 | P73: =VLOOKUP(A73,'ИЗ ОСНОВЫ НОМЕНКЛАТУР'!D:E,2,0) -> Кромочные материалы | Q73: =VLOOKUP(A73,'ИЗ ОСНОВЫ НОМЕНКЛАТУР'!D:F,3,0) -> Кромка ПВХ Китай | R73: =VLOOKUP(A:A,'ИЗ ОСНОВЫ НОМЕНКЛАТУР'!D:G,4,0) -> 27.61529 | S73: =VLOOKUP(A:A,'ИЗ ОСНОВЫ НОМЕНКЛАТУР'!D:H,5,0) -> A | T73: =$R73*D73 -> 0 | U73: =$R73*E73 -> 0 | V73: =$R73*F73 -> 0 | W73: =$R73*G73 -> 248.53761 | X73: =$R73*H73 -> 0 | Y73: =$R73*I73 -> 0 | Z73: =$R73*J73 -> 241468.1 | AA73: =$R73*K73 -> 0 | ... AD73: =$R73*N73 -> 278693.51 | AE73: =SUM(T73:AD73) -> 520410.14
A74: 19*0,8мм ПВХ Анкор белый MS | J74: 1130 | K74: 4400 | O74: 5530 | P74: =VLOOKUP(A74,'ИЗ ОСНОВЫ НОМЕНКЛАТУР'!D:E,2,0) -> Кромочные материалы | Q74: =VLOOKUP(A74,'ИЗ ОСНОВЫ НОМЕНКЛАТУР'!D:F,3,0) -> Распродажа кромка | R74: =VLOOKUP(A:A,'ИЗ ОСНОВЫ НОМЕНКЛАТУР'!D:G,4,0) -> 42.163834 | S74: =VLOOKUP(A:A,'ИЗ ОСНОВЫ НОМЕНКЛАТУР'!D:H,5,0) -> C | T74: =$R74*D74 -> 0 | U74: =$R74*E74 -> 0 | V74: =$R74*F74 -> 0 | W74: =$R74*G74 -> 0 | X74: =$R74*H74 -> 0 | Y74: =$R74*I74 -> 0 | Z74: =$R74*J74 -> 47645.132 | AA74: =$R74*K74 -> 185520.87 | ... AD74: =$R74*N74 -> 0 | AE74: =SUM(T74:AD74) -> 233166
A75: 19*0,8мм ПВХ Анкор белый SJ | D75: 3026 | G75: 1400 | I75: 22000 | K75: 27000 | L75: 103 | M75: 4400 | N75: 979 | O75: 58908 | P75: =VLOOKUP(A75,'ИЗ ОСНОВЫ НОМЕНКЛАТУР'!D:E,2,0) -> Кромочные материалы | Q75: =VLOOKUP(A75,'ИЗ ОСНОВЫ НОМЕНКЛАТУР'!D:F,3,0) -> Кромка ПВХ Китай | R75: =VLOOKUP(A:A,'ИЗ ОСНОВЫ НОМЕНКЛАТУР'!D:G,4,0) -> 25.815628 | S75: =VLOOKUP(A:A,'ИЗ ОСНОВЫ НОМЕНКЛАТУР'!D:H,5,0) -> A | T75: =$R75*D75 -> 78118.091 | U75: =$R75*E75 -> 0 | V75: =$R75*F75 -> 0 | W75: =$R75*G75 -> 36141.879 | X75: =$R75*H75 -> 0 | Y75: =$R75*I75 -> 567943.82 | Z75: =$R75*J75 -> 0 | AA75: =$R75*K75 -> 697021.96 | ... AD75: =$R75*N75 -> 25273.5 | AE75: =SUM(T75:AD75) -> 1520747
A76: 19*0,8мм ПВХ Анкор светлый AN | D76: 22 | E76: 200 | G76: 11 | L76: 132 | M76: 1800 | N76: 2993 | O76: 5158 | P76: =VLOOKUP(A76,'ИЗ ОСНОВЫ НОМЕНКЛАТУР'!D:E,2,0) -> Кромочные материалы | Q76: =VLOOKUP(A76,'ИЗ ОСНОВЫ НОМЕНКЛАТУР'!D:F,3,0) -> Кромка ПВХ Китай | R76: =VLOOKUP(A:A,'ИЗ ОСНОВЫ НОМЕНКЛАТУР'!D:G,4,0) -> 27.307434 | S76: =VLOOKUP(A:A,'ИЗ ОСНОВЫ НОМЕНКЛАТУР'!D:H,5,0) -> B | T76: =$R76*D76 -> 600.76355 | U76: =$R76*E76 -> 5461.4868 | V76: =$R76*F76 -> 0 | W76: =$R76*G76 -> 300.38177 | X76: =$R76*H76 -> 0 | Y76: =$R76*I76 -> 0 | Z76: =$R76*J76 -> 0 | AA76: =$R76*K76 -> 0 | ... AD76: =$R76*N76 -> 81731.15 | AE76: =SUM(T76:AD76) -> 140851.74
A77: 19*0,8мм ПВХ Анкор светлый SJ | J77: 1178 | K77: 11000 | N77: 4252 | O77: 16430 | P77: =VLOOKUP(A77,'ИЗ ОСНОВЫ НОМЕНКЛАТУР'!D:E,2,0) -> Кромочные материалы | Q77: =VLOOKUP(A77,'ИЗ ОСНОВЫ НОМЕНКЛАТУР'!D:F,3,0) -> Кромка ПВХ Китай | R77: =VLOOKUP(A:A,'ИЗ ОСНОВЫ НОМЕНКЛАТУР'!D:G,4,0) -> 26.643854 | S77: =VLOOKUP(A:A,'ИЗ ОСНОВЫ НОМЕНКЛАТУР'!D:H,5,0) -> B | T77: =$R77*D77 -> 0 | U77: =$R77*E77 -> 0 | V77: =$R77*F77 -> 0 | W77: =$R77*G77 -> 0 | X77: =$R77*H77 -> 0 | Y77: =$R77*I77 -> 0 | Z77: =$R77*J77 -> 31386.46 | AA77: =$R77*K77 -> 293082.4 | ... AD77: =$R77*N77 -> 113289.67 | AE77: =SUM(T77:AD77) -> 437758.52
A78: 19*0,8мм ПВХ Анкор темный AN | D78: 2466 | E78: 200 | G78: 765 | I78: 35000 | J78: 5405 | K78: 20200 | L78: 137 | M78: 3800 | N78: 6719 | O78: 74692 | P78: =VLOOKUP(A78,'ИЗ ОСНОВЫ НОМЕНКЛАТУР'!D:E,2,0) -> Кромочные материалы | Q78: =VLOOKUP(A78,'ИЗ ОСНОВЫ НОМЕНКЛАТУР'!D:F,3,0) -> Кромка ПВХ Китай | R78: =VLOOKUP(A:A,'ИЗ ОСНОВЫ НОМЕНКЛАТУР'!D:G,4,0) -> 28.906671 | S78: =VLOOKUP(A:A,'ИЗ ОСНОВЫ НОМЕНКЛАТУР'!D:H,5,0) -> B | T78: =$R78*D78 -> 71283.85 | U78: =$R78*E78 -> 5781.3341 | V78: =$R78*F78 -> 0 | W78: =$R78*G78 -> 22113.603 | X78: =$R78*H78 -> 0 | Y78: =$R78*I78 -> 1011733.5 | Z78: =$R78*J78 -> 156240.55 | AA78: =$R78*K78 -> 583914.75 | ... AD78: =$R78*N78 -> 194223.92 | AE78: =SUM(T78:AD78) -> 2159097
A79: 19*0,8мм ПВХ Антрацит AN | D79: 22 | J79: 2028 | K79: 224 | L79: 76 | M79: 400 | N79: 200 | O79: 2950 | P79: =VLOOKUP(A79,'ИЗ ОСНОВЫ НОМЕНКЛАТУР'!D:E,2,0) -> Кромочные материалы | Q79: =VLOOKUP(A79,'ИЗ ОСНОВЫ НОМЕНКЛАТУР'!D:F,3,0) -> Кромка ПВХ Китай | R79: =VLOOKUP(A:A,'ИЗ ОСНОВЫ НОМЕНКЛАТУР'!D:G,4,0) -> 19.798543 | S79: =VLOOKUP(A:A,'ИЗ ОСНОВЫ НОМЕНКЛАТУР'!D:H,5,0) -> A | T79: =$R79*D79 -> 435.56795 | U79: =$R79*E79 -> 0 | V79: =$R79*F79 -> 0 | W79: =$R79*G79 -> 0 | X79: =$R79*H79 -> 0 | Y79: =$R79*I79 -> 0 | Z79: =$R79*J79 -> 40151.446 | AA79: =$R79*K79 -> 4434.8737 | ... AD79: =$R79*N79 -> 3959.7086 | AE79: =SUM(T79:AD79) -> 58405.702
A80: 19*0,8мм ПВХ Антрацит SJ | D80: 40 | G80: 1000 | I80: 4000 | J80: 5000 | N80: 70 | O80: 10110 | P80: =VLOOKUP(A80,'ИЗ ОСНОВЫ НОМЕНКЛАТУР'!D:E,2,0) -> Кромочные материалы | Q80: =VLOOKUP(A80,'ИЗ ОСНОВЫ НОМЕНКЛАТУР'!D:F,3,0) -> Кромка ПВХ Китай | R80: =VLOOKUP(A:A,'ИЗ ОСНОВЫ НОМЕНКЛАТУР'!D:G,4,0) -> 18.367106 | S80: =VLOOKUP(A:A,'ИЗ ОСНОВЫ НОМЕНКЛАТУР'!D:H,5,0) -> A | T80: =$R80*D80 -> 734.68423 | U80: =$R80*E80 -> 0 | V80: =$R80*F80 -> 0 | W80: =$R80*G80 -> 18367.106 | X80: =$R80*H80 -> 0 | Y80: =$R80*I80 -> 73468.423 | Z80: =$R80*J80 -> 91835.529 | AA80: =$R80*K80 -> 0 | ... AD80: =$R80*N80 -> 1285.6974 | AE80: =SUM(T80:AD80) -> 185691.44
A81: 19*0,8мм ПВХ Антрацит серый SD | G81: 127 | J81: 12195 | O81: 12322 | P81: =VLOOKUP(A81,'ИЗ ОСНОВЫ НОМЕНКЛАТУР'!D:E,2,0) -> Кромочные материалы | Q81: =VLOOKUP(A81,'ИЗ ОСНОВЫ НОМЕНКЛАТУР'!D:F,3,0) -> Распродажа кромка | R81: =VLOOKUP(A:A,'ИЗ ОСНОВЫ НОМЕНКЛАТУР'!D:G,4,0) -> 21 | S81: =VLOOKUP(A:A,'ИЗ ОСНОВЫ НОМЕНКЛАТУР'!D:H,5,0) -> B | T81: =$R81*D81 -> 0 | U81: =$R81*E81 -> 0 | V81: =$R81*F81 -> 0 | W81: =$R81*G81 -> 2667 | X81: =$R81*H81 -> 0 | Y81: =$R81*I81 -> 0 | Z81: =$R81*J81 -> 256095 | AA81: =$R81*K81 -> 0 | ... AD81: =$R81*N81 -> 0 | AE81: =SUM(T81:AD81) -> 258762
A82: 19*0,8мм ПВХ Антрацитовый камень C309 SJ | J82: 2000 | K82: 3000 | O82: 5000 | P82: =VLOOKUP(A82,'ИЗ ОСНОВЫ НОМЕНКЛАТУР'!D:E,2,0) -> Кромочные материалы | Q82: =VLOOKUP(A82,'ИЗ ОСНОВЫ НОМЕНКЛАТУР'!D:F,3,0) -> Кромка ПВХ Китай | R82: =VLOOKUP(A:A,'ИЗ ОСНОВЫ НОМЕНКЛАТУР'!D:G,4,0) -> 24.6 | S82: =VLOOKUP(A:A,'ИЗ ОСНОВЫ НОМЕНКЛАТУР'!D:H,5,0) -> C | T82: =$R82*D82 -> 0 | U82: =$R82*E82 -> 0 | V82: =$R82*F82 -> 0 | W82: =$R82*G82 -> 0 | X82: =$R82*H82 -> 0 | Y82: =$R82*I82 -> 0 | Z82: =$R82*J82 -> 49200 | AA82: =$R82*K82 -> 73800 | ... AD82: =$R82*N82 -> 0 | AE82: =SUM(T82:AD82) -> 123000
A83: 19*0,8мм ПВХ Арабика AN | J83: 2884 | L83: 149 | M83: 4600 | N83: 560 | O83: 8193 | P83: =VLOOKUP(A83,'ИЗ ОСНОВЫ НОМЕНКЛАТУР'!D:E,2,0) -> Кромочные материалы | Q83: =VLOOKUP(A83,'ИЗ ОСНОВЫ НОМЕНКЛАТУР'!D:F,3,0) -> Кромка ПВХ Китай | R83: =VLOOKUP(A:A,'ИЗ ОСНОВЫ НОМЕНКЛАТУР'!D:G,4,0) -> 21.769389 | S83: =VLOOKUP(A:A,'ИЗ ОСНОВЫ НОМЕНКЛАТУР'!D:H,5,0) -> B | T83: =$R83*D83 -> 0 | U83: =$R83*E83 -> 0 | V83: =$R83*F83 -> 0 | W83: =$R83*G83 -> 0 | X83: =$R83*H83 -> 0 | Y83: =$R83*I83 -> 0 | Z83: =$R83*J83 -> 62782.919 | AA83: =$R83*K83 -> 0 | ... AD83: =$R83*N83 -> 12190.858 | AE83: =SUM(T83:AD83) -> 178356.61
A84: 19*0,8мм ПВХ Арабика SD | G84: 145 | O84: 145 | P84: =VLOOKUP(A84,'ИЗ ОСНОВЫ НОМЕНКЛАТУР'!D:E,2,0) -> Кромочные материалы | Q84: =VLOOKUP(A84,'ИЗ ОСНОВЫ НОМЕНКЛАТУР'!D:F,3,0) -> Распродажа кромка | R84: =VLOOKUP(A:A,'ИЗ ОСНОВЫ НОМЕНКЛАТУР'!D:G,4,0) -> 21.517241 | S84: =VLOOKUP(A:A,'ИЗ ОСНОВЫ НОМЕНКЛАТУР'!D:H,5,0) -> C | T84: =$R84*D84 -> 0 | U84: =$R84*E84 -> 0 | V84: =$R84*F84 -> 0 | W84: =$R84*G84 -> 3120 | X84: =$R84*H84 -> 0 | Y84: =$R84*I84 -> 0 | Z84: =$R84*J84 -> 0 | AA84: =$R84*K84 -> 0 | ... AD84: =$R84*N84 -> 0 | AE84: =SUM(T84:AD84) -> 3120
A85: 19*0,8мм ПВХ Ароза светлая U701 SJ | J85: 2000 | K85: 3000 | O85: 5000 | P85: =VLOOKUP(A85,'ИЗ ОСНОВЫ НОМЕНКЛАТУР'!D:E,2,0) -> Кромочные материалы | Q85: =VLOOKUP(A85,'ИЗ ОСНОВЫ НОМЕНКЛАТУР'!D:F,3,0) -> Кромка ПВХ Китай | R85: =VLOOKUP(A:A,'ИЗ ОСНОВЫ НОМЕНКЛАТУР'!D:G,4,0) -> 24.3 | S85: =VLOOKUP(A:A,'ИЗ ОСНОВЫ НОМЕНКЛАТУР'!D:H,5,0) -> C | T85: =$R85*D85 -> 0 | U85: =$R85*E85 -> 0 | V85: =$R85*F85 -> 0 | W85: =$R85*G85 -> 0 | X85: =$R85*H85 -> 0 | Y85: =$R85*I85 -> 0 | Z85: =$R85*J85 -> 48600 | AA85: =$R85*K85 -> 72900 | ... AD85: =$R85*N85 -> 0 | AE85: =SUM(T85:AD85) -> 121500
A86: 19*0,8мм ПВХ Базальт AN | D86: 908 | E86: 200 | G86: 404 | I86: 128600 | J86: 7662 | K86: 8000 | L86: 105 | M86: 6400 | N86: 7629 | O86: 159908 | P86: =VLOOKUP(A86,'ИЗ ОСНОВЫ НОМЕНКЛАТУР'!D:E,2,0) -> Кромочные материалы | Q86: =VLOOKUP(A86,'ИЗ ОСНОВЫ НОМЕНКЛАТУР'!D:F,3,0) -> Кромка ПВХ Китай | R86: =VLOOKUP(A:A,'ИЗ ОСНОВЫ НОМЕНКЛАТУР'!D:G,4,0) -> 20.78326 | S86: =VLOOKUP(A:A,'ИЗ ОСНОВЫ НОМЕНКЛАТУР'!D:H,5,0) -> A | T86: =$R86*D86 -> 18871.2 | U86: =$R86*E86 -> 4156.652 | V86: =$R86*F86 -> 0 | W86: =$R86*G86 -> 8396.4369 | X86: =$R86*H86 -> 0 | Y86: =$R86*I86 -> 2672727.2 | Z86: =$R86*J86 -> 159241.34 | AA86: =$R86*K86 -> 166266.08 | ... AD86: =$R86*N86 -> 158555.49 | AE86: =SUM(T86:AD86) -> 3323409.5
A87: 19*0,8мм ПВХ Базальт SJ | J87: 1925 | K87: 10000 | O87: 11925 | P87: =VLOOKUP(A87,'ИЗ ОСНОВЫ НОМЕНКЛАТУР'!D:E,2,0) -> Кромочные материалы | Q87: =VLOOKUP(A87,'ИЗ ОСНОВЫ НОМЕНКЛАТУР'!D:F,3,0) -> Кромка ПВХ Китай | R87: =VLOOKUP(A:A,'ИЗ ОСНОВЫ НОМЕНКЛАТУР'!D:G,4,0) -> 17.6 | S87: =VLOOKUP(A:A,'ИЗ ОСНОВЫ НОМЕНКЛАТУР'!D:H,5,0) -> A | T87: =$R87*D87 -> 0 | U87: =$R87*E87 -> 0 | V87: =$R87*F87 -> 0 | W87: =$R87*G87 -> 0 | X87: =$R87*H87 -> 0 | Y87: =$R87*I87 -> 0 | Z87: =$R87*J87 -> 33880 | AA87: =$R87*K87 -> 176000 | ... AD87: =$R87*N87 -> 0 | AE87: =SUM(T87:AD87) -> 209880
A88: 19*0,8мм ПВХ Бамбук AN | G88: 352 | O88: 352 | P88: =VLOOKUP(A88,'ИЗ ОСНОВЫ НОМЕНКЛАТУР'!D:E,2,0) -> Кромочные материалы | Q88: =VLOOKUP(A88,'ИЗ ОСНОВЫ НОМЕНКЛАТУР'!D:F,3,0) -> Кромка ПВХ Китай | R88: =VLOOKUP(A:A,'ИЗ ОСНОВЫ НОМЕНКЛАТУР'!D:G,4,0) -> 26.772959 | S88: =VLOOKUP(A:A,'ИЗ ОСНОВЫ НОМЕНКЛАТУР'!D:H,5,0) -> B | T88: =$R88*D88 -> 0 | U88: =$R88*E88 -> 0 | V88: =$R88*F88 -> 0 | W88: =$R88*G88 -> 9424.0814 | X88: =$R88*H88 -> 0 | Y88: =$R88*I88 -> 0 | Z88: =$R88*J88 -> 0 | AA88: =$R88*K88 -> 0 | ... AD88: =$R88*N88 -> 0 | AE88: =SUM(T88:AD88) -> 9424.0814
A89: 19*0,8мм ПВХ Бамбук SJ | D89: 33 | G89: 1000 | I89: 5000 | J89: 3688 | K89: 7000 | N89: 7734 | O89: 24455 | P89: =VLOOKUP(A89,'ИЗ ОСНОВЫ НОМЕНКЛАТУР'!D:E,2,0) -> Кромочные материалы | Q89: =VLOOKUP(A89,'ИЗ ОСНОВЫ НОМЕНКЛАТУР'!D:F,3,0) -> Кромка ПВХ Китай | R89: =VLOOKUP(A:A,'ИЗ ОСНОВЫ НОМЕНКЛАТУР'!D:G,4,0) -> 24.750883 | S89: =VLOOKUP(A:A,'ИЗ ОСНОВЫ НОМЕНКЛАТУР'!D:H,5,0) -> B | T89: =$R89*D89 -> 816.77914 | U89: =$R89*E89 -> 0 | V89: =$R89*F89 -> 0 | W89: =$R89*G89 -> 24750.883 | X89: =$R89*H89 -> 0 | Y89: =$R89*I89 -> 123754.41 | Z89: =$R89*J89 -> 91281.256 | AA89: =$R89*K89 -> 173256.18 | ... AD89: =$R89*N89 -> 191423.33 | AE89: =SUM(T89:AD89) -> 605282.84
A90: 19*0,8мм ПВХ Бежевый AN | N90: -63 | O90: -63 | P90: =VLOOKUP(A90,'ИЗ ОСНОВЫ НОМЕНКЛАТУР'!D:E,2,0) -> Кромочные материалы | Q90: =VLOOKUP(A90,'ИЗ ОСНОВЫ НОМЕНКЛАТУР'!D:F,3,0) -> Кромка ПВХ Китай | R90: =VLOOKUP(A:A,'ИЗ ОСНОВЫ НОМЕНКЛАТУР'!D:G,4,0) -> 23.348041 | S90: =VLOOKUP(A:A,'ИЗ ОСНОВЫ НОМЕНКЛАТУР'!D:H,5,0) -> A | T90: =$R90*D90 -> 0 | U90: =$R90*E90 -> 0 | V90: =$R90*F90 -> 0 | W90: =$R90*G90 -> 0 | X90: =$R90*H90 -> 0 | Y90: =$R90*I90 -> 0 | Z90: =$R90*J90 -> 0 | AA90: =$R90*K90 -> 0 | ... AD90: =$R90*N90 -> -1470.9266 | AE90: =SUM(T90:AD90) -> -1470.9266
A91: 19*0,8мм ПВХ Бежевый SJ | G91: 627 | I91: 19000 | J91: 8456 | K91: 15000 | L91: 64 | M91: 6800 | N91: 1563 | O91: 51510 | P91: =VLOOKUP(A91,'ИЗ ОСНОВЫ НОМЕНКЛАТУР'!D:E,2,0) -> Кромочные материалы | Q91: =VLOOKUP(A91,'ИЗ ОСНОВЫ НОМЕНКЛАТУР'!D:F,3,0) -> Кромка ПВХ Китай | R91: =VLOOKUP(A:A,'ИЗ ОСНОВЫ НОМЕНКЛАТУР'!D:G,4,0) -> 19.077207 | S91: =VLOOKUP(A:A,'ИЗ ОСНОВЫ НОМЕНКЛАТУР'!D:H,5,0) -> A | T91: =$R91*D91 -> 0 | U91: =$R91*E91 -> 0 | V91: =$R91*F91 -> 0 | W91: =$R91*G91 -> 11961.409 | X91: =$R91*H91 -> 0 | Y91: =$R91*I91 -> 362466.93 | Z91: =$R91*J91 -> 161316.86 | AA91: =$R91*K91 -> 286158.11 | ... AD91: =$R91*N91 -> 29817.675 | AE91: =SUM(T91:AD91) -> 982666.93
A92: 19*0,8мм ПВХ Белоснежный гладкий AN | N92: 2 | O92: 2 | P92: =VLOOKUP(A92,'ИЗ ОСНОВЫ НОМЕНКЛАТУР'!D:E,2,0) -> Кромочные материалы | Q92: =VLOOKUP(A92,'ИЗ ОСНОВЫ НОМЕНКЛАТУР'!D:F,3,0) -> Кромка ПВХ Китай | R92: =VLOOKUP(A:A,'ИЗ ОСНОВЫ НОМЕНКЛАТУР'!D:G,4,0) -> 20.133662 | S92: =VLOOKUP(A:A,'ИЗ ОСНОВЫ НОМЕНКЛАТУР'!D:H,5,0) -> B | T92: =$R92*D92 -> 0 | U92: =$R92*E92 -> 0 | V92: =$R92*F92 -> 0 | W92: =$R92*G92 -> 0 | X92: =$R92*H92 -> 0 | Y92: =$R92*I92 -> 0 | Z92: =$R92*J92 -> 0 | AA92: =$R92*K92 -> 0 | ... AD92: =$R92*N92 -> 40.267323 | AE92: =SUM(T92:AD92) -> 40.267323
A93: 19*0,8мм ПВХ Белоснежный гладкий SJ | I93: 21000 | J93: 4487 | K93: 5000 | N93: 48 | O93: 30535 | P93: =VLOOKUP(A93,'ИЗ ОСНОВЫ НОМЕНКЛАТУР'!D:E,2,0) -> Кромочные материалы | Q93: =VLOOKUP(A93,'ИЗ ОСНОВЫ НОМЕНКЛАТУР'!D:F,3,0) -> Кромка ПВХ Китай | R93: =VLOOKUP(A:A,'ИЗ ОСНОВЫ НОМЕНКЛАТУР'!D:G,4,0) -> 17.6 | S93: =VLOOKUP(A:A,'ИЗ ОСНОВЫ НОМЕНКЛАТУР'!D:H,5,0) -> B | T93: =$R93*D93 -> 0 | U93: =$R93*E93 -> 0 | V93: =$R93*F93 -> 0 | W93: =$R93*G93 -> 0 | X93: =$R93*H93 -> 0 | Y93: =$R93*I93 -> 369600 | Z93: =$R93*J93 -> 78971.2 | AA93: =$R93*K93 -> 88000 | ... AD93: =$R93*N93 -> 844.8 | AE93: =SUM(T93:AD93) -> 537416
A94: 19*0,8мм ПВХ Белый (Гладкий) AN | G94: 68 | J94: 4773 | L94: 15 | N94: 1439 | O94: 6295 | P94: =VLOOKUP(A94,'ИЗ ОСНОВЫ НОМЕНКЛАТУР'!D:E,2,0) -> Кромочные материалы | Q94: =VLOOKUP(A94,'ИЗ ОСНОВЫ НОМЕНКЛАТУР'!D:F,3,0) -> Кромка ПВХ Китай | R94: =VLOOKUP(A:A,'ИЗ ОСНОВЫ НОМЕНКЛАТУР'!D:G,4,0) -> 22.252896 | S94: =VLOOKUP(A:A,'ИЗ ОСНОВЫ НОМЕНКЛАТУР'!D:H,5,0) -> A | T94: =$R94*D94 -> 0 | U94: =$R94*E94 -> 0 | V94: =$R94*F94 -> 0 | W94: =$R94*G94 -> 1513.1969 | X94: =$R94*H94 -> 0 | Y94: =$R94*I94 -> 0 | Z94: =$R94*J94 -> 106213.07 | AA94: =$R94*K94 -> 0 | ... AD94: =$R94*N94 -> 32021.918 | AE94: =SUM(T94:AD94) -> 140081.98
A95: 19*0,8мм ПВХ Белый (Гладкий) KZ | N95: 3264 | O95: 3264 | P95: =VLOOKUP(A95,'ИЗ ОСНОВЫ НОМЕНКЛАТУР'!D:E,2,0) -> Кромочные материалы | Q95: =VLOOKUP(A95,'ИЗ ОСНОВЫ НОМЕНКЛАТУР'!D:F,3,0) -> Кромка ПВХ Казахстан | R95: =VLOOKUP(A:A,'ИЗ ОСНОВЫ НОМЕНКЛАТУР'!D:G,4,0) -> 25.70815 | S95: =VLOOKUP(A:A,'ИЗ ОСНОВЫ НОМЕНКЛАТУР'!D:H,5,0) -> B | T95: =$R95*D95 -> 0 | U95: =$R95*E95 -> 0 | V95: =$R95*F95 -> 0 | W95: =$R95*G95 -> 0 | X95: =$R95*H95 -> 0 | Y95: =$R95*I95 -> 0 | Z95: =$R95*J95 -> 0 | AA95: =$R95*K95 -> 0 | ... AD95: =$R95*N95 -> 83911.402 | AE95: =SUM(T95:AD95) -> 83911.402
A96: 19*0,8мм ПВХ Белый (Гладкий) SJ | G96: 1800 | I96: 15000 | J96: 10000 | K96: 5000 | N96: 25000 | O96: 56800 | P96: =VLOOKUP(A96,'ИЗ ОСНОВЫ НОМЕНКЛАТУР'!D:E,2,0) -> Кромочные материалы | Q96: =VLOOKUP(A96,'ИЗ ОСНОВЫ НОМЕНКЛАТУР'!D:F,3,0) -> Кромка ПВХ Китай | R96: =VLOOKUP(A:A,'ИЗ ОСНОВЫ НОМЕНКЛАТУР'!D:G,4,0) -> 17.8 | S96: =VLOOKUP(A:A,'ИЗ ОСНОВЫ НОМЕНКЛАТУР'!D:H,5,0) -> C | T96: =$R96*D96 -> 0 | U96: =$R96*E96 -> 0 | V96: =$R96*F96 -> 0 | W96: =$R96*G96 -> 32040 | X96: =$R96*H96 -> 0 | Y96: =$R96*I96 -> 267000 | Z96: =$R96*J96 -> 178000 | AA96: =$R96*K96 -> 89000 | ... AD96: =$R96*N96 -> 445000 | AE96: =SUM(T96:AD96) -> 1011040
A97: 19*0,8мм ПВХ Белый AN | D97: 81362 | E97: 400 | G97: 4546 | I97: 2774800 | J97: 98688 | K97: 176655 | L97: 4255 | M97: 232800 | N97: 23973 | O97: 3397479 | P97: =VLOOKUP(A97,'ИЗ ОСНОВЫ НОМЕНКЛАТУР'!D:E,2,0) -> Кромочные материалы | Q97: =VLOOKUP(A97,'ИЗ ОСНОВЫ НОМЕНКЛАТУР'!D:F,3,0) -> Кромка ПВХ Китай | R97: =VLOOKUP(A:A,'ИЗ ОСНОВЫ НОМЕНКЛАТУР'!D:G,4,0) -> 18.061539 | S97: =VLOOKUP(A:A,'ИЗ ОСНОВЫ НОМЕНКЛАТУР'!D:H,5,0) -> A | T97: =$R97*D97 -> 1469523 | U97: =$R97*E97 -> 7224.6157 | V97: =$R97*F97 -> 0 | W97: =$R97*G97 -> 82107.758 | X97: =$R97*H97 -> 0 | Y97: =$R97*I97 -> 50117159 | Z97: =$R97*J97 -> 1782457.2 | AA97: =$R97*K97 -> 3190661.2 | ... AD97: =$R97*N97 -> 432989.28 | AE97: =SUM(T97:AD97) -> 61363701
A98: 19*0,8мм ПВХ Белый SJ | I98: 104000 | J98: 43863 | K98: 52000 | O98: 199863 | P98: =VLOOKUP(A98,'ИЗ ОСНОВЫ НОМЕНКЛАТУР'!D:E,2,0) -> Кромочные материалы | Q98: =VLOOKUP(A98,'ИЗ ОСНОВЫ НОМЕНКЛАТУР'!D:F,3,0) -> Кромка ПВХ Китай | R98: =VLOOKUP(A:A,'ИЗ ОСНОВЫ НОМЕНКЛАТУР'!D:G,4,0) -> 16.403402 | S98: =VLOOKUP(A:A,'ИЗ ОСНОВЫ НОМЕНКЛАТУР'!D:H,5,0) -> A | T98: =$R98*D98 -> 0 | U98: =$R98*E98 -> 0 | V98: =$R98*F98 -> 0 | W98: =$R98*G98 -> 0 | X98: =$R98*H98 -> 0 | Y98: =$R98*I98 -> 1705953.8 | Z98: =$R98*J98 -> 719502.41 | AA98: =$R98*K98 -> 852976.89 | ... AD98: =$R98*N98 -> 0 | AE98: =SUM(T98:AD98) -> 3278433.1
A99: 19*0,8мм ПВХ Белый Бриллиант 8681 SJ | J99: 2000 | K99: 3000 | O99: 5000 | P99: =VLOOKUP(A99,'ИЗ ОСНОВЫ НОМЕНКЛАТУР'!D:E,2,0) -> Кромочные материалы | Q99: =VLOOKUP(A99,'ИЗ ОСНОВЫ НОМЕНКЛАТУР'!D:F,3,0) -> Кромка ПВХ Китай | R99: =VLOOKUP(A:A,'ИЗ ОСНОВЫ НОМЕНКЛАТУР'!D:G,4,0) -> 18 | S99: =VLOOKUP(A:A,'ИЗ ОСНОВЫ НОМЕНКЛАТУР'!D:H,5,0) -> C | T99: =$R99*D99 -> 0 | U99: =$R99*E99 -> 0 | V99: =$R99*F99 -> 0 | W99: =$R99*G99 -> 0 | X99: =$R99*H99 -> 0 | Y99: =$R99*I99 -> 0 | Z99: =$R99*J99 -> 36000 | AA99: =$R99*K99 -> 54000 | ... AD99: =$R99*N99 -> 0 | AE99: =SUM(T99:AD99) -> 90000
A100: 19*0,8мм ПВХ Береза Мраморная AN | D100: 3681 | E100: 200 | G100: 399 | J100: 2358 | K100: 4000 | L100: 129 | M100: 400 | N100: 3686 | O100: 14853 | P100: =VLOOKUP(A100,'ИЗ ОСНОВЫ НОМЕНКЛАТУР'!D:E,2,0) -> Кромочные материалы | Q100: =VLOOKUP(A100,'ИЗ ОСНОВЫ НОМЕНКЛАТУР'!D:F,3,0) -> Кромка ПВХ Китай | R100: =VLOOKUP(A:A,'ИЗ ОСНОВЫ НОМЕНКЛАТУР'!D:G,4,0) -> 26.767395 | S100: =VLOOKUP(A:A,'ИЗ ОСНОВЫ НОМЕНКЛАТУР'!D:H,5,0) -> B | T100: =$R100*D100 -> 98530.782 | U100: =$R100*E100 -> 5353.4791 | V100: =$R100*F100 -> 0 | W100: =$R100*G100 -> 10680.191 | X100: =$R100*H100 -> 0 | Y100: =$R100*I100 -> 0 | Z100: =$R100*J100 -> 63117.518 | AA100: =$R100*K100 -> 107069.58 | ... AD100: =$R100*N100 -> 98664.619 | AE100: =SUM(T100:AD100) -> 397576.12
A101: 19*0,8мм ПВХ Береза Мраморная SJ | D101: 801 | E101: 200 | I101: 10000 | J101: 1780 | N101: 378 | O101: 13159 | P101: =VLOOKUP(A101,'ИЗ ОСНОВЫ НОМЕНКЛАТУР'!D:E,2,0) -> Кромочные материалы | Q101: =VLOOKUP(A101,'ИЗ ОСНОВЫ НОМЕНКЛАТУР'!D:F,3,0) -> Кромка ПВХ Китай | R101: =VLOOKUP(A:A,'ИЗ ОСНОВЫ НОМЕНКЛАТУР'!D:G,4,0) -> 24.002487 | S101: =VLOOKUP(A:A,'ИЗ ОСНОВЫ НОМЕНКЛАТУР'!D:H,5,0) -> B | T101: =$R101*D101 -> 19225.992 | U101: =$R101*E101 -> 4800.4974 | V101: =$R101*F101 -> 0 | W101: =$R101*G101 -> 0 | X101: =$R101*H101 -> 0 | Y101: =$R101*I101 -> 240024.87 | Z101: =$R101*J101 -> 42724.427 | AA101: =$R101*K101 -> 0 | ... AD101: =$R101*N101 -> 9072.94 | AE101: =SUM(T101:AD101) -> 315848.72
...

Sheet ПРОДАЖИ
D1: qty | E1: qty | F1: qty | G1: qty | H1: qty | I1: qty | J1: qty | K1: qty | L1: amnt | M1: amnt | N1: amnt | O1: amnt | P1: amnt | Q1: amnt | R1: amnt | S1: amnt | T1: AMS ПО СЕБ.СТ. | U1: AMS ПО СЕБ.СТ. | V1: AMS ПО СЕБ.СТ. | W1: AMS ПО СЕБ.СТ. | X1: AMS ПО СЕБ.СТ. | Y1: AMS ПО СЕБ.СТ. | Z1: AMS ПО СЕБ.СТ. | AA1: AMS ПО СЕБ.СТ. | AB1: AMS ПО СЕБ.СТ.
A2: КАТЕГОРИЯ | B2: ПОДКАТЕГОРИЯ | C2: Номенклатура | D2: ТД Казыбаева ФУРНИТУРА магазин ( продажи 01.07.2024-01.07.2025 гг.) | E2: Казыбаева Склад Фурнитура TRADE ( продажи 01.07.2024-01.07.2025 гг.) | F2: Барыс Склад Фурнитура TRADE ( продажи 01.07.2024-01.07.2025 гг.) | G2: АО Склад Фурнитура TRADE ( продажи 01.07.2024-01.07.2025 гг.) | H2: Магазин фурнитуры ( продажи 01.07.2024-01.07.2025 гг.) | I2: склад фурнитура № 1 ( продажи 01.07.2024-01.07.2025 гг.) | J2: 6 Склад фурнитуры Овощная база Магазин ( продажи 01.07.2024-01.07.2025 гг.) | K2: 4 Склад фурнитуры АЗМ Шымкент Овощная база ( продажи 01.07.2024-01.07.2025 гг.) | L2: ТД Казыбаева ФУРНИТУРА магазин ( продажи 01.07.2024-01.07.2025 гг.) | M2: Казыбаева Склад Фурнитура TRADE ( продажи 01.07.2024-01.07.2025 гг.) | N2: Барыс Склад Фурнитура TRADE ( продажи 01.07.2024-01.07.2025 гг.) | O2: АО Склад Фурнитура TRADE ( продажи 01.07.2024-01.07.2025 гг.) | P2: Магазин фурнитуры ( продажи 01.07.2024-01.07.2025 гг.) | Q2: склад фурнитура № 1 ( продажи 01.07.2024-01.07.2025 гг.) | R2: 6 Склад фурнитуры Овощная база Магазин ( продажи 01.07.2024-01.07.2025 гг.) | S2: 4 Склад фурнитуры АЗМ Шымкент Овощная база ( продажи 01.07.2024-01.07.2025 гг.) | T2: ТД Казыбаева ФУРНИТУРА магазин ( продажи 01.07.2024-01.07.2025 гг.) | U2: Казыбаева Склад Фурнитура TRADE ( продажи 01.07.2024-01.07.2025 гг.) | V2: Барыс Склад Фурнитура TRADE ( продажи 01.07.2024-01.07.2025 гг.) | W2: АО Склад Фурнитура TRADE ( продажи 01.07.2024-01.07.2025 гг.) | X2: Магазин фурнитуры ( продажи 01.07.2024-01.07.2025 гг.) | Y2: склад фурнитура № 1 ( продажи 01.07.2024-01.07.2025 гг.) | Z2: 6 Склад фурнитуры Овощная база Магазин ( продажи 01.07.2024-01.07.2025 гг.) | AA2: 4 Склад фурнитуры АЗМ Шымкент Овощная база ( продажи 01.07.2024-01.07.2025 гг.) | AB2: тотал AMS | AC2: кат | AD2: кат-2 | AE2: abc
A3: Кромочные материалы | D3: 0 | E3: 0 | F3: 0 | G3: 0 | H3: 0 | I3: 0 | J3: 0 | K3: 0 | L3: 0 | M3: 0 | N3: 0 | O3: 0 | P3: 0 | Q3: 0 | R3: 0 | S3: 0 | T3: =L3/12 -> 0 | U3: =M3/12 -> 0 | V3: =N3/12 -> 0 | W3: =O3/12 -> 0 | X3: =P3/12 -> 0 | Y3: =Q3/12 -> 0 | Z3: =R3/12 -> 0 | AA3: =S3/12 -> 0 | AB3: =T3+U3+V3+W3+X3+Y3+Z3+AA3 -> 0 | AC3: =VLOOKUP(ПРОДАЖИ!C:C,'ИЗ ОСНОВЫ НОМЕНКЛАТУР'!D:E,2,0) -> #N/A | AD3: =VLOOKUP(C:C,'ИЗ ОСНОВЫ НОМЕНКЛАТУР'!D:F,3,0) -> #N/A | AE3: =VLOOKUP(C:C,'ИЗ ОСНОВЫ НОМЕНКЛАТУР'!D:H,5,0) -> #N/A
A4: Кромочные материалы | B4: Кромка ПВХ | D4: 0 | E4: 0 | F4: 0 | G4: 0 | H4: 0 | I4: 0 | J4: 0 | K4: 0 | L4: 0 | M4: 0 | N4: 0 | O4: 0 | P4: 0 | Q4: 0 | R4: 0 | S4: 0 | T4: =L4/12 -> 0 | U4: =M4/12 -> 0 | V4: =N4/12 -> 0 | W4: =O4/12 -> 0 | X4: =P4/12 -> 0 | Y4: =Q4/12 -> 0 | Z4: =R4/12 -> 0 | AA4: =S4/12 -> 0 | AB4: =T4+U4+V4+W4+X4+Y4+Z4+AA4 -> 0 | AC4: =VLOOKUP(ПРОДАЖИ!C:C,'ИЗ ОСНОВЫ НОМЕНКЛАТУР'!D:E,2,0) -> #N/A | AD4: =VLOOKUP(C:C,'ИЗ ОСНОВЫ НОМЕНКЛАТУР'!D:F,3,0) -> #N/A | AE4: =VLOOKUP(C:C,'ИЗ ОСНОВЫ НОМЕНКЛАТУР'!D:H,5,0) -> #N/A
A5: Кромочные материалы | B5: Кромка ПВХ Китай | D5: 0 | E5: 0 | F5: 0 | G5: 0 | H5: 0 | I5: 0 | J5: 0 | K5: 0 | L5: 0 | M5: 0 | N5: 0 | O5: 0 | P5: 0 | Q5: 0 | R5: 0 | S5: 0 | T5: =L5/12 -> 0 | U5: =M5/12 -> 0 | V5: =N5/12 -> 0 | W5: =O5/12 -> 0 | X5: =P5/12 -> 0 | Y5: =Q5/12 -> 0 | Z5: =R5/12 -> 0 | AA5: =S5/12 -> 0 | AB5: =T5+U5+V5+W5+X5+Y5+Z5+AA5 -> 0 | AC5: =VLOOKUP(ПРОДАЖИ!C:C,'ИЗ ОСНОВЫ НОМЕНКЛАТУР'!D:E,2,0) -> #N/A | AD5: =VLOOKUP(C:C,'ИЗ ОСНОВЫ НОМЕНКЛАТУР'!D:F,3,0) -> #N/A | AE5: =VLOOKUP(C:C,'ИЗ ОСНОВЫ НОМЕНКЛАТУР'!D:H,5,0) -> #N/A
A6: Кромочные материалы | B6: 19*0,8мм ПВХ | D6: 0 | E6: 0 | F6: 0 | G6: 0 | H6: 0 | I6: 0 | J6: 0 | K6: 0 | L6: 0 | M6: 0 | N6: 0 | O6: 0 | P6: 0 | Q6: 0 | R6: 0 | S6: 0 | T6: =L6/12 -> 0 | U6: =M6/12 -> 0 | V6: =N6/12 -> 0 | W6: =O6/12 -> 0 | X6: =P6/12 -> 0 | Y6: =Q6/12 -> 0 | Z6: =R6/12 -> 0 | AA6: =S6/12 -> 0 | AB6: =T6+U6+V6+W6+X6+Y6+Z6+AA6 -> 0 | AC6: =VLOOKUP(ПРОДАЖИ!C:C,'ИЗ ОСНОВЫ НОМЕНКЛАТУР'!D:E,2,0) -> #N/A | AD6: =VLOOKUP(C:C,'ИЗ ОСНОВЫ НОМЕНКЛАТУР'!D:F,3,0) -> #N/A | AE6: =VLOOKUP(C:C,'ИЗ ОСНОВЫ НОМЕНКЛАТУР'!D:H,5,0) -> #N/A
A7: Кромочные материалы | C7: 19*0,8мм ПВХ Белый AN | D7: 1397761 | E7: 520079 | F7: 1709519 | G7: 117814 | H7: 738367 | I7: 1546280 | J7: 1800 | K7: 1782465 | L7: 27977554 | M7: 9629845.9 | N7: 31636898 | O7: 2189874.1 | P7: 13645556 | Q7: 27971742 | R7: 29186 | S7: 28053748 | T7: =L7/12 -> 2331462.8 | U7: =M7/12 -> 802487.16 | V7: =N7/12 -> 2636408.2 | W7: =O7/12 -> 182489.51 | X7: =P7/12 -> 1137129.7 | Y7: =Q7/12 -> 2330978.5 | Z7: =R7/12 -> 2432.1667 | AA7: =S7/12 -> 2337812.3 | AB7: =T7+U7+V7+W7+X7+Y7+Z7+AA7 -> 11761200 | AC7: =VLOOKUP(ПРОДАЖИ!C:C,'ИЗ ОСНОВЫ НОМЕНКЛАТУР'!D:E,2,0) -> Кромочные материалы | AD7: =VLOOKUP(C:C,'ИЗ ОСНОВЫ НОМЕНКЛАТУР'!D:F,3,0) -> Кромка ПВХ Китай | AE7: =VLOOKUP(C:C,'ИЗ ОСНОВЫ НОМЕНКЛАТУР'!D:H,5,0) -> A
A8: Кромочные материалы | C8: 19*0,8мм ПВХ Дуб сонома AN | D8: 168499 | E8: 77200 | F8: 132474 | G8: 10134 | H8: 129885 | I8: 208513 | J8: 1600 | K8: 58766 | L8: 4184268.9 | M8: 1939265.1 | N8: 3247768 | O8: 264045.7 | P8: 3315092.6 | Q8: 5264210.6 | R8: 38750.81 | S8: 1452541.6 | T8: =L8/12 -> 348689.07 | U8: =M8/12 -> 161605.42 | V8: =N8/12 -> 270647.34 | W8: =O8/12 -> 22003.808 | X8: =P8/12 -> 276257.71 | Y8: =Q8/12 -> 438684.22 | Z8: =R8/12 -> 3229.2342 | AA8: =S8/12 -> 121045.13 | AB8: =T8+U8+V8+W8+X8+Y8+Z8+AA8 -> 1642161.9 | AC8: =VLOOKUP(ПРОДАЖИ!C:C,'ИЗ ОСНОВЫ НОМЕНКЛАТУР'!D:E,2,0) -> Кромочные материалы | AD8: =VLOOKUP(C:C,'ИЗ ОСНОВЫ НОМЕНКЛАТУР'!D:F,3,0) -> Кромка ПВХ Китай | AE8: =VLOOKUP(C:C,'ИЗ ОСНОВЫ НОМЕНКЛАТУР'!D:H,5,0) -> A
A9: Кромочные материалы | C9: 19*0,8мм ПВХ Дуб Вотан AN | D9: 176065 | E9: 18200 | F9: 180289 | G9: 22501 | H9: 166449 | I9: 99000 | J9: 800 | K9: 117622 | L9: 5120115.9 | M9: 530730.86 | N9: 4451845.3 | O9: 561167.57 | P9: 4249831.3 | Q9: 2532691.8 | R9: 20076.04 | S9: 2951405.9 | T9: =L9/12 -> 426676.33 | U9: =M9/12 -> 44227.572 | V9: =N9/12 -> 370987.1 | W9: =O9/12 -> 46763.964 | X9: =P9/12 -> 354152.61 | Y9: =Q9/12 -> 211057.65 | Z9: =R9/12 -> 1673.0033 | AA9: =S9/12 -> 245950.49 | AB9: =T9+U9+V9+W9+X9+Y9+Z9+AA9 -> 1701488.7 | AC9: =VLOOKUP(ПРОДАЖИ!C:C,'ИЗ ОСНОВЫ НОМЕНКЛАТУР'!D:E,2,0) -> Кромочные материалы | AD9: =VLOOKUP(C:C,'ИЗ ОСНОВЫ НОМЕНКЛАТУР'!D:F,3,0) -> Кромка ПВХ Китай | AE9: =VLOOKUP(C:C,'ИЗ ОСНОВЫ НОМЕНКЛАТУР'!D:H,5,0) -> A
A10: Кромочные материалы | C10: 19*0,8мм ПВХ Серый SJ | D10: 122753 | E10: 24800 | F10: 98781 | G10: 12107 | H10: 104677 | I10: 66700 | J10: 400 | K10: 127152 | L10: 2217369.3 | M10: 452489.3 | N10: 1783910.9 | O10: 222545.7 | P10: 1913177.5 | Q10: 1208221.9 | R10: 7073.17 | S10: 2322400.6 | T10: =L10/12 -> 184780.77 | U10: =M10/12 -> 37707.442 | V10: =N10/12 -> 148659.24 | W10: =O10/12 -> 18545.475 | X10: =P10/12 -> 159431.46 | Y10: =Q10/12 -> 100685.16 | Z10: =R10/12 -> 589.43083 | AA10: =S10/12 -> 193533.38 | AB10: =T10+U10+V10+W10+X10+Y10+Z10+AA10 -> 843932.36 | AC10: =VLOOKUP(ПРОДАЖИ!C:C,'ИЗ ОСНОВЫ НОМЕНКЛАТУР'!D:E,2,0) -> Кромочные материалы | AD10: =VLOOKUP(C:C,'ИЗ ОСНОВЫ НОМЕНКЛАТУР'!D:F,3,0) -> Кромка ПВХ Китай | AE10: =VLOOKUP(C:C,'ИЗ ОСНОВЫ НОМЕНКЛАТУР'!D:H,5,0) -> A
A11: Кромочные материалы | C11: 19*0,8мм ПВХ Тэффи SJ | D11: 60185 | E11: 2000 | F11: 50983 | G11: 6000 | H11: 111813 | I11: 72900 | J11: 600 | K11: 61169 | L11: 1059256 | M11: 35200 | N11: 898551.38 | O11: 106500 | P11: 1993577.2 | Q11: 1297907.9 | R11: 10679.37 | S11: 1091571.7 | T11: =L11/12 -> 88271.333 | U11: =M11/12 -> 2933.3333 | V11: =N11/12 -> 74879.282 | W11: =O11/12 -> 8875 | X11: =P11/12 -> 166131.43 | Y11: =Q11/12 -> 108158.99 | Z11: =R11/12 -> 889.9475 | AA11: =S11/12 -> 90964.308 | AB11: =T11+U11+V11+W11+X11+Y11+Z11+AA11 -> 541103.63 | AC11: =VLOOKUP(ПРОДАЖИ!C:C,'ИЗ ОСНОВЫ НОМЕНКЛАТУР'!D:E,2,0) -> Кромочные материалы | AD11: =VLOOKUP(C:C,'ИЗ ОСНОВЫ НОМЕНКЛАТУР'!D:F,3,0) -> Кромка ПВХ Китай | AE11: =VLOOKUP(C:C,'ИЗ ОСНОВЫ НОМЕНКЛАТУР'!D:H,5,0) -> A
A12: Кромочные материалы | C12: 19*0,8мм ПВХ Тэффи AN | D12: 103898 | E12: 9020 | F12: 50331 | G12: 8260 | H12: 66838 | I12: 42400 | J12: 600 | K12: 96259 | L12: 1957051.9 | M12: 160613.16 | N12: 960658.82 | O12: 155643.99 | P12: 1906615.7 | Q12: 1278182.9 | R12: 10680 | S12: 1724703.3 | T12: =L12/12 -> 163087.66 | U12: =M12/12 -> 13384.43 | V12: =N12/12 -> 80054.902 | W12: =O12/12 -> 12970.332 | X12: =P12/12 -> 158884.64 | Y12: =Q12/12 -> 106515.24 | Z12: =R12/12 -> 890 | AA12: =S12/12 -> 143725.27 | AB12: =T12+U12+V12+W12+X12+Y12+Z12+AA12 -> 679512.48 | AC12: =VLOOKUP(ПРОДАЖИ!C:C,'ИЗ ОСНОВЫ НОМЕНКЛАТУР'!D:E,2,0) -> Кромочные материалы | AD12: =VLOOKUP(C:C,'ИЗ ОСНОВЫ НОМЕНКЛАТУР'!D:F,3,0) -> Кромка ПВХ Китай | AE12: =VLOOKUP(C:C,'ИЗ ОСНОВЫ НОМЕНКЛАТУР'!D:H,5,0) -> A
A13: Кромочные материалы | C13: 19*0,8мм ПВХ Черный AN | D13: 153308 | E13: 37858 | F13: 97984 | G13: 5878 | H13: 32055 | I13: 39710 | J13: 400 | K13: 70396 | L13: 2902112.4 | M13: 681709.41 | N13: 1919044 | O13: 109641.97 | P13: 592327.77 | Q13: 742134.46 | R13: 9726.91 | S13: 1276862.4 | T13: =L13/12 -> 241842.7 | U13: =M13/12 -> 56809.118 | V13: =N13/12 -> 159920.33 | W13: =O13/12 -> 9136.8308 | X13: =P13/12 -> 49360.647 | Y13: =Q13/12 -> 61844.538 | Z13: =R13/12 -> 810.57583 | AA13: =S13/12 -> 106405.2 | AB13: =T13+U13+V13+W13+X13+Y13+Z13+AA13 -> 686129.94 | AC13: =VLOOKUP(ПРОДАЖИ!C:C,'ИЗ ОСНОВЫ НОМЕНКЛАТУР'!D:E,2,0) -> Кромочные материалы | AD13: =VLOOKUP(C:C,'ИЗ ОСНОВЫ НОМЕНКЛАТУР'!D:F,3,0) -> Кромка ПВХ Китай | AE13: =VLOOKUP(C:C,'ИЗ ОСНОВЫ НОМЕНКЛАТУР'!D:H,5,0) -> A
A14: Кромочные материалы | C14: 19*0,8мм ПВХ Белый (Гладкий) AN | D14: 343849 | E14: 23000 | F14: 136196 | G14: 29502 | H14: 49162 | I14: 42240 | J14: 803 | K14: 159220 | L14: 7785864.4 | M14: 510245.27 | N14: 3164468.7 | O14: 641148.8 | P14: 1089334.8 | Q14: 957704.07 | R14: 15979.7 | S14: 3280901.8 | T14: =L14/12 -> 648822.03 | U14: =M14/12 -> 42520.439 | V14: =N14/12 -> 263705.72 | W14: =O14/12 -> 53429.067 | X14: =P14/12 -> 90777.9 | Y14: =Q14/12 -> 79808.673 | Z14: =R14/12 -> 1331.6417 | AA14: =S14/12 -> 273408.49 | AB14: =T14+U14+V14+W14+X14+Y14+Z14+AA14 -> 1453804 | AC14: =VLOOKUP(ПРОДАЖИ!C:C,'ИЗ ОСНОВЫ НОМЕНКЛАТУР'!D:E,2,0) -> Кромочные материалы | AD14: =VLOOKUP(C:C,'ИЗ ОСНОВЫ НОМЕНКЛАТУР'!D:F,3,0) -> Кромка ПВХ Китай | AE14: =VLOOKUP(C:C,'ИЗ ОСНОВЫ НОМЕНКЛАТУР'!D:H,5,0) -> A
A15: Кромочные материалы | C15: 19*0,8мм ПВХ Вулканический серый AN | D15: 81600 | E15: 3000 | F15: 31118 | G15: 6151 | H15: 29450 | I15: 12210 | J15: 800 | K15: 59867 | L15: 1891308.8 | M15: 69329.63 | N15: 718946.34 | O15: 142001.08 | P15: 680434.8 | Q15: 282135.48 | R15: 18449.19 | S15: 1378481.5 | T15: =L15/12 -> 157609.07 | U15: =M15/12 -> 5777.4692 | V15: =N15/12 -> 59912.195 | W15: =O15/12 -> 11833.423 | X15: =P15/12 -> 56702.9 | Y15: =Q15/12 -> 23511.29 | Z15: =R15/12 -> 1537.4325 | AA15: =S15/12 -> 114873.46 | AB15: =T15+U15+V15+W15+X15+Y15+Z15+AA15 -> 431757.24 | AC15: =VLOOKUP(ПРОДАЖИ!C:C,'ИЗ ОСНОВЫ НОМЕНКЛАТУР'!D:E,2,0) -> Кромочные материалы | AD15: =VLOOKUP(C:C,'ИЗ ОСНОВЫ НОМЕНКЛАТУР'!D:F,3,0) -> Кромка ПВХ Китай | AE15: =VLOOKUP(C:C,'ИЗ ОСНОВЫ НОМЕНКЛАТУР'!D:H,5,0) -> A
A16: Кромочные материалы | C16: 19*0,8мм ПВХ Антрацит AN | D16: 118711 | E16: 8700 | F16: 50202 | G16: 3932 | H16: 29463 | I16: 19430 | J16: 1000 | K16: 115269 | L16: 2396709.4 | M16: 173941.18 | N16: 1039548.6 | O16: 80475.7 | P16: 591737.27 | Q16: 393747.56 | R16: 19482.88 | S16: 2168650.9 | T16: =L16/12 -> 199725.79 | U16: =M16/12 -> 14495.098 | V16: =N16/12 -> 86629.048 | W16: =O16/12 -> 6706.3083 | X16: =P16/12 -> 49311.439 | Y16: =Q16/12 -> 32812.297 | Z16: =R16/12 -> 1623.5733 | AA16: =S16/12 -> 180720.91 | AB16: =T16+U16+V16+W16+X16+Y16+Z16+AA16 -> 572024.46 | AC16: =VLOOKUP(ПРОДАЖИ!C:C,'ИЗ ОСНОВЫ НОМЕНКЛАТУР'!D:E,2,0) -> Кромочные материалы | AD16: =VLOOKUP(C:C,'ИЗ ОСНОВЫ НОМЕНКЛАТУР'!D:F,3,0) -> Кромка ПВХ Китай | AE16: =VLOOKUP(C:C,'ИЗ ОСНОВЫ НОМЕНКЛАТУР'!D:H,5,0) -> A
A17: Кромочные материалы | C17: 19*0,8мм ПВХ Ясень шимо светлый AN | D17: 72133 | E17: 58800 | F17: 25854 | G17: 2165 | H17: 22287 | I17: 14700 | J17: 200 | K17: 5849 | L17: 1851227.9 | M17: 1414097.4 | N17: 668558.86 | O17: 55150.49 | P17: 542383.41 | Q17: 369403.04 | R17: 5716.37 | S17: 151929.71 | T17: =L17/12 -> 154268.99 | U17: =M17/12 -> 117841.45 | V17: =N17/12 -> 55713.238 | W17: =O17/12 -> 4595.8742 | X17: =P17/12 -> 45198.618 | Y17: =Q17/12 -> 30783.587 | Z17: =R17/12 -> 476.36417 | AA17: =S17/12 -> 12660.809 | AB17: =T17+U17+V17+W17+X17+Y17+Z17+AA17 -> 421538.93 | AC17: =VLOOKUP(ПРОДАЖИ!C:C,'ИЗ ОСНОВЫ НОМЕНКЛАТУР'!D:E,2,0) -> Кромочные материалы | AD17: =VLOOKUP(C:C,'ИЗ ОСНОВЫ НОМЕНКЛАТУР'!D:F,3,0) -> Кромка ПВХ Китай | AE17: =VLOOKUP(C:C,'ИЗ ОСНОВЫ НОМЕНКЛАТУР'!D:H,5,0) -> A
A18: Кромочные материалы | C18: 19*0,8мм ПВХ Серый AN | D18: 99580 | E18: 3816 | F18: 42073 | G18: 6897 | H18: 51073 | I18: 37950 | J18: 200 | K18: 44879 | L18: 2043489.7 | M18: 78275.53 | N18: 863957.02 | O18: 141437.56 | P18: 1051446 | Q18: 781007.89 | R18: 4688.14 | S18: 926500.81 | T18: =L18/12 -> 170290.81 | U18: =M18/12 -> 6522.9608 | V18: =N18/12 -> 71996.418 | W18: =O18/12 -> 11786.463 | X18: =P18/12 -> 87620.502 | Y18: =Q18/12 -> 65083.991 | Z18: =R18/12 -> 390.67833 | AA18: =S18/12 -> 77208.401 | AB18: =T18+U18+V18+W18+X18+Y18+Z18+AA18 -> 490900.22 | AC18: =VLOOKUP(ПРОДАЖИ!C:C,'ИЗ ОСНОВЫ НОМЕНКЛАТУР'!D:E,2,0) -> Кромочные материалы | AD18: =VLOOKUP(C:C,'ИЗ ОСНОВЫ НОМЕНКЛАТУР'!D:F,3,0) -> Кромка ПВХ Китай | AE18: =VLOOKUP(C:C,'ИЗ ОСНОВЫ НОМЕНКЛАТУР'!D:H,5,0) -> A
... A213: Кромочные материалы | C213: 19*0,8мм ПВХ Ена AN | D213: 557 | E213: 0 | F213: 500 | G213: 0 | H213: 934 | I213: 400 | J213: 200 | K213: 2664 | L213: 20218.59 | M213: 0 | N213: 118617.59 | O213: 0 | P213: 103667.62 | Q213: 44397.27 | R213: 6209.73 | S213: 82713.6 | T213: =L213/12 -> 1684.8825 | U213: =M213/12 -> 0 | V213: =N213/12 -> 9884.7992 | W213: =O213/12 -> 0 | X213: =P213/12 -> 8638.9683 | Y213: =Q213/12 -> 3699.7725 | Z213: =R213/12 -> 517.4775 | AA213: =S213/12 -> 6892.8 | AB213: =T213+U213+V213+W213+X213+Y213+Z213+AA213 -> 31318.7 | AC213: =VLOOKUP(ПРОДАЖИ!C:C,'ИЗ ОСНОВЫ НОМЕНКЛАТУР'!D:E,2,0) -> Кромочные материалы | AD213: =VLOOKUP(C:C,'ИЗ ОСНОВЫ НОМЕНКЛАТУР'!D:F,3,0) -> Кромка ПВХ Китай | AE213: =VLOOKUP(C:C,'ИЗ ОСНОВЫ НОМЕНКЛАТУР'!D:H,5,0) -> C
A214: Кромочные материалы | B214: 19*1,5мм ПВХ | D214: 0 | E214: 0 | F214: 0 | G214: 0 | H214: 0 | I214: 0 | J214: 0 | K214: 0 | L214: 0 | M214: 0 | N214: 0 | O214: 0 | P214: 0 | Q214: 0 | R214: 0 | S214: 0 | T214: =L214/12 -> 0 | U214: =M214/12 -> 0 | V214: =N214/12 -> 0 | W214: =O214/12 -> 0 | X214: =P214/12 -> 0 | Y214: =Q214/12 -> 0 | Z214: =R214/12 -> 0 | AA214: =S214/12 -> 0 | AB214: =T214+U214+V214+W214+X214+Y214+Z214+AA214 -> 0 | AC214: =VLOOKUP(ПРОДАЖИ!C:C,'ИЗ ОСНОВЫ НОМЕНКЛАТУР'!D:E,2,0) -> #N/A | AD214: =VLOOKUP(C:C,'ИЗ ОСНОВЫ НОМЕНКЛАТУР'!D:F,3,0) -> #N/A | AE214: =VLOOKUP(C:C,'ИЗ ОСНОВЫ НОМЕНКЛАТУР'!D:H,5,0) -> #N/A
A215: Кромочные материалы | C215: 19*1,5мм ПВХ Белый AN | D215: 92876 | E215: 216670 | F215: 43902 | G215: 7935 | H215: 776 | I215: 96900 | J215: 0 | K215: 2070 | L215: 3472191.9 | M215: 8042869.5 | N215: 1782025.8 | O215: 300449.61 | P215: 28798.23 | Q215: 3580918.8 | R215: 0 | S215: 76024.76 | T215: =L215/12 -> 289349.33 | U215: =M215/12 -> 670239.12 | V215: =N215/12 -> 148502.15 | W215: =O215/12 -> 25037.467 | X215: =P215/12 -> 2399.8525 | Y215: =Q215/12 -> 298409.9 | Z215: =R215/12 -> 0 | AA215: =S215/12 -> 6335.3967 | AB215: =T215+U215+V215+W215+X215+Y215+Z215+AA215 -> 1440273.2 | AC215: =VLOOKUP(ПРОДАЖИ!C:C,'ИЗ ОСНОВЫ НОМЕНКЛАТУР'!D:E,2,0) -> Кромочные материалы | AD215: =VLOOKUP(C:C,'ИЗ ОСНОВЫ НОМЕНКЛАТУР'!D:F,3,0) -> Кромка ПВХ Китай | AE215: =VLOOKUP(C:C,'ИЗ ОСНОВЫ НОМЕНКЛАТУР'!D:H,5,0) -> A
A216: Кромочные материалы | C216: 19*1,5мм ПВХ Ясень шимо светлый SJ | D216: 1400 | E216: 93900 | F216: 3439 | G216: 0 | H216: 0 | I216: 46600 | J216: 0 | K216: 0 | L216: 52466.58 | M216: 3439415.4 | N216: 135496.6 | O216: 0 | P216: 0 | Q216: 1767240 | R216: 0 | S216: 0 | T216: =L216/12 -> 4372.215 | U216: =M216/12 -> 286617.95 | V216: =N216/12 -> 11291.383 | W216: =O216/12 -> 0 | X216: =P216/12 -> 0 | Y216: =Q216/12 -> 147270 | Z216: =R216/12 -> 0 | AA216: =S216/12 -> 0 | AB216: =T216+U216+V216+W216+X216+Y216+Z216+AA216 -> 449551.55 | AC216: =VLOOKUP(ПРОДАЖИ!C:C,'ИЗ ОСНОВЫ НОМЕНКЛАТУР'!D:E,2,0) -> Кромочные материалы | AD216: =VLOOKUP(C:C,'ИЗ ОСНОВЫ НОМЕНКЛАТУР'!D:F,3,0) -> Кромка ПВХ Китай | AE216: =VLOOKUP(C:C,'ИЗ ОСНОВЫ НОМЕНКЛАТУР'!D:H,5,0) -> A
A217: Кромочные материалы | C217: 19*1,5мм ПВХ Дуб вотан AN | D217: 24496 | E217: 89080 | F217: 7246 | G217: 1502 | H217: 171 | I217: 12100 | J217: 0 | K217: 0 | L217: 1045210.1 | M217: 3790321.6 | N217: 311045.67 | O217: 71747.68 | P217: 7852.28 | Q217: 526137.99 | R217: 0 | S217: 0 | T217: =L217/12 -> 87100.844 | U217: =M217/12 -> 315860.14 | V217: =N217/12 -> 25920.472 | W217: =O217/12 -> 5978.9733 | X217: =P217/12 -> 654.35667 | Y217: =Q217/12 -> 43844.832 | Z217: =R217/12 -> 0 | AA217: =S217/12 -> 0 | AB217: =T217+U217+V217+W217+X217+Y217+Z217+AA217 -> 479359.62 | AC217: =VLOOKUP(ПРОДАЖИ!C:C,'ИЗ ОСНОВЫ НОМЕНКЛАТУР'!D:E,2,0) -> Кромочные материалы | AD217: =VLOOKUP(C:C,'ИЗ ОСНОВЫ НОМЕНКЛАТУР'!D:F,3,0) -> Кромка ПВХ Китай | AE217: =VLOOKUP(C:C,'ИЗ ОСНОВЫ НОМЕНКЛАТУР'!D:H,5,0) -> A
A218: Кромочные материалы | C218: 19*1,5мм ПВХ Ясень шимо светлый AN | D218: 8486 | E218: 79000 | F218: 4756 | G218: 198 | H218: 930 | I218: 47700 | J218: 0 | K218: 1291 | L218: 383187.6 | M218: 3450486.7 | N218: 214564.8 | O218: 7665.68 | P218: 41847.24 | Q218: 2086116.4 | R218: 0 | S218: 58388.86 | T218: =L218/12 -> 31932.3 | U218: =M218/12 -> 287540.55 | V218: =N218/12 -> 17880.4 | W218: =O218/12 -> 638.80667 | X218: =P218/12 -> 3487.27 | Y218: =Q218/12 -> 173843.04 | Z218: =R218/12 -> 0 | AA218: =S218/12 -> 4865.7383 | AB218: =T218+U218+V218+W218+X218+Y218+Z218+AA218 -> 520188.11 | AC218: =VLOOKUP(ПРОДАЖИ!C:C,'ИЗ ОСНОВЫ НОМЕНКЛАТУР'!D:E,2,0) -> Кромочные материалы | AD218: =VLOOKUP(C:C,'ИЗ ОСНОВЫ НОМЕНКЛАТУР'!D:F,3,0) -> Кромка ПВХ Китай | AE218: =VLOOKUP(C:C,'ИЗ ОСНОВЫ НОМЕНКЛАТУР'!D:H,5,0) -> A
A219: Кромочные материалы | C219: 19*1,5мм ПВХ Бежевый AN | D219: 63522 | E219: 71800 | F219: 100 | G219: 1000 | H219: 110 | I219: 1000 | J219: 0 | K219: 0 | L219: 2807622.9 | M219: 3177692 | N219: 4571.83 | O219: 44030 | P219: 5391.1 | Q219: 49010 | R219: 0 | S219: 0 | T219: =L219/12 -> 233968.57 | U219: =M219/12 -> 264807.67 | V219: =N219/12 -> 380.98583 | W219: =O219/12 -> 3669.1667 | X219: =P219/12 -> 449.25833 | Y219: =Q219/12 -> 4084.1667 | Z219: =R219/12 -> 0 | AA219: =S219/12 -> 0 | AB219: =T219+U219+V219+W219+X219+Y219+Z219+AA219 -> 507359.81 | AC219: =VLOOKUP(ПРОДАЖИ!C:C,'ИЗ ОСНОВЫ НОМЕНКЛАТУР'!D:E,2,0) -> Кромочные материалы | AD219: =VLOOKUP(C:C,'ИЗ ОСНОВЫ НОМЕНКЛАТУР'!D:F,3,0) -> Кромка ПВХ Китай | AE219: =VLOOKUP(C:C,'ИЗ ОСНОВЫ НОМЕНКЛАТУР'!D:H,5,0) -> A
A220: Кромочные материалы | C220: 19*1,5мм ПВХ Ясень шимо темный AN | D220: 25847 | E220: 70200 | F220: 3231 | G220: 0 | H220: 7 | I220: 35500 | J220: 0 | K220: 0 | L220: 1252753.8 | M220: 3369202 | N220: 166925.49 | O220: 0 | P220: 338.16 | Q220: 1692752.5 | R220: 0 | S220: 0 | T220: =L220/12 -> 104396.15 | U220: =M220/12 -> 280766.84 | V220: =N220/12 -> 13910.457 | W220: =O220/12 -> 0 | X220: =P220/12 -> 28.18 | Y220: =Q220/12 -> 141062.71 | Z220: =R220/12 -> 0 | AA220: =S220/12 -> 0 | AB220: =T220+U220+V220+W220+X220+Y220+Z220+AA220 -> 540164.33 | AC220: =VLOOKUP(ПРОДАЖИ!C:C,'ИЗ ОСНОВЫ НОМЕНКЛАТУР'!D:E,2,0) -> Кромочные материалы | AD220: =VLOOKUP(C:C,'ИЗ ОСНОВЫ НОМЕНКЛАТУР'!D:F,3,0) -> Кромка ПВХ Китай | AE220: =VLOOKUP(C:C,'ИЗ ОСНОВЫ НОМЕНКЛАТУР'!D:H,5,0) -> A
A221: Кромочные материалы | C221: 19*1,5мм ПВХ Дуб Сонома AN | D221: 17817 | E221: 23498 | F221: 10513 | G221: 100 | H221: 262 | I221: 16800 | J221: 0 | K221: 408 | L221: 858235.42 | M221: 1138312 | N221: 478922.07 | O221: 6048.42 | P221: 11077.59 | Q221: 714698.64 | R221: 0 | S221: 19476.46 | T221: =L221/12 -> 71519.618 | U221: =M221/12 -> 94859.333 | V221: =N221/12 -> 39910.173 | W221: =O221/12 -> 504.035 | X221: =P221/12 -> 923.1325 | Y221: =Q221/12 -> 59558.22 | Z221: =R221/12 -> 0 | AA221: =S221/12 -> 1623.0383 | AB221: =T221+U221+V221+W221+X221+Y221+Z221+AA221 -> 268897.55 | AC221: =VLOOKUP(ПРОДАЖИ!C:C,'ИЗ ОСНОВЫ НОМЕНКЛАТУР'!D:E,2,0) -> Кромочные материалы | AD221: =VLOOKUP(C:C,'ИЗ ОСНОВЫ НОМЕНКЛАТУР'!D:F,3,0) -> Кромка ПВХ Китай | AE221: =VLOOKUP(C:C,'ИЗ ОСНОВЫ НОМЕНКЛАТУР'!D:H,5,0) -> A
A222: Кромочные материалы | C222: 19*1,5мм ПВХ Ясень шимо темный SJ | D222: 109 | E222: 33500 | F222: 0 | G222: 0 | H222: 0 | I222: 22500 | J222: 0 | K222: 0 | L222: 4687 | M222: 1430475 | N222: 0 | O222: 0 | P222: 0 | Q222: 956100 | R222: 0 | S222: 0 | T222: =L222/12 -> 390.58333 | U222: =M222/12 -> 119206.25 | V222: =N222/12 -> 0 | W222: =O222/12 -> 0 | X222: =P222/12 -> 0 | Y222: =Q222/12 -> 79675 | Z222: =R222/12 -> 0 | AA222: =S222/12 -> 0 | AB222: =T222+U222+V222+W222+X222+Y222+Z222+AA222 -> 199271.83 | AC222: =VLOOKUP(ПРОДАЖИ!C:C,'ИЗ ОСНОВЫ НОМЕНКЛАТУР'!D:E,2,0) -> Кромочные материалы | AD222: =VLOOKUP(C:C,'ИЗ ОСНОВЫ НОМЕНКЛАТУР'!D:F,3,0) -> Кромка ПВХ Китай | AE222: =VLOOKUP(C:C,'ИЗ ОСНОВЫ НОМЕНКЛАТУР'!D:H,5,0) -> A
A223: Кромочные материалы | C223: 19*1,5мм ПВХ Серый AN | D223: 20672 | E223: 25400 | F223: 3777 | G223: 627 | H223: 750 | I223: 4800 | J223: 300 | K223: 574 | L223: 775710.74 | M223: 951131.91 | N223: 176157.17 | O223: 28549.04 | P223: 32702.42 | Q223: 212563.58 | R223: 12487.13 | S223: 22245.17 | T223: =L223/12 -> 64642.562 | U223: =M223/12 -> 79260.993 | V223: =N223/12 -> 14679.764 | W223: =O223/12 -> 2379.0867 | X223: =P223/12 -> 2725.2017 | Y223: =Q223/12 -> 17713.632 | Z223: =R223/12 -> 1040.5942 | AA223: =S223/12 -> 1853.7642 | AB223: =T223+U223+V223+W223+X223+Y223+Z223+AA223 -> 184295.6 | AC223: =VLOOKUP(ПРОДАЖИ!C:C,'ИЗ ОСНОВЫ НОМЕНКЛАТУР'!D:E,2,0) -> Кромочные материалы | AD223: =VLOOKUP(C:C,'ИЗ ОСНОВЫ НОМЕНКЛАТУР'!D:F,3,0) -> Кромка ПВХ Китай | AE223: =VLOOKUP(C:C,'ИЗ ОСНОВЫ НОМЕНКЛАТУР'!D:H,5,0) -> A
A224: Кромочные материалы | C224: 19*1,5мм ПВХ Дуб сонома SJ | D224: 3839 | E224: 11500 | F224: 58 | G224: 100 | H224: 158 | I224: 27700 | J224: 0 | K224: 0 | L224: 161809.12 | M224: 475018.85 | N224: 2331.12 | O224: 4300 | P224: 6794 | Q224: 1160635.6 | R224: 0 | S224: 0 | T224: =L224/12 -> 13484.093 | U224: =M224/12 -> 39584.904 | V224: =N224/12 -> 194.26 | W224: =O224/12 -> 358.33333 | X224: =P224/12 -> 566.16667 | Y224: =Q224/12 -> 96719.637 | Z224: =R224/12 -> 0 | AA224: =S224/12 -> 0 | AB224: =T224+U224+V224+W224+X224+Y224+Z224+AA224 -> 150907.39 | AC224: =VLOOKUP(ПРОДАЖИ!C:C,'ИЗ ОСНОВЫ НОМЕНКЛАТУР'!D:E,2,0) -> Кромочные материалы | AD224: =VLOOKUP(C:C,'ИЗ ОСНОВЫ НОМЕНКЛАТУР'!D:F,3,0) -> Кромка ПВХ Китай | AE224: =VLOOKUP(C:C,'ИЗ ОСНОВЫ НОМЕНКЛАТУР'!D:H,5,0) -> A
A225: Кромочные материалы | C225: 19*1,5мм ПВХ Антрацит AN | D225: 5979 | E225: 35000 | F225: 833 | G225: 0 | H225: 136 | I225: 2300 | J225: 0 | K225: 0 | L225: 236860.63 | M225: 1351354.4 | N225: 35046.24 | O225: 0 | P225: 6022.97 | Q225: 102100.16 | R225: 0 | S225: 0 | T225: =L225/12 -> 19738.386 | U225: =M225/12 -> 112612.87 | V225: =N225/12 -> 2920.52 | W225: =O225/12 -> 0 | X225: =P225/12 -> 501.91417 | Y225: =Q225/12 -> 8508.3467 | Z225: =R225/12 -> 0 | AA225: =S225/12 -> 0 | AB225: =T225+U225+V225+W225+X225+Y225+Z225+AA225 -> 144282.04 | AC225: =VLOOKUP(ПРОДАЖИ!C:C,'ИЗ ОСНОВЫ НОМЕНКЛАТУР'!D:E,2,0) -> Кромочные материалы | AD225: =VLOOKUP(C:C,'ИЗ ОСНОВЫ НОМЕНКЛАТУР'!D:F,3,0) -> Кромка ПВХ Китай | AE225: =VLOOKUP(C:C,'ИЗ ОСНОВЫ НОМЕНКЛАТУР'!D:H,5,0) -> B
A226: Кромочные материалы | C226: 19*1,5мм ПВХ Алюминий AN | D226: 3724 | E226: 500 | F226: 503 | G226: 12700 | H226: 0 | I226: 0 | J226: 0 | K226: 280 | L226: 179457.27 | M226: 24633.68 | N226: 28261.84 | O226: 628343.06 | P226: 0 | Q226: 0 | R226: 0 | S226: 13840.4 | T226: =L226/12 -> 14954.772 | U226: =M226/12 -> 2052.8067 | V226: =N226/12 -> 2355.1533 | W226: =O226/12 -> 52361.922 | X226: =P226/12 -> 0 | Y226: =Q226/12 -> 0 | Z226: =R226/12 -> 0 | AA226: =S226/12 -> 1153.3667 | AB226: =T226+U226+V226+W226+X226+Y226+Z226+AA226 -> 72878.021 | AC226: =VLOOKUP(ПРОДАЖИ!C:C,'ИЗ ОСНОВЫ НОМЕНКЛАТУР'!D:E,2,0) -> Кромочные материалы | AD226: =VLOOKUP(C:C,'ИЗ ОСНОВЫ НОМЕНКЛАТУР'!D:F,3,0) -> Кромка ПВХ Китай | AE226: =VLOOKUP(C:C,'ИЗ ОСНОВЫ НОМЕНКЛАТУР'!D:H,5,0) -> B
... A262: Кромочные материалы | C262: 19*1,5мм ПВХ Дуб честерфилд AN | D262: 100 | E262: 0 | F262: 0 | G262: 0 | H262: 0 | I262: 0 | J262: 0 | K262: 0 | L262: 5107.48 | M262: 0 | N262: 0 | O262: 0 | P262: 0 | Q262: 0 | R262: 0 | S262: 0 | T262: =L262/12 -> 425.62333 | U262: =M262/12 -> 0 | V262: =N262/12 -> 0 | W262: =O262/12 -> 0 | X262: =P262/12 -> 0 | Y262: =Q262/12 -> 0 | Z262: =R262/12 -> 0 | AA262: =S262/12 -> 0 | AB262: =T262+U262+V262+W262+X262+Y262+Z262+AA262 -> 425.62333 | AC262: =VLOOKUP(ПРОДАЖИ!C:C,'ИЗ ОСНОВЫ НОМЕНКЛАТУР'!D:E,2,0) -> Кромочные материалы | AD262: =VLOOKUP(C:C,'ИЗ ОСНОВЫ НОМЕНКЛАТУР'!D:F,3,0) -> Кромка ПВХ Китай | AE262: =VLOOKUP(C:C,'ИЗ ОСНОВЫ НОМЕНКЛАТУР'!D:H,5,0) -> C
A263: Кромочные материалы | B263: 36*1,5мм ПВХ | D263: 0 | E263: 0 | F263: 0 | G263: 0 | H263: 0 | I263: 0 | J263: 0 | K263: 0 | L263: 0 | M263: 0 | N263: 0 | O263: 0 | P263: 0 | Q263: 0 | R263: 0 | S263: 0 | T263: =L263/12 -> 0 | U263: =M263/12 -> 0 | V263: =N263/12 -> 0 | W263: =O263/12 -> 0 | X263: =P263/12 -> 0 | Y263: =Q263/12 -> 0 | Z263: =R263/12 -> 0 | AA263: =S263/12 -> 0 | AB263: =T263+U263+V263+W263+X263+Y263+Z263+AA263 -> 0 | AC263: =VLOOKUP(ПРОДАЖИ!C:C,'ИЗ ОСНОВЫ НОМЕНКЛАТУР'!D:E,2,0) -> #N/A | AD263: =VLOOKUP(C:C,'ИЗ ОСНОВЫ НОМЕНКЛАТУР'!D:F,3,0) -> #N/A | AE263: =VLOOKUP(C:C,'ИЗ ОСНОВЫ НОМЕНКЛАТУР'!D:H,5,0) -> #N/A
A264: Кромочные материалы | C264: 36*1,5мм ПВХ Белый AN | D264: 24065 | E264: 24800 | F264: 12387 | G264: 831 | H264: 2905 | I264: 19200 | J264: 100 | K264: 3960 | L264: 1654897.6 | M264: 1748562.6 | N264: 855020.8 | O264: 62911.15 | P264: 194991.87 | Q264: 1278322.4 | R264: 6214.56 | S264: 259940.77 | T264: =L264/12 -> 137908.13 | U264: =M264/12 -> 145713.55 | V264: =N264/12 -> 71251.733 | W264: =O264/12 -> 5242.5958 | X264: =P264/12 -> 16249.323 | Y264: =Q264/12 -> 106526.86 | Z264: =R264/12 -> 517.88 | AA264: =S264/12 -> 21661.731 | AB264: =T264+U264+V264+W264+X264+Y264+Z264+AA264 -> 505071.82 | AC264: =VLOOKUP(ПРОДАЖИ!C:C,'ИЗ ОСНОВЫ НОМЕНКЛАТУР'!D:E,2,0) -> Кромочные материалы | AD264: =VLOOKUP(C:C,'ИЗ ОСНОВЫ НОМЕНКЛАТУР'!D:F,3,0) -> Кромка ПВХ Китай | AE264: =VLOOKUP(C:C,'ИЗ ОСНОВЫ НОМЕНКЛАТУР'!D:H,5,0) -> A
A265: Кромочные материалы | C265: 36*1,5мм ПВХ Дуб Вотан AN | D265: 12313 | E265: 15730 | F265: 9102 | G265: 604 | H265: 3444 | I265: 3280 | J265: 200 | K265: 2983 | L265: 1040156.8 | M265: 1284804.6 | N265: 746359.65 | O265: 49404.53 | P265: 283158.5 | Q265: 253604.13 | R265: 16089.93 | S265: 236931.93 | T265: =L265/12 -> 86679.737 | U265: =M265/12 -> 107067.05 | V265: =N265/12 -> 62196.638 | W265: =O265/12 -> 4117.0442 | X265: =P265/12 -> 23596.542 | Y265: =Q265/12 -> 21133.678 | Z265: =R265/12 -> 1340.8275 | AA265: =S265/12 -> 19744.327 | AB265: =T265+U265+V265+W265+X265+Y265+Z265+AA265 -> 325875.85 | AC265: =VLOOKUP(ПРОДАЖИ!C:C,'ИЗ ОСНОВЫ НОМЕНКЛАТУР'!D:E,2,0) -> Кромочные материалы | AD265: =VLOOKUP(C:C,'ИЗ ОСНОВЫ НОМЕНКЛАТУР'!D:F,3,0) -> Кромка ПВХ Китай | AE265: =VLOOKUP(C:C,'ИЗ ОСНОВЫ НОМЕНКЛАТУР'!D:H,5,0) -> B
A266: Кромочные материалы | C266: 36*1,5мм ПВХ Дуб Сонома AN | D266: 11610 | E266: 6100 | F266: 6908 | G266: 1207 | H266: 3112 | I266: 6600 | J266: 200 | K266: 3684 | L266: 1061814.2 | M266: 556377.74 | N266: 629788.33 | O266: 110660.96 | P266: 271460.58 | Q266: 581567.59 | R266: 17423.21 | S266: 315212.74 | T266: =L266/12 -> 88484.514 | U266: =M266/12 -> 46364.812 | V266: =N266/12 -> 52482.361 | W266: =O266/12 -> 9221.7467 | X266: =P266/12 -> 22621.715 | Y266: =Q266/12 -> 48463.966 | Z266: =R266/12 -> 1451.9342 | AA266: =S266/12 -> 26267.728 | AB266: =T266+U266+V266+W266+X266+Y266+Z266+AA266 -> 295358.78 | AC266: =VLOOKUP(ПРОДАЖИ!C:C,'ИЗ ОСНОВЫ НОМЕНКЛАТУР'!D:E,2,0) -> Кромочные материалы | AD266: =VLOOKUP(C:C,'ИЗ ОСНОВЫ НОМЕНКЛАТУР'!D:F,3,0) -> Кромка ПВХ Китай | AE266: =VLOOKUP(C:C,'ИЗ ОСНОВЫ НОМЕНКЛАТУР'!D:H,5,0) -> B
A267: Кромочные материалы | C267: 36*1,5мм ПВХ Ясень шимо светлый AN | D267: 11696 | E267: 9000 | F267: 4307 | G267: 122 | H267: 992 | I267: 6800 | J267: 0 | K267: 2687 | L267: 1073493 | M267: 824760.38 | N267: 423183.48 | O267: 11321.36 | P267: 89294.12 | Q267: 606934.3 | R267: 0 | S267: 246631.13 | T267: =L267/12 -> 89457.752 | U267: =M267/12 -> 68730.032 | V267: =N267/12 -> 35265.29 | W267: =O267/12 -> 943.44667 | X267: =P267/12 -> 7441.1767 | Y267: =Q267/12 -> 50577.858 | Z267: =R267/12 -> 0 | AA267: =S267/12 -> 20552.594 | AB267: =T267+U267+V267+W267+X267+Y267+Z267+AA267 -> 272968.15 | AC267: =VLOOKUP(ПРОДАЖИ!C:C,'ИЗ ОСНОВЫ НОМЕНКЛАТУР'!D:E,2,0) -> Кромочные материалы | AD267: =VLOOKUP(C:C,'ИЗ ОСНОВЫ НОМЕНКЛАТУР'!D:F,3,0) -> Кромка ПВХ Китай | AE267: =VLOOKUP(C:C,'ИЗ ОСНОВЫ НОМЕНКЛАТУР'!D:H,5,0) -> B
A268: Кромочные материалы | C268: 36*1,5мм ПВХ Белый SJ | D268: 7642 | E268: 0 | F268: 1638 | G268: 1660 | H268: 1280 | I268: 1120 | J268: 0 | K268: 1500 | L268: 479642.43 | M268: 0 | N268: 102047.4 | O268: 105410 | P268: 79744 | Q268: 69776 | R268: 0 | S268: 93450 | T268: =L268/12 -> 39970.202 | U268: =M268/12 -> 0 | V268: =N268/12 -> 8503.95 | W268: =O268/12 -> 8784.1667 | X268: =P268/12 -> 6645.3333 | Y268: =Q268/12 -> 5814.6667 | Z268: =R268/12 -> 0 | AA268: =S268/12 -> 7787.5 | AB268: =T268+U268+V268+W268+X268+Y268+Z268+AA268 -> 77505.819 | AC268: =VLOOKUP(ПРОДАЖИ!C:C,'ИЗ ОСНОВЫ НОМЕНКЛАТУР'!D:E,2,0) -> Кромочные материалы | AD268: =VLOOKUP(C:C,'ИЗ ОСНОВЫ НОМЕНКЛАТУР'!D:F,3,0) -> Кромка ПВХ Китай | AE268: =VLOOKUP(C:C,'ИЗ ОСНОВЫ НОМЕНКЛАТУР'!D:H,5,0) -> B
A269: Кромочные материалы | C269: 36*1,5мм ПВХ Черный AN | D269: 9474 | E269: 2125 | F269: 8074 | G269: 168 | H269: 2518 | I269: 2160 | J269: 100 | K269: 1958 | L269: 785736.41 | M269: 176308.25 | N269: 665954.99 | O269: 14050.34 | P269: 208011.98 | Q269: 178437.6 | R269: 8219.84 | S269: 160686.17 | T269: =L269/12 -> 65478.034 | U269: =M269/12 -> 14692.354 | V269: =N269/12 -> 55496.249 | W269: =O269/12 -> 1170.8617 | X269: =P269/12 -> 17334.332 | Y269: =Q269/12 -> 14869.8 | Z269: =R269/12 -> 684.98667 | AA269: =S269/12 -> 13390.514 | AB269: =T269+U269+V269+W269+X269+Y269+Z269+AA269 -> 183117.13 | AC269: =VLOOKUP(ПРОДАЖИ!C:C,'ИЗ ОСНОВЫ НОМЕНКЛАТУР'!D:E,2,0) -> Кромочные материалы | AD269: =VLOOKUP(C:C,'ИЗ ОСНОВЫ НОМЕНКЛАТУР'!D:F,3,0) -> Кромка ПВХ Китай | AE269: =VLOOKUP(C:C,'ИЗ ОСНОВЫ НОМЕНКЛАТУР'!D:H,5,0) -> B
A270: Кромочные материалы | C270: 36*1,5мм ПВХ Дуб Вотан SJ | D270: 2969 | E270: 4100 | F270: 4433 | G270: 0 | H270: 1500 | I270: 200 | J270: 0 | K270: 0 | L270: 224558.67 | M270: 305860 | N270: 330701.8 | O270: 0 | P270: 111900 | Q270: 14920 | R270: 0 | S270: 0 | T270: =L270/12 -> 18713.222 | U270: =M270/12 -> 25488.333 | V270: =N270/12 -> 27558.483 | W270: =O270/12 -> 0 | X270: =P270/12 -> 9325 | Y270: =Q270/12 -> 1243.3333 | Z270: =R270/12 -> 0 | AA270: =S270/12 -> 0 | AB270: =T270+U270+V270+W270+X270+Y270+Z270+AA270 -> 82328.372 | AC270: =VLOOKUP(ПРОДАЖИ!C:C,'ИЗ ОСНОВЫ НОМЕНКЛАТУР'!D:E,2,0) -> Кромочные материалы | AD270: =VLOOKUP(C:C,'ИЗ ОСНОВЫ НОМЕНКЛАТУР'!D:F,3,0) -> Кромка ПВХ Китай | AE270: =VLOOKUP(C:C,'ИЗ ОСНОВЫ НОМЕНКЛАТУР'!D:H,5,0) -> B
A271: Кромочные материалы | C271: 36*1,5мм ПВХ Серый AN | D271: 5472 | E271: 11300 | F271: 2748 | G271: 166 | H271: 1443 | I271: 1200 | J271: 0 | K271: 569 | L271: 423221.39 | M271: 862192.04 | N271: 211210.56 | O271: 15898.44 | P271: 109497.34 | Q271: 91263.82 | R271: 0 | S271: 37458.07 | T271: =L271/12 -> 35268.449 | U271: =M271/12 -> 71849.337 | V271: =N271/12 -> 17600.88 | W271: =O271/12 -> 1324.87 | X271: =P271/12 -> 9124.7783 | Y271: =Q271/12 -> 7605.3183 | Z271: =R271/12 -> 0 | AA271: =S271/12 -> 3121.5058 | AB271: =T271+U271+V271+W271+X271+Y271+Z271+AA271 -> 145895.14 | AC271: =VLOOKUP(ПРОДАЖИ!C:C,'ИЗ ОСНОВЫ НОМЕНКЛАТУР'!D:E,2,0) -> Кромочные материалы | AD271: =VLOOKUP(C:C,'ИЗ ОСНОВЫ НОМЕНКЛАТУР'!D:F,3,0) -> Кромка ПВХ Китай | AE271: =VLOOKUP(C:C,'ИЗ ОСНОВЫ НОМЕНКЛАТУР'!D:H,5,0) -> B
A272: Кромочные материалы | C272: 36*1,5мм ПВХ Тэффи AN | D272: 2791 | E272: 4200 | F272: 520 | G272: 164 | H272: 1517 | I272: 1700 | J272: 100 | K272: 3217 | L272: 216153.77 | M272: 324088.08 | N272: 40064.23 | O272: 13347.96 | P272: 113095 | Q272: 125984.48 | R272: 8037.93 | S272: 245940.09 | T272: =L272/12 -> 18012.814 | U272: =M272/12 -> 27007.34 | V272: =N272/12 -> 3338.6858 | W272: =O272/12 -> 1112.33 | X272: =P272/12 -> 9424.5833 | Y272: =Q272/12 -> 10498.707 | Z272: =R272/12 -> 669.8275 | AA272: =S272/12 -> 20495.007 | AB272: =T272+U272+V272+W272+X272+Y272+Z272+AA272 -> 90559.295 | AC272: =VLOOKUP(ПРОДАЖИ!C:C,'ИЗ ОСНОВЫ НОМЕНКЛАТУР'!D:E,2,0) -> Кромочные материалы | AD272: =VLOOKUP(C:C,'ИЗ ОСНОВЫ НОМЕНКЛАТУР'!D:F,3,0) -> Кромка ПВХ Китай | AE272: =VLOOKUP(C:C,'ИЗ ОСНОВЫ НОМЕНКЛАТУР'!D:H,5,0) -> B
A273: Кромочные материалы | C273: 36*1,5мм ПВХ Антрацит AN | D273: 6045 | E273: 7400 | F273: 1020 | G273: 156 | H273: 1120 | I273: 600 | J273: 100 | K273: 3061 | L273: 478356.75 | M273: 582395.29 | N273: 84559.34 | O273: 12246 | P273: 90787.13 | Q273: 48799.24 | R273: 7850 | S273: 240288.5 | T273: =L273/12 -> 39863.062 | U273: =M273/12 -> 48532.941 | V273: =N273/12 -> 7046.6117 | W273: =O273/12 -> 1020.5 | X273: =P273/12 -> 7565.5942 | Y273: =Q273/12 -> 4066.6033 | Z273: =R273/12 -> 654.16667 | AA273: =S273/12 -> 20024.042 | AB273: =T273+U273+V273+W273+X273+Y273+Z273+AA273 -> 128773.52 | AC273: =VLOOKUP(ПРОДАЖИ!C:C,'ИЗ ОСНОВЫ НОМЕНКЛАТУР'!D:E,2,0) -> Кромочные материалы | AD273: =VLOOKUP(C:C,'ИЗ ОСНОВЫ НОМЕНКЛАТУР'!D:F,3,0) -> Кромка ПВХ Китай | AE273: =VLOOKUP(C:C,'ИЗ ОСНОВЫ НОМЕНКЛАТУР'!D:H,5,0) -> B
A274: Кромочные материалы | C274: 36*1,5мм ПВХ Белый гладкий AN | D274: 8633 | E274: 1600 | F274: 1217 | G274: 1469 | H274: 75 | I274: 3100 | J274: 0 | K274: 979 | L274: 685898.28 | M274: 126932.1 | N274: 108591.56 | O274: 115316.5 | P274: 5887.5 | Q274: 243350 | R274: 0 | S274: 77047.35 | T274: =L274/12 -> 57158.19 | U274: =M274/12 -> 10577.675 | V274: =N274/12 -> 9049.2967 | W274: =O274/12 -> 9609.7083 | X274: =P274/12 -> 490.625 | Y274: =Q274/12 -> 20279.167 | Z274: =R274/12 -> 0 | AA274: =S274/12 -> 6420.6125 | AB274: =T274+U274+V274+W274+X274+Y274+Z274+AA274 -> 113585.27 | AC274: =VLOOKUP(ПРОДАЖИ!C:C,'ИЗ ОСНОВЫ НОМЕНКЛАТУР'!D:E,2,0) -> Кромочные материалы | AD274: =VLOOKUP(C:C,'ИЗ ОСНОВЫ НОМЕНКЛАТУР'!D:F,3,0) -> Кромка ПВХ Китай | AE274: =VLOOKUP(C:C,'ИЗ ОСНОВЫ НОМЕНКЛАТУР'!D:H,5,0) -> B
A275: Кромочные материалы | C275: 36*1,5мм ПВХ Гикори Джексон светлый AN | D275: 6853 | E275: 0 | F275: 1138 | G275: 0 | H275: 139 | I275: 1000 | J275: 0 | K275: 1351 | L275: 579413.07 | M275: 0 | N275: 92826.66 | O275: 0 | P275: 11338.23 | Q275: 81570 | R275: 0 | S275: 110201.07 | T275: =L275/12 -> 48284.422 | U275: =M275/12 -> 0 | V275: =N275/12 -> 7735.555 | W275: =O275/12 -> 0 | X275: =P275/12 -> 944.8525 | Y275: =Q275/12 -> 6797.5 | Z275: =R275/12 -> 0 | AA275: =S275/12 -> 9183.4225 | AB275: =T275+U275+V275+W275+X275+Y275+Z275+AA275 -> 72945.753 | AC275: =VLOOKUP(ПРОДАЖИ!C:C,'ИЗ ОСНОВЫ НОМЕНКЛАТУР'!D:E,2,0) -> Кромочные материалы | AD275: =VLOOKUP(C:C,'ИЗ ОСНОВЫ НОМЕНКЛАТУР'!D:F,3,0) -> Кромка ПВХ Китай | AE275: =VLOOKUP(C:C,'ИЗ ОСНОВЫ НОМЕНКЛАТУР'!D:H,5,0) -> B
... A355: Кромочные материалы | C355: 36*1,5мм ПВХ Серенити SJ | D355: 0 | E355: 0 | F355: 5 | G355: 0 | H355: 0 | I355: 0 | J355: 0 | K355: 0 | L355: 0 | M355: 0 | N355: 328.5 | O355: 0 | P355: 0 | Q355: 0 | R355: 0 | S355: 0 | T355: =L355/12 -> 0 | U355: =M355/12 -> 0 | V355: =N355/12 -> 27.375 | W355: =O355/12 -> 0 | X355: =P355/12 -> 0 | Y355: =Q355/12 -> 0 | Z355: =R355/12 -> 0 | AA355: =S355/12 -> 0 | AB355: =T355+U355+V355+W355+X355+Y355+Z355+AA355 -> 27.375 | AC355: =VLOOKUP(ПРОДАЖИ!C:C,'ИЗ ОСНОВЫ НОМЕНКЛАТУР'!D:E,2,0) -> Кромочные материалы | AD355: =VLOOKUP(C:C,'ИЗ ОСНОВЫ НОМЕНКЛАТУР'!D:F,3,0) -> Кромка ПВХ Китай | AE355: =VLOOKUP(C:C,'ИЗ ОСНОВЫ НОМЕНКЛАТУР'!D:H,5,0) -> C
A356: Кромочные материалы | B356: 19*1,0мм ПВХ | D356: 0 | E356: 0 | F356: 0 | G356: 0 | H356: 0 | I356: 0 | J356: 0 | K356: 0 | L356: 0 | M356: 0 | N356: 0 | O356: 0 | P356: 0 | Q356: 0 | R356: 0 | S356: 0 | T356: =L356/12 -> 0 | U356: =M356/12 -> 0 | V356: =N356/12 -> 0 | W356: =O356/12 -> 0 | X356: =P356/12 -> 0 | Y356: =Q356/12 -> 0 | Z356: =R356/12 -> 0 | AA356: =S356/12 -> 0 | AB356: =T356+U356+V356+W356+X356+Y356+Z356+AA356 -> 0 | AC356: =VLOOKUP(ПРОДАЖИ!C:C,'ИЗ ОСНОВЫ НОМЕНКЛАТУР'!D:E,2,0) -> #N/A | AD356: =VLOOKUP(C:C,'ИЗ ОСНОВЫ НОМЕНКЛАТУР'!D:F,3,0) -> #N/A | AE356: =VLOOKUP(C:C,'ИЗ ОСНОВЫ НОМЕНКЛАТУР'!D:H,5,0) -> #N/A
A357: Кромочные материалы | C357: 19*1мм ПВХ Дуб Вотан AN | D357: 39650 | E357: 0 | F357: 46813 | G357: 5418 | H357: 14040 | I357: 30000 | J357: 0 | K357: 0 | L357: 1339723.9 | M357: 0 | N357: 1581646.2 | O357: 182654.83 | P357: 473930.8 | Q357: 1013700 | R357: 0 | S357: 0 | T357: =L357/12 -> 111643.65 | U357: =M357/12 -> 0 | V357: =N357/12 -> 131803.85 | W357: =O357/12 -> 15221.236 | X357: =P357/12 -> 39494.233 | Y357: =Q357/12 -> 84475 | Z357: =R357/12 -> 0 | AA357: =S357/12 -> 0 | AB357: =T357+U357+V357+W357+X357+Y357+Z357+AA357 -> 382637.98 | AC357: =VLOOKUP(ПРОДАЖИ!C:C,'ИЗ ОСНОВЫ НОМЕНКЛАТУР'!D:E,2,0) -> Кромочные материалы | AD357: =VLOOKUP(C:C,'ИЗ ОСНОВЫ НОМЕНКЛАТУР'!D:F,3,0) -> Кромка ПВХ Китай | AE357: =VLOOKUP(C:C,'ИЗ ОСНОВЫ НОМЕНКЛАТУР'!D:H,5,0) -> A
A358: Кромочные материалы | C358: 19*1мм ПВХ Белый AN | D358: 32753 | E358: 13000 | F358: 28888 | G358: 2052 | H358: 0 | I358: 41600 | J358: 0 | K358: 385 | L358: 838515.75 | M358: 327506 | N358: 677934.62 | O358: 46785.6 | P358: 0 | Q358: 962784.39 | R358: 0 | S358: 7803.14 | T358: =L358/12 -> 69876.312 | U358: =M358/12 -> 27292.167 | V358: =N358/12 -> 56494.552 | W358: =O358/12 -> 3898.8 | X358: =P358/12 -> 0 | Y358: =Q358/12 -> 80232.033 | Z358: =R358/12 -> 0 | AA358: =S358/12 -> 650.26167 | AB358: =T358+U358+V358+W358+X358+Y358+Z358+AA358 -> 238444.12 | AC358: =VLOOKUP(ПРОДАЖИ!C:C,'ИЗ ОСНОВЫ НОМЕНКЛАТУР'!D:E,2,0) -> Кромочные материалы | AD358: =VLOOKUP(C:C,'ИЗ ОСНОВЫ НОМЕНКЛАТУР'!D:F,3,0) -> Кромка ПВХ Китай | AE358: =VLOOKUP(C:C,'ИЗ ОСНОВЫ НОМЕНКЛАТУР'!D:H,5,0) -> A
A359: Кромочные материалы | C359: 19*1мм ПВХ Белый (Гладкий) AN | D359: 20196 | E359: 5600 | F359: 28160 | G359: 9143 | H359: 0 | I359: 0 | J359: 600 | K359: 15107 | L359: 532292.41 | M359: 147560 | N359: 744777.99 | O359: 240826.62 | P359: 0 | Q359: 0 | R359: 16068 | S359: 397918.25 | T359: =L359/12 -> 44357.701 | U359: =M359/12 -> 12296.667 | V359: =N359/12 -> 62064.832 | W359: =O359/12 -> 20068.885 | X359: =P359/12 -> 0 | Y359: =Q359/12 -> 0 | Z359: =R359/12 -> 1339 | AA359: =S359/12 -> 33159.854 | AB359: =T359+U359+V359+W359+X359+Y359+Z359+AA359 -> 173286.94 | AC359: =VLOOKUP(ПРОДАЖИ!C:C,'ИЗ ОСНОВЫ НОМЕНКЛАТУР'!D:E,2,0) -> Кромочные материалы | AD359: =VLOOKUP(C:C,'ИЗ ОСНОВЫ НОМЕНКЛАТУР'!D:F,3,0) -> Кромка ПВХ Китай | AE359: =VLOOKUP(C:C,'ИЗ ОСНОВЫ НОМЕНКЛАТУР'!D:H,5,0) -> A
A360: Кромочные материалы | C360: 19*1мм ПВХ Дуб сонома AN | D360: 10797 | E360: 20000 | F360: 19422 | G360: 0 | H360: 10800 | I360: 24200 | J360: 0 | K360: 0 | L360: 348189.16 | M360: 644484.62 | N360: 626372.2 | O360: 0 | P360: 347328 | Q360: 778272 | R360: 0 | S360: 0 | T360: =L360/12 -> 29015.763 | U360: =M360/12 -> 53707.052 | V360: =N360/12 -> 52197.683 | W360: =O360/12 -> 0 | X360: =P360/12 -> 28944 | Y360: =Q360/12 -> 64856 | Z360: =R360/12 -> 0 | AA360: =S360/12 -> 0 | AB360: =T360+U360+V360+W360+X360+Y360+Z360+AA360 -> 228720.5 | AC360: =VLOOKUP(ПРОДАЖИ!C:C,'ИЗ ОСНОВЫ НОМЕНКЛАТУР'!D:E,2,0) -> Кромочные материалы | AD360: =VLOOKUP(C:C,'ИЗ ОСНОВЫ НОМЕНКЛАТУР'!D:F,3,0) -> Кромка ПВХ Китай | AE360: =VLOOKUP(C:C,'ИЗ ОСНОВЫ НОМЕНКЛАТУР'!D:H,5,0) -> A
A361: Кромочные материалы | C361: 19*1мм ПВХ Имбирь AN | D361: 8107 | E361: 0 | F361: 6726 | G361: 0 | H361: 13161 | I361: 6400 | J361: 0 | K361: 3000 | L361: 209610.52 | M361: 0 | N361: 177394.47 | O361: 0 | P361: 338944.85 | Q361: 164928 | R361: 0 | S361: 77310 | T361: =L361/12 -> 17467.543 | U361: =M361/12 -> 0 | V361: =N361/12 -> 14782.872 | W361: =O361/12 -> 0 | X361: =P361/12 -> 28245.404 | Y361: =Q361/12 -> 13744 | Z361: =R361/12 -> 0 | AA361: =S361/12 -> 6442.5 | AB361: =T361+U361+V361+W361+X361+Y361+Z361+AA361 -> 80682.32 | AC361: =VLOOKUP(ПРОДАЖИ!C:C,'ИЗ ОСНОВЫ НОМЕНКЛАТУР'!D:E,2,0) -> Кромочные материалы | AD361: =VLOOKUP(C:C,'ИЗ ОСНОВЫ НОМЕНКЛАТУР'!D:F,3,0) -> Кромка ПВХ Китай | AE361: =VLOOKUP(C:C,'ИЗ ОСНОВЫ НОМЕНКЛАТУР'!D:H,5,0) -> B
A362: Кромочные материалы | C362: 19*1мм ПВХ Ясень шимо светлый AN | D362: 961 | E362: 10000 | F362: 6216 | G362: 1650 | H362: 1600 | I362: 13400 | J362: 0 | K362: 7117 | L362: 31943.64 | M362: 332400 | N362: 206619.84 | O362: 53064 | P362: 51456 | Q362: 433122 | R362: 0 | S362: 228882.72 | T362: =L362/12 -> 2661.97 | U362: =M362/12 -> 27700 | V362: =N362/12 -> 17218.32 | W362: =O362/12 -> 4422 | X362: =P362/12 -> 4288 | Y362: =Q362/12 -> 36093.5 | Z362: =R362/12 -> 0 | AA362: =S362/12 -> 19073.56 | AB362: =T362+U362+V362+W362+X362+Y362+Z362+AA362 -> 111457.35 | AC362: =VLOOKUP(ПРОДАЖИ!C:C,'ИЗ ОСНОВЫ НОМЕНКЛАТУР'!D:E,2,0) -> Кромочные материалы | AD362: =VLOOKUP(C:C,'ИЗ ОСНОВЫ НОМЕНКЛАТУР'!D:F,3,0) -> Кромка ПВХ Китай | AE362: =VLOOKUP(C:C,'ИЗ ОСНОВЫ НОМЕНКЛАТУР'!D:H,5,0) -> B
A363: Кромочные материалы | C363: 19*1мм ПВХ Серый AN | D363: 0 | E363: 0 | F363: 2856 | G363: 0 | H363: 12400 | I363: 9600 | J363: 0 | K363: 0 | L363: 0 | M363: 0 | N363: 73164.25 | O363: 0 | P363: 326616 | Q363: 252864 | R363: 0 | S363: 0 | T363: =L363/12 -> 0 | U363: =M363/12 -> 0 | V363: =N363/12 -> 6097.0208 | W363: =O363/12 -> 0 | X363: =P363/12 -> 27218 | Y363: =Q363/12 -> 21072 | Z363: =R363/12 -> 0 | AA363: =S363/12 -> 0 | AB363: =T363+U363+V363+W363+X363+Y363+Z363+AA363 -> 54387.021 | AC363: =VLOOKUP(ПРОДАЖИ!C:C,'ИЗ ОСНОВЫ НОМЕНКЛАТУР'!D:E,2,0) -> Кромочные материалы | AD363: =VLOOKUP(C:C,'ИЗ ОСНОВЫ НОМЕНКЛАТУР'!D:F,3,0) -> Кромка ПВХ Китай | AE363: =VLOOKUP(C:C,'ИЗ ОСНОВЫ НОМЕНКЛАТУР'!D:H,5,0) -> B
A364: Кромочные материалы | C364: 19*1мм ПВХ Выбеленное дерево AN | D364: 6931 | E364: 0 | F364: 2254 | G364: 511 | H364: 3600 | I364: 1400 | J364: 0 | K364: 0 | L364: 223671.19 | M364: 0 | N364: 73659.53 | O364: 16433.76 | P364: 115776 | Q364: 45024 | R364: 0 | S364: 0 | T364: =L364/12 -> 18639.266 | U364: =M364/12 -> 0 | V364: =N364/12 -> 6138.2942 | W364: =O364/12 -> 1369.48 | X364: =P364/12 -> 9648 | Y364: =Q364/12 -> 3752 | Z364: =R364/12 -> 0 | AA364: =S364/12 -> 0 | AB364: =T364+U364+V364+W364+X364+Y364+Z364+AA364 -> 39547.04 | AC364: =VLOOKUP(ПРОДАЖИ!C:C,'ИЗ ОСНОВЫ НОМЕНКЛАТУР'!D:E,2,0) -> Кромочные материалы | AD364: =VLOOKUP(C:C,'ИЗ ОСНОВЫ НОМЕНКЛАТУР'!D:F,3,0) -> Кромка ПВХ Китай | AE364: =VLOOKUP(C:C,'ИЗ ОСНОВЫ НОМЕНКЛАТУР'!D:H,5,0) -> B
A365: Кромочные материалы | C365: 19*1мм ПВХ Анкор белый AN | D365: 50 | E365: 0 | F365: 3300 | G365: 0 | H365: 4785 | I365: 1400 | J365: 0 | K365: 1857 | L365: 1607 | M365: 0 | N365: 106062 | O365: 0 | P365: 153885.6 | Q365: 45024 | R365: 0 | S365: 59705.62 | T365: =L365/12 -> 133.91667 | U365: =M365/12 -> 0 | V365: =N365/12 -> 8838.5 | W365: =O365/12 -> 0 | X365: =P365/12 -> 12823.8 | Y365: =Q365/12 -> 3752 | Z365: =R365/12 -> 0 | AA365: =S365/12 -> 4975.4683 | AB365: =T365+U365+V365+W365+X365+Y365+Z365+AA365 -> 30523.685 | AC365: =VLOOKUP(ПРОДАЖИ!C:C,'ИЗ ОСНОВЫ НОМЕНКЛАТУР'!D:E,2,0) -> Кромочные материалы | AD365: =VLOOKUP(C:C,'ИЗ ОСНОВЫ НОМЕНКЛАТУР'!D:F,3,0) -> Кромка ПВХ Китай | AE365: =VLOOKUP(C:C,'ИЗ ОСНОВЫ НОМЕНКЛАТУР'!D:H,5,0) -> B
A366: Кромочные материалы | C366: 19*1мм ПВХ Черный AN | D366: 0 | E366: 0 | F366: 5482 | G366: 0 | H366: 3975 | I366: 3025 | J366: 0 | K366: 0 | L366: 0 | M366: 0 | N366: 147136.88 | O366: 0 | P366: 102435.75 | Q366: 77954.25 | R366: 0 | S366: 0 | T366: =L366/12 -> 0 | U366: =M366/12 -> 0 | V366: =N366/12 -> 12261.407 | W366: =O366/12 -> 0 | X366: =P366/12 -> 8536.3125 | Y366: =Q366/12 -> 6496.1875 | Z366: =R366/12 -> 0 | AA366: =S366/12 -> 0 | AB366: =T366+U366+V366+W366+X366+Y366+Z366+AA366 -> 27293.907 | AC366: =VLOOKUP(ПРОДАЖИ!C:C,'ИЗ ОСНОВЫ НОМЕНКЛАТУР'!D:E,2,0) -> Кромочные материалы | AD366: =VLOOKUP(C:C,'ИЗ ОСНОВЫ НОМЕНКЛАТУР'!D:F,3,0) -> Кромка ПВХ Китай | AE366: =VLOOKUP(C:C,'ИЗ ОСНОВЫ НОМЕНКЛАТУР'!D:H,5,0) -> B
A367: Кромочные материалы | C367: 19*1мм ПВХ Антрацит AN | D367: 179 | E367: 5600 | F367: 1200 | G367: 200 | H367: 0 | I367: 0 | J367: 0 | K367: 0 | L367: 6614.8 | M367: 134076.11 | N367: 29463.56 | O367: 4910.59 | P367: 0 | Q367: 0 | R367: 0 | S367: 0 | T367: =L367/12 -> 551.23333 | U367: =M367/12 -> 11173.009 | V367: =N367/12 -> 2455.2967 | W367: =O367/12 -> 409.21583 | X367: =P367/12 -> 0 | Y367: =Q367/12 -> 0 | Z367: =R367/12 -> 0 | AA367: =S367/12 -> 0 | AB367: =T367+U367+V367+W367+X367+Y367+Z367+AA367 -> 14588.755 | AC367: =VLOOKUP(ПРОДАЖИ!C:C,'ИЗ ОСНОВЫ НОМЕНКЛАТУР'!D:E,2,0) -> Кромочные материалы | AD367: =VLOOKUP(C:C,'ИЗ ОСНОВЫ НОМЕНКЛАТУР'!D:F,3,0) -> Кромка ПВХ Китай | AE367: =VLOOKUP(C:C,'ИЗ ОСНОВЫ НОМЕНКЛАТУР'!D:H,5,0) -> C
A368: Кромочные материалы | C368: 19*1мм ПВХ Анкор светлый AN | D368: 0 | E368: 0 | F368: 375 | G368: 41 | H368: 1600 | I368: 400 | J368: 0 | K368: 3887 | L368: 0 | M368: 0 | N368: 12052.5 | O368: 1318.56 | P368: 51424 | Q368: 12856 | R368: 0 | S368: 124995.58 | T368: =L368/12 -> 0 | U368: =M368/12 -> 0 | V368: =N368/12 -> 1004.375 | W368: =O368/12 -> 109.88 | X368: =P368/12 -> 4285.3333 | Y368: =Q368/12 -> 1071.3333 | Z368: =R368/12 -> 0 | AA368: =S368/12 -> 10416.298 | AB368: =T368+U368+V368+W368+X368+Y368+Z368+AA368 -> 16887.22 | AC368: =VLOOKUP(ПРОДАЖИ!C:C,'ИЗ ОСНОВЫ НОМЕНКЛАТУР'!D:E,2,0) -> Кромочные материалы | AD368: =VLOOKUP(C:C,'ИЗ ОСНОВЫ НОМЕНКЛАТУР'!D:F,3,0) -> Кромка ПВХ Китай | AE368: =VLOOKUP(C:C,'ИЗ ОСНОВЫ НОМЕНКЛАТУР'!D:H,5,0) -> C
... A383: Кромочные материалы | C383: 19*1мм ПВХ Серый SJ | D383: 0 | E383: 0 | F383: 465 | G383: 0 | H383: 0 | I383: 0 | J383: 0 | K383: 0 | L383: 0 | M383: 0 | N383: 10509 | O383: 0 | P383: 0 | Q383: 0 | R383: 0 | S383: 0 | T383: =L383/12 -> 0 | U383: =M383/12 -> 0 | V383: =N383/12 -> 875.75 | W383: =O383/12 -> 0 | X383: =P383/12 -> 0 | Y383: =Q383/12 -> 0 | Z383: =R383/12 -> 0 | AA383: =S383/12 -> 0 | AB383: =T383+U383+V383+W383+X383+Y383+Z383+AA383 -> 875.75 | AC383: =VLOOKUP(ПРОДАЖИ!C:C,'ИЗ ОСНОВЫ НОМЕНКЛАТУР'!D:E,2,0) -> Кромочные материалы | AD383: =VLOOKUP(C:C,'ИЗ ОСНОВЫ НОМЕНКЛАТУР'!D:F,3,0) -> Кромка ПВХ Китай | AE383: =VLOOKUP(C:C,'ИЗ ОСНОВЫ НОМЕНКЛАТУР'!D:H,5,0) -> B
A384: Кромочные материалы | B384: 45*1,0мм ПВХ | D384: 0 | E384: 0 | F384: 0 | G384: 0 | H384: 0 | I384: 0 | J384: 0 | K384: 0 | L384: 0 | M384: 0 | N384: 0 | O384: 0 | P384: 0 | Q384: 0 | R384: 0 | S384: 0 | T384: =L384/12 -> 0 | U384: =M384/12 -> 0 | V384: =N384/12 -> 0 | W384: =O384/12 -> 0 | X384: =P384/12 -> 0 | Y384: =Q384/12 -> 0 | Z384: =R384/12 -> 0 | AA384: =S384/12 -> 0 | AB384: =T384+U384+V384+W384+X384+Y384+Z384+AA384 -> 0 | AC384: =VLOOKUP(ПРОДАЖИ!C:C,'ИЗ ОСНОВЫ НОМЕНКЛАТУР'!D:E,2,0) -> #N/A | AD384: =VLOOKUP(C:C,'ИЗ ОСНОВЫ НОМЕНКЛАТУР'!D:F,3,0) -> #N/A | AE384: =VLOOKUP(C:C,'ИЗ ОСНОВЫ НОМЕНКЛАТУР'!D:H,5,0) -> #N/A
A385: Кромочные материалы | C385: 45*1мм ПВХ Белый AN | D385: 2826 | E385: 100 | F385: 2664.5 | G385: 0 | H385: 1813 | I385: 300 | J385: 0 | K385: 1169 | L385: 186805.18 | M385: 6610 | N385: 176958.98 | O385: 0 | P385: 121006.75 | Q385: 19918.29 | R385: 0 | S385: 77270.9 | T385: =L385/12 -> 15567.098 | U385: =M385/12 -> 550.83333 | V385: =N385/12 -> 14746.582 | W385: =O385/12 -> 0 | X385: =P385/12 -> 10083.896 | Y385: =Q385/12 -> 1659.8575 | Z385: =R385/12 -> 0 | AA385: =S385/12 -> 6439.2417 | AB385: =T385+U385+V385+W385+X385+Y385+Z385+AA385 -> 49047.508 | AC385: =VLOOKUP(ПРОДАЖИ!C:C,'ИЗ ОСНОВЫ НОМЕНКЛАТУР'!D:E,2,0) -> Кромочные материалы | AD385: =VLOOKUP(C:C,'ИЗ ОСНОВЫ НОМЕНКЛАТУР'!D:F,3,0) -> Кромка ПВХ Китай | AE385: =VLOOKUP(C:C,'ИЗ ОСНОВЫ НОМЕНКЛАТУР'!D:H,5,0) -> B
A386: Кромочные материалы | C386: 45*1мм ПВХ Дуб вотан AN | D386: 2043 | E386: 0 | F386: 836 | G386: 0 | H386: 1464 | I386: 200 | J386: 0 | K386: 0 | L386: 170005.78 | M386: 0 | N386: 73487.92 | O386: 0 | P386: 124622.94 | Q386: 16954.84 | R386: 0 | S386: 0 | T386: =L386/12 -> 14167.148 | U386: =M386/12 -> 0 | V386: =N386/12 -> 6123.9933 | W386: =O386/12 -> 0 | X386: =P386/12 -> 10385.245 | Y386: =Q386/12 -> 1412.9033 | Z386: =R386/12 -> 0 | AA386: =S386/12 -> 0 | AB386: =T386+U386+V386+W386+X386+Y386+Z386+AA386 -> 32089.29 | AC386: =VLOOKUP(ПРОДАЖИ!C:C,'ИЗ ОСНОВЫ НОМЕНКЛАТУР'!D:E,2,0) -> Кромочные материалы | AD386: =VLOOKUP(C:C,'ИЗ ОСНОВЫ НОМЕНКЛАТУР'!D:F,3,0) -> Кромка ПВХ Китай | AE386: =VLOOKUP(C:C,'ИЗ ОСНОВЫ НОМЕНКЛАТУР'!D:H,5,0) -> C
A387: Кромочные материалы | C387: 45*1мм ПВХ Дуб сонома AN | D387: 1633 | E387: 700 | F387: 277 | G387: 0 | H387: 993 | I387: 203 | J387: 0 | K387: 1208 | L387: 135279.08 | M387: 57992.08 | N387: 24694.43 | O387: 0 | P387: 112135.72 | Q387: 22924.02 | R387: 0 | S387: 92394 | T387: =L387/12 -> 11273.257 | U387: =M387/12 -> 4832.6733 | V387: =N387/12 -> 2057.8692 | W387: =O387/12 -> 0 | X387: =P387/12 -> 9344.6433 | Y387: =Q387/12 -> 1910.335 | Z387: =R387/12 -> 0 | AA387: =S387/12 -> 7699.5 | AB387: =T387+U387+V387+W387+X387+Y387+Z387+AA387 -> 37118.277 | AC387: =VLOOKUP(ПРОДАЖИ!C:C,'ИЗ ОСНОВЫ НОМЕНКЛАТУР'!D:E,2,0) -> Кромочные материалы | AD387: =VLOOKUP(C:C,'ИЗ ОСНОВЫ НОМЕНКЛАТУР'!D:F,3,0) -> Кромка ПВХ Китай | AE387: =VLOOKUP(C:C,'ИЗ ОСНОВЫ НОМЕНКЛАТУР'!D:H,5,0) -> C
A388: Кромочные материалы | C388: 45*1мм ПВХ Черный AN | D388: 2615 | E388: 100 | F388: 941 | G388: 0 | H388: 1009 | I388: 500 | J388: 0 | K388: 928 | L388: 181138.98 | M388: 6927.04 | N388: 66550.45 | O388: 0 | P388: 69884.89 | Q388: 34632.08 | R388: 0 | S388: 64282.56 | T388: =L388/12 -> 15094.915 | U388: =M388/12 -> 577.25333 | V388: =N388/12 -> 5545.8708 | W388: =O388/12 -> 0 | X388: =P388/12 -> 5823.7408 | Y388: =Q388/12 -> 2886.0067 | Z388: =R388/12 -> 0 | AA388: =S388/12 -> 5356.88 | AB388: =T388+U388+V388+W388+X388+Y388+Z388+AA388 -> 35284.667 | AC388: =VLOOKUP(ПРОДАЖИ!C:C,'ИЗ ОСНОВЫ НОМЕНКЛАТУР'!D:E,2,0) -> Кромочные материалы | AD388: =VLOOKUP(C:C,'ИЗ ОСНОВЫ НОМЕНКЛАТУР'!D:F,3,0) -> Кромка ПВХ Китай | AE388: =VLOOKUP(C:C,'ИЗ ОСНОВЫ НОМЕНКЛАТУР'!D:H,5,0) -> C
A389: Кромочные материалы | C389: 45*1мм ПВХ Белый глянец AN | D389: 1093 | E389: 0 | F389: 51 | G389: 0 | H389: 204 | I389: 100 | J389: 200 | K389: 563 | L389: 90676.11 | M389: 0 | N389: 4420.17 | O389: 0 | P389: 17664.06 | Q389: 8667 | R389: 16739.18 | S389: 47133.3 | T389: =L389/12 -> 7556.3425 | U389: =M389/12 -> 0 | V389: =N389/12 -> 368.3475 | W389: =O389/12 -> 0 | X389: =P389/12 -> 1472.005 | Y389: =Q389/12 -> 722.25 | Z389: =R389/12 -> 1394.9317 | AA389: =S389/12 -> 3927.775 | AB389: =T389+U389+V389+W389+X389+Y389+Z389+AA389 -> 15441.652 | AC389: =VLOOKUP(ПРОДАЖИ!C:C,'ИЗ ОСНОВЫ НОМЕНКЛАТУР'!D:E,2,0) -> Кромочные материалы | AD389: =VLOOKUP(C:C,'ИЗ ОСНОВЫ НОМЕНКЛАТУР'!D:F,3,0) -> Кромка ПВХ Китай | AE389: =VLOOKUP(C:C,'ИЗ ОСНОВЫ НОМЕНКЛАТУР'!D:H,5,0) -> C
A390: Кромочные материалы | C390: 45*1мм ПВХ Черный глянец AN | D390: 424 | E390: 100 | F390: 193 | G390: 0 | H390: 0 | I390: 0 | J390: 100 | K390: 420 | L390: 30381.04 | M390: 6610 | N390: 12757.3 | O390: 0 | P390: 0 | Q390: 0 | R390: 6610 | S390: 28002.65 | T390: =L390/12 -> 2531.7533 | U390: =M390/12 -> 550.83333 | V390: =N390/12 -> 1063.1083 | W390: =O390/12 -> 0 | X390: =P390/12 -> 0 | Y390: =Q390/12 -> 0 | Z390: =R390/12 -> 550.83333 | AA390: =S390/12 -> 2333.5542 | AB390: =T390+U390+V390+W390+X390+Y390+Z390+AA390 -> 7030.0825 | AC390: =VLOOKUP(ПРОДАЖИ!C:C,'ИЗ ОСНОВЫ НОМЕНКЛАТУР'!D:E,2,0) -> Кромочные материалы | AD390: =VLOOKUP(C:C,'ИЗ ОСНОВЫ НОМЕНКЛАТУР'!D:F,3,0) -> Кромка ПВХ Китай | AE390: =VLOOKUP(C:C,'ИЗ ОСНОВЫ НОМЕНКЛАТУР'!D:H,5,0) -> C
A391: Кромочные материалы | C391: 45*1мм ПВХ Серый AN | D391: 1156 | E391: 0 | F391: 474 | G391: 2 | H391: 627 | I391: 0 | J391: 2 | K391: 190 | L391: 77645.58 | M391: 0 | N391: 41998.06 | O391: 132.2 | P391: 65082.6 | Q391: 0 | R391: 142.4 | S391: 13300.16 | T391: =L391/12 -> 6470.465 | U391: =M391/12 -> 0 | V391: =N391/12 -> 3499.8383 | W391: =O391/12 -> 11.016667 | X391: =P391/12 -> 5423.55 | Y391: =Q391/12 -> 0 | Z391: =R391/12 -> 11.866667 | AA391: =S391/12 -> 1108.3467 | AB391: =T391+U391+V391+W391+X391+Y391+Z391+AA391 -> 16525.083 | AC391: =VLOOKUP(ПРОДАЖИ!C:C,'ИЗ ОСНОВЫ НОМЕНКЛАТУР'!D:E,2,0) -> Кромочные материалы | AD391: =VLOOKUP(C:C,'ИЗ ОСНОВЫ НОМЕНКЛАТУР'!D:F,3,0) -> Кромка ПВХ Китай | AE391: =VLOOKUP(C:C,'ИЗ ОСНОВЫ НОМЕНКЛАТУР'!D:H,5,0) -> C
A392: Кромочные материалы | C392: 45*1мм ПВХ Бежевый AN | D392: 577 | E392: 0 | F392: 280 | G392: 0 | H392: 0 | I392: 0 | J392: 0 | K392: 162 | L392: 38206.49 | M392: 0 | N392: 18266.91 | O392: 0 | P392: 0 | Q392: 0 | R392: 0 | S392: 10708.2 | T392: =L392/12 -> 3183.8742 | U392: =M392/12 -> 0 | V392: =N392/12 -> 1522.2425 | W392: =O392/12 -> 0 | X392: =P392/12 -> 0 | Y392: =Q392/12 -> 0 | Z392: =R392/12 -> 0 | AA392: =S392/12 -> 892.35 | AB392: =T392+U392+V392+W392+X392+Y392+Z392+AA392 -> 5598.4667 | AC392: =VLOOKUP(ПРОДАЖИ!C:C,'ИЗ ОСНОВЫ НОМЕНКЛАТУР'!D:E,2,0) -> Кромочные материалы | AD392: =VLOOKUP(C:C,'ИЗ ОСНОВЫ НОМЕНКЛАТУР'!D:F,3,0) -> Кромка ПВХ Китай | AE392: =VLOOKUP(C:C,'ИЗ ОСНОВЫ НОМЕНКЛАТУР'!D:H,5,0) -> C
A393: Кромочные материалы | C393: 45*1мм ПВХ Дуб сонома SJ | D393: 433 | E393: 0 | F393: 0 | G393: 0 | H393: 0 | I393: 0 | J393: 0 | K393: 0 | L393: 29199.83 | M393: 0 | N393: 0 | O393: 0 | P393: 0 | Q393: 0 | R393: 0 | S393: 0 | T393: =L393/12 -> 2433.3192 | U393: =M393/12 -> 0 | V393: =N393/12 -> 0 | W393: =O393/12 -> 0 | X393: =P393/12 -> 0 | Y393: =Q393/12 -> 0 | Z393: =R393/12 -> 0 | AA393: =S393/12 -> 0 | AB393: =T393+U393+V393+W393+X393+Y393+Z393+AA393 -> 2433.3192 | AC393: =VLOOKUP(ПРОДАЖИ!C:C,'ИЗ ОСНОВЫ НОМЕНКЛАТУР'!D:E,2,0) -> Кромочные материалы | AD393: =VLOOKUP(C:C,'ИЗ ОСНОВЫ НОМЕНКЛАТУР'!D:F,3,0) -> Кромка ПВХ Китай | AE393: =VLOOKUP(C:C,'ИЗ ОСНОВЫ НОМЕНКЛАТУР'!D:H,5,0) -> C
A394: Кромочные материалы | C394: 45*1мм ПВХ Алюминий AN | D394: 301 | E394: 0 | F394: 17 | G394: 0 | H394: 0 | I394: 0 | J394: 0 | K394: 0 | L394: 30955.32 | M394: 0 | N394: 1532.83 | O394: 0 | P394: 0 | Q394: 0 | R394: 0 | S394: 0 | T394: =L394/12 -> 2579.61 | U394: =M394/12 -> 0 | V394: =N394/12 -> 127.73583 | W394: =O394/12 -> 0 | X394: =P394/12 -> 0 | Y394: =Q394/12 -> 0 | Z394: =R394/12 -> 0 | AA394: =S394/12 -> 0 | AB394: =T394+U394+V394+W394+X394+Y394+Z394+AA394 -> 2707.3458 | AC394: =VLOOKUP(ПРОДАЖИ!C:C,'ИЗ ОСНОВЫ НОМЕНКЛАТУР'!D:E,2,0) -> Кромочные материалы | AD394: =VLOOKUP(C:C,'ИЗ ОСНОВЫ НОМЕНКЛАТУР'!D:F,3,0) -> Кромка ПВХ Китай | AE394: =VLOOKUP(C:C,'ИЗ ОСНОВЫ НОМЕНКЛАТУР'!D:H,5,0) -> C
A395: Кромочные материалы | B395: 19*0,4мм ПВХ | D395: 0 | E395: 0 | F395: 0 | G395: 0 | H395: 0 | I395: 0 | J395: 0 | K395: 0 | L395: 0 | M395: 0 | N395: 0 | O395: 0 | P395: 0 | Q395: 0 | R395: 0 | S395: 0 | T395: =L395/12 -> 0 | U395: =M395/12 -> 0 | V395: =N395/12 -> 0 | W395: =O395/12 -> 0 | X395: =P395/12 -> 0 | Y395: =Q395/12 -> 0 | Z395: =R395/12 -> 0 | AA395: =S395/12 -> 0 | AB395: =T395+U395+V395+W395+X395+Y395+Z395+AA395 -> 0 | AC395: =VLOOKUP(ПРОДАЖИ!C:C,'ИЗ ОСНОВЫ НОМЕНКЛАТУР'!D:E,2,0) -> #N/A | AD395: =VLOOKUP(C:C,'ИЗ ОСНОВЫ НОМЕНКЛАТУР'!D:F,3,0) -> #N/A | AE395: =VLOOKUP(C:C,'ИЗ ОСНОВЫ НОМЕНКЛАТУР'!D:H,5,0) -> #N/A
A396: Кромочные материалы | C396: 19*0,4мм ПВХ Белый AN | D396: 6300 | E396: 17000 | F396: 79900 | G396: 0 | H396: 0 | I396: 0 | J396: 0 | K396: 0 | L396: 76461.51 | M396: 206541.92 | N396: 940378.03 | O396: 0 | P396: 0 | Q396: 0 | R396: 0 | S396: 0 | T396: =L396/12 -> 6371.7925 | U396: =M396/12 -> 17211.827 | V396: =N396/12 -> 78364.836 | W396: =O396/12 -> 0 | X396: =P396/12 -> 0 | Y396: =Q396/12 -> 0 | Z396: =R396/12 -> 0 | AA396: =S396/12 -> 0 | AB396: =T396+U396+V396+W396+X396+Y396+Z396+AA396 -> 101948.46 | AC396: =VLOOKUP(ПРОДАЖИ!C:C,'ИЗ ОСНОВЫ НОМЕНКЛАТУР'!D:E,2,0) -> Кромочные материалы | AD396: =VLOOKUP(C:C,'ИЗ ОСНОВЫ НОМЕНКЛАТУР'!D:F,3,0) -> Кромка ПВХ Китай | AE396: =VLOOKUP(C:C,'ИЗ ОСНОВЫ НОМЕНКЛАТУР'!D:H,5,0) -> A
A397: Кромочные материалы | C397: 19*0,4мм ПВХ Белый SJ | D397: 1000 | E397: 400 | F397: 64400 | G397: 0 | H397: 0 | I397: 0 | J397: 0 | K397: 0 | L397: 9700 | M397: 3880 | N397: 604311.67 | O397: 0 | P397: 0 | Q397: 0 | R397: 0 | S397: 0 | T397: =L397/12 -> 808.33333 | U397: =M397/12 -> 323.33333 | V397: =N397/12 -> 50359.306 | W397: =O397/12 -> 0 | X397: =P397/12 -> 0 | Y397: =Q397/12 -> 0 | Z397: =R397/12 -> 0 | AA397: =S397/12 -> 0 | AB397: =T397+U397+V397+W397+X397+Y397+Z397+AA397 -> 51490.973 | AC397: =VLOOKUP(ПРОДАЖИ!C:C,'ИЗ ОСНОВЫ НОМЕНКЛАТУР'!D:E,2,0) -> Кромочные материалы | AD397: =VLOOKUP(C:C,'ИЗ ОСНОВЫ НОМЕНКЛАТУР'!D:F,3,0) -> Кромка ПВХ Китай | AE397: =VLOOKUP(C:C,'ИЗ ОСНОВЫ НОМЕНКЛАТУР'!D:H,5,0) -> A
A398: Кромочные материалы | C398: 19*0,4мм ПВХ Дуб сонома AN | D398: 13800 | E398: 14400 | F398: 0 | G398: 0 | H398: 0 | I398: 0 | J398: 0 | K398: 0 | L398: 261532.78 | M398: 271746.94 | N398: 0 | O398: 0 | P398: 0 | Q398: 0 | R398: 0 | S398: 0 | T398: =L398/12 -> 21794.398 | U398: =M398/12 -> 22645.578 | V398: =N398/12 -> 0 | W398: =O398/12 -> 0 | X398: =P398/12 -> 0 | Y398: =Q398/12 -> 0 | Z398: =R398/12 -> 0 | AA398: =S398/12 -> 0 | AB398: =T398+U398+V398+W398+X398+Y398+Z398+AA398 -> 44439.977 | AC398: =VLOOKUP(ПРОДАЖИ!C:C,'ИЗ ОСНОВЫ НОМЕНКЛАТУР'!D:E,2,0) -> Кромочные материалы | AD398: =VLOOKUP(C:C,'ИЗ ОСНОВЫ НОМЕНКЛАТУР'!D:F,3,0) -> Кромка ПВХ Китай | AE398: =VLOOKUP(C:C,'ИЗ ОСНОВЫ НОМЕНКЛАТУР'!D:H,5,0) -> B
A399: Кромочные материалы | C399: 19*0,4мм ПВХ Серый AN | D399: 3045 | E399: 6000 | F399: 58000 | G399: 0 | H399: 0 | I399: 0 | J399: 0 | K399: 0 | L399: 37652.27 | M399: 72218.76 | N399: 694260 | O399: 0 | P399: 0 | Q399: 0 | R399: 0 | S399: 0 | T399: =L399/12 -> 3137.6892 | U399: =M399/12 -> 6018.23 | V399: =N399/12 -> 57855 | W399: =O399/12 -> 0 | X399: =P399/12 -> 0 | Y399: =Q399/12 -> 0 | Z399: =R399/12 -> 0 | AA399: =S399/12 -> 0 | AB399: =T399+U399+V399+W399+X399+Y399+Z399+AA399 -> 67010.919 | AC399: =VLOOKUP(ПРОДАЖИ!C:C,'ИЗ ОСНОВЫ НОМЕНКЛАТУР'!D:E,2,0) -> Кромочные материалы | AD399: =VLOOKUP(C:C,'ИЗ ОСНОВЫ НОМЕНКЛАТУР'!D:F,3,0) -> Кромка ПВХ Китай | AE399: =VLOOKUP(C:C,'ИЗ ОСНОВЫ НОМЕНКЛАТУР'!D:H,5,0) -> A
A400: Кромочные материалы | C400: 19*0,4мм ПВХ Черный SJ | D400: 0 | E400: 0 | F400: 10000 | G400: 0 | H400: 0 | I400: 0 | J400: 0 | K400: 0 | L400: 0 | M400: 0 | N400: 97000 | O400: 0 | P400: 0 | Q400: 0 | R400: 0 | S400: 0 | T400: =L400/12 -> 0 | U400: =M400/12 -> 0 | V400: =N400/12 -> 8083.3333 | W400: =O400/12 -> 0 | X400: =P400/12 -> 0 | Y400: =Q400/12 -> 0 | Z400: =R400/12 -> 0 | AA400: =S400/12 -> 0 | AB400: =T400+U400+V400+W400+X400+Y400+Z400+AA400 -> 8083.3333 | AC400: =VLOOKUP(ПРОДАЖИ!C:C,'ИЗ ОСНОВЫ НОМЕНКЛАТУР'!D:E,2,0) -> Кромочные материалы | AD400: =VLOOKUP(C:C,'ИЗ ОСНОВЫ НОМЕНКЛАТУР'!D:F,3,0) -> Кромка ПВХ Китай | AE400: =VLOOKUP(C:C,'ИЗ ОСНОВЫ НОМЕНКЛАТУР'!D:H,5,0) -> B
A401: Кромочные материалы | C401: 19*0,4мм ПВХ Дуб Вотан AN | D401: 2800 | E401: 2600 | F401: 0 | G401: 0 | H401: 0 | I401: 0 | J401: 0 | K401: 0 | L401: 50724 | M401: 47052 | N401: 0 | O401: 0 | P401: 0 | Q401: 0 | R401: 0 | S401: 0 | T401: =L401/12 -> 4227 | U401: =M401/12 -> 3921 | V401: =N401/12 -> 0 | W401: =O401/12 -> 0 | X401: =P401/12 -> 0 | Y401: =Q401/12 -> 0 | Z401: =R401/12 -> 0 | AA401: =S401/12 -> 0 | AB401: =T401+U401+V401+W401+X401+Y401+Z401+AA401 -> 8148 | AC401: =VLOOKUP(ПРОДАЖИ!C:C,'ИЗ ОСНОВЫ НОМЕНКЛАТУР'!D:E,2,0) -> Кромочные материалы | AD401: =VLOOKUP(C:C,'ИЗ ОСНОВЫ НОМЕНКЛАТУР'!D:F,3,0) -> Кромка ПВХ Китай | AE401: =VLOOKUP(C:C,'ИЗ ОСНОВЫ НОМЕНКЛАТУР'!D:H,5,0) -> C
A402: Кромочные материалы | C402: 19*0,4мм ПВХ Крем AN | D402: 600 | E402: 4200 | F402: 0 | G402: 0 | H402: 0 | I402: 0 | J402: 0 | K402: 0 | L402: 6366.01 | M402: 44562.12 | N402: 0 | O402: 0 | P402: 0 | Q402: 0 | R402: 0 | S402: 0 | T402: =L402/12 -> 530.50083 | U402: =M402/12 -> 3713.51 | V402: =N402/12 -> 0 | W402: =O402/12 -> 0 | X402: =P402/12 -> 0 | Y402: =Q402/12 -> 0 | Z402: =R402/12 -> 0 | AA402: =S402/12 -> 0 | AB402: =T402+U402+V402+W402+X402+Y402+Z402+AA402 -> 4244.0108 | AC402: =VLOOKUP(ПРОДАЖИ!C:C,'ИЗ ОСНОВЫ НОМЕНКЛАТУР'!D:E,2,0) -> Кромочные материалы | AD402: =VLOOKUP(C:C,'ИЗ ОСНОВЫ НОМЕНКЛАТУР'!D:F,3,0) -> Кромка ПВХ Китай | AE402: =VLOOKUP(C:C,'ИЗ ОСНОВЫ НОМЕНКЛАТУР'!D:H,5,0) -> C
A403: Кромочные материалы | C403: 19*0,4мм ПВХ Венге AN | D403: 509 | E403: 2400 | F403: 0 | G403: 0 | H403: 0 | I403: 0 | J403: 0 | K403: 0 | L403: 8763.25 | M403: 41315.77 | N403: 0 | O403: 0 | P403: 0 | Q403: 0 | R403: 0 | S403: 0 | T403: =L403/12 -> 730.27083 | U403: =M403/12 -> 3442.9808 | V403: =N403/12 -> 0 | W403: =O403/12 -> 0 | X403: =P403/12 -> 0 | Y403: =Q403/12 -> 0 | Z403: =R403/12 -> 0 | AA403: =S403/12 -> 0 | AB403: =T403+U403+V403+W403+X403+Y403+Z403+AA403 -> 4173.2517 | AC403: =VLOOKUP(ПРОДАЖИ!C:C,'ИЗ ОСНОВЫ НОМЕНКЛАТУР'!D:E,2,0) -> Кромочные материалы | AD403: =VLOOKUP(C:C,'ИЗ ОСНОВЫ НОМЕНКЛАТУР'!D:F,3,0) -> Кромка ПВХ Китай | AE403: =VLOOKUP(C:C,'ИЗ ОСНОВЫ НОМЕНКЛАТУР'!D:H,5,0) -> C
A404: Кромочные материалы | C404: 19*0,4мм ПВХ Антрацит AN | D404: 978 | E404: 2000 | F404: 0 | G404: 0 | H404: 0 | I404: 0 | J404: 0 | K404: 0 | L404: 11031.84 | M404: 22564.18 | N404: 0 | O404: 0 | P404: 0 | Q404: 0 | R404: 0 | S404: 0 | T404: =L404/12 -> 919.32 | U404: =M404/12 -> 1880.3483 | V404: =N404/12 -> 0 | W404: =O404/12 -> 0 | X404: =P404/12 -> 0 | Y404: =Q404/12 -> 0 | Z404: =R404/12 -> 0 | AA404: =S404/12 -> 0 | AB404: =T404+U404+V404+W404+X404+Y404+Z404+AA404 -> 2799.6683 | AC404: =VLOOKUP(ПРОДАЖИ!C:C,'ИЗ ОСНОВЫ НОМЕНКЛАТУР'!D:E,2,0) -> Кромочные материалы | AD404: =VLOOKUP(C:C,'ИЗ ОСНОВЫ НОМЕНКЛАТУР'!D:F,3,0) -> Кромка ПВХ Китай | AE404: =VLOOKUP(C:C,'ИЗ ОСНОВЫ НОМЕНКЛАТУР'!D:H,5,0) -> C
A405: Кромочные материалы | C405: 19*0,4мм ПВХ Ночь экко AN | D405: 600 | E405: 1000 | F405: 0 | G405: 0 | H405: 0 | I405: 0 | J405: 0 | K405: 0 | L405: 10332.15 | M405: 17220.25 | N405: 0 | O405: 0 | P405: 0 | Q405: 0 | R405: 0 | S405: 0 | T405: =L405/12 -> 861.0125 | U405: =M405/12 -> 1435.0208 | V405: =N405/12 -> 0 | W405: =O405/12 -> 0 | X405: =P405/12 -> 0 | Y405: =Q405/12 -> 0 | Z405: =R405/12 -> 0 | AA405: =S405/12 -> 0 | AB405: =T405+U405+V405+W405+X405+Y405+Z405+AA405 -> 2296.0333 | AC405: =VLOOKUP(ПРОДАЖИ!C:C,'ИЗ ОСНОВЫ НОМЕНКЛАТУР'!D:E,2,0) -> Кромочные материалы | AD405: =VLOOKUP(C:C,'ИЗ ОСНОВЫ НОМЕНКЛАТУР'!D:F,3,0) -> Кромка ПВХ Китай | AE405: =VLOOKUP(C:C,'ИЗ ОСНОВЫ НОМЕНКЛАТУР'!D:H,5,0) -> C
A406: Кромочные материалы | C406: 19*0,4мм ПВХ Дуб млечный AN | D406: 0 | E406: 1000 | F406: 0 | G406: 0 | H406: 0 | I406: 0 | J406: 0 | K406: 0 | L406: 0 | M406: 16260 | N406: 0 | O406: 0 | P406: 0 | Q406: 0 | R406: 0 | S406: 0 | T406: =L406/12 -> 0 | U406: =M406/12 -> 1355 | V406: =N406/12 -> 0 | W406: =O406/12 -> 0 | X406: =P406/12 -> 0 | Y406: =Q406/12 -> 0 | Z406: =R406/12 -> 0 | AA406: =S406/12 -> 0 | AB406: =T406+U406+V406+W406+X406+Y406+Z406+AA406 -> 1355 | AC406: =VLOOKUP(ПРОДАЖИ!C:C,'ИЗ ОСНОВЫ НОМЕНКЛАТУР'!D:E,2,0) -> Кромочные материалы | AD406: =VLOOKUP(C:C,'ИЗ ОСНОВЫ НОМЕНКЛАТУР'!D:F,3,0) -> Кромка ПВХ Китай | AE406: =VLOOKUP(C:C,'ИЗ ОСНОВЫ НОМЕНКЛАТУР'!D:H,5,0) -> C
A407: Кромочные материалы | C407: 19*0,4мм ПВХ Ясень шимо светлый AN | D407: 0 | E407: 2000 | F407: 0 | G407: 0 | H407: 0 | I407: 0 | J407: 0 | K407: 0 | L407: 0 | M407: 37780 | N407: 0 | O407: 0 | P407: 0 | Q407: 0 | R407: 0 | S407: 0 | T407: =L407/12 -> 0 | U407: =M407/12 -> 3148.3333 | V407: =N407/12 -> 0 | W407: =O407/12 -> 0 | X407: =P407/12 -> 0 | Y407: =Q407/12 -> 0 | Z407: =R407/12 -> 0 | AA407: =S407/12 -> 0 | AB407: =T407+U407+V407+W407+X407+Y407+Z407+AA407 -> 3148.3333 | AC407: =VLOOKUP(ПРОДАЖИ!C:C,'ИЗ ОСНОВЫ НОМЕНКЛАТУР'!D:E,2,0) -> Кромочные материалы | AD407: =VLOOKUP(C:C,'ИЗ ОСНОВЫ НОМЕНКЛАТУР'!D:F,3,0) -> Кромка ПВХ Китай | AE407: =VLOOKUP(C:C,'ИЗ ОСНОВЫ НОМЕНКЛАТУР'!D:H,5,0) -> C
... A410: Кромочные материалы | C410: 19*0,4мм ПВХ Выбеленное дерево AN | D410: 0 | E410: 2000 | F410: 20 | G410: 0 | H410: 0 | I410: 0 | J410: 0 | K410: 0 | L410: 0 | M410: 35491.59 | N410: 349.63 | O410: 0 | P410: 0 | Q410: 0 | R410: 0 | S410: 0 | T410: =L410/12 -> 0 | U410: =M410/12 -> 2957.6325 | V410: =N410/12 -> 29.135833 | W410: =O410/12 -> 0 | X410: =P410/12 -> 0 | Y410: =Q410/12 -> 0 | Z410: =R410/12 -> 0 | AA410: =S410/12 -> 0 | AB410: =T410+U410+V410+W410+X410+Y410+Z410+AA410 -> 2986.7683 | AC410: =VLOOKUP(ПРОДАЖИ!C:C,'ИЗ ОСНОВЫ НОМЕНКЛАТУР'!D:E,2,0) -> Кромочные материалы | AD410: =VLOOKUP(C:C,'ИЗ ОСНОВЫ НОМЕНКЛАТУР'!D:F,3,0) -> Кромка ПВХ Китай | AE410: =VLOOKUP(C:C,'ИЗ ОСНОВЫ НОМЕНКЛАТУР'!D:H,5,0) -> C
A411: Кромочные материалы | B411: 22*1,0мм ПВХ | D411: 0 | E411: 0 | F411: 0 | G411: 0 | H411: 0 | I411: 0 | J411: 0 | K411: 0 | L411: 0 | M411: 0 | N411: 0 | O411: 0 | P411: 0 | Q411: 0 | R411: 0 | S411: 0 | T411: =L411/12 -> 0 | U411: =M411/12 -> 0 | V411: =N411/12 -> 0 | W411: =O411/12 -> 0 | X411: =P411/12 -> 0 | Y411: =Q411/12 -> 0 | Z411: =R411/12 -> 0 | AA411: =S411/12 -> 0 | AB411: =T411+U411+V411+W411+X411+Y411+Z411+AA411 -> 0 | AC411: =VLOOKUP(ПРОДАЖИ!C:C,'ИЗ ОСНОВЫ НОМЕНКЛАТУР'!D:E,2,0) -> #N/A | AD411: =VLOOKUP(C:C,'ИЗ ОСНОВЫ НОМЕНКЛАТУР'!D:F,3,0) -> #N/A | AE411: =VLOOKUP(C:C,'ИЗ ОСНОВЫ НОМЕНКЛАТУР'!D:H,5,0) -> #N/A
A412: Кромочные материалы | C412: 22*1мм ПВХ Белый глянец AN | D412: 13916 | E412: 0 | F412: 11961 | G412: 259 | H412: 10647 | I412: 3300 | J412: 400 | K412: 11706 | L412: 587273.9 | M412: 0 | N412: 500225.17 | O412: 10907.41 | P412: 444733.24 | Q412: 137831.6 | R412: 16850.45 | S412: 490546.26 | T412: =L412/12 -> 48939.492 | U412: =M412/12 -> 0 | V412: =N412/12 -> 41685.431 | W412: =O412/12 -> 908.95083 | X412: =P412/12 -> 37061.103 | Y412: =Q412/12 -> 11485.967 | Z412: =R412/12 -> 1404.2042 | AA412: =S412/12 -> 40878.855 | AB412: =T412+U412+V412+W412+X412+Y412+Z412+AA412 -> 182364 | AC412: =VLOOKUP(ПРОДАЖИ!C:C,'ИЗ ОСНОВЫ НОМЕНКЛАТУР'!D:E,2,0) -> Кромочные материалы | AD412: =VLOOKUP(C:C,'ИЗ ОСНОВЫ НОМЕНКЛАТУР'!D:F,3,0) -> Кромка ПВХ Китай | AE412: =VLOOKUP(C:C,'ИЗ ОСНОВЫ НОМЕНКЛАТУР'!D:H,5,0) -> B
A413: Кромочные материалы | B413: 45*1,5мм ПВХ | D413: 0 | E413: 0 | F413: 0 | G413: 0 | H413: 0 | I413: 0 | J413: 0 | K413: 0 | L413: 0 | M413: 0 | N413: 0 | O413: 0 | P413: 0 | Q413: 0 | R413: 0 | S413: 0 | T413: =L413/12 -> 0 | U413: =M413/12 -> 0 | V413: =N413/12 -> 0 | W413: =O413/12 -> 0 | X413: =P413/12 -> 0 | Y413: =Q413/12 -> 0 | Z413: =R413/12 -> 0 | AA413: =S413/12 -> 0 | AB413: =T413+U413+V413+W413+X413+Y413+Z413+AA413 -> 0 | AC413: =VLOOKUP(ПРОДАЖИ!C:C,'ИЗ ОСНОВЫ НОМЕНКЛАТУР'!D:E,2,0) -> #N/A | AD413: =VLOOKUP(C:C,'ИЗ ОСНОВЫ НОМЕНКЛАТУР'!D:F,3,0) -> #N/A | AE413: =VLOOKUP(C:C,'ИЗ ОСНОВЫ НОМЕНКЛАТУР'!D:H,5,0) -> #N/A
A414: Кромочные материалы | C414: 45*1,5мм ПВХ Дуб вотан AN | D414: 695 | E414: 0 | F414: 64 | G414: 113 | H414: 100 | I414: 0 | J414: 0 | K414: 297 | L414: 82913.49 | M414: 0 | N414: 7623.67 | O414: 13563.39 | P414: 12003 | Q414: 0 | R414: 0 | S414: 35243.89 | T414: =L414/12 -> 6909.4575 | U414: =M414/12 -> 0 | V414: =N414/12 -> 635.30583 | W414: =O414/12 -> 1130.2825 | X414: =P414/12 -> 1000.25 | Y414: =Q414/12 -> 0 | Z414: =R414/12 -> 0 | AA414: =S414/12 -> 2936.9908 | AB414: =T414+U414+V414+W414+X414+Y414+Z414+AA414 -> 12612.287 | AC414: =VLOOKUP(ПРОДАЖИ!C:C,'ИЗ ОСНОВЫ НОМЕНКЛАТУР'!D:E,2,0) -> Кромочные материалы | AD414: =VLOOKUP(C:C,'ИЗ ОСНОВЫ НОМЕНКЛАТУР'!D:F,3,0) -> Кромка ПВХ Китай | AE414: =VLOOKUP(C:C,'ИЗ ОСНОВЫ НОМЕНКЛАТУР'!D:H,5,0) -> C
A415: Кромочные материалы | C415: 45*1,5мм ПВХ Белый SJ | D415: 765 | E415: 0 | F415: 122 | G415: 3 | H415: 0 | I415: 0 | J415: 0 | K415: 0 | L415: 62626.83 | M415: 0 | N415: 9796.6 | O415: 249 | P415: 0 | Q415: 0 | R415: 0 | S415: 0 | T415: =L415/12 -> 5218.9025 | U415: =M415/12 -> 0 | V415: =N415/12 -> 816.38333 | W415: =O415/12 -> 20.75 | X415: =P415/12 -> 0 | Y415: =Q415/12 -> 0 | Z415: =R415/12 -> 0 | AA415: =S415/12 -> 0 | AB415: =T415+U415+V415+W415+X415+Y415+Z415+AA415 -> 6056.0358 | AC415: =VLOOKUP(ПРОДАЖИ!C:C,'ИЗ ОСНОВЫ НОМЕНКЛАТУР'!D:E,2,0) -> Кромочные материалы | AD415: =VLOOKUP(C:C,'ИЗ ОСНОВЫ НОМЕНКЛАТУР'!D:F,3,0) -> Кромка ПВХ Китай | AE415: =VLOOKUP(C:C,'ИЗ ОСНОВЫ НОМЕНКЛАТУР'!D:H,5,0) -> C
A416: Кромочные материалы | C416: 45*1,5мм ПВХ Черный AN | D416: 882 | E416: 2 | F416: 226 | G416: 21 | H416: 0 | I416: 400 | J416: 0 | K416: 0 | L416: 91629.7 | M416: 195.96 | N416: 22869.72 | O416: 2139.06 | P416: 0 | Q416: 40744 | R416: 0 | S416: 0 | T416: =L416/12 -> 7635.8083 | U416: =M416/12 -> 16.33 | V416: =N416/12 -> 1905.81 | W416: =O416/12 -> 178.255 | X416: =P416/12 -> 0 | Y416: =Q416/12 -> 3395.3333 | Z416: =R416/12 -> 0 | AA416: =S416/12 -> 0 | AB416: =T416+U416+V416+W416+X416+Y416+Z416+AA416 -> 13131.537 | AC416: =VLOOKUP(ПРОДАЖИ!C:C,'ИЗ ОСНОВЫ НОМЕНКЛАТУР'!D:E,2,0) -> Кромочные материалы | AD416: =VLOOKUP(C:C,'ИЗ ОСНОВЫ НОМЕНКЛАТУР'!D:F,3,0) -> Кромка ПВХ Китай | AE416: =VLOOKUP(C:C,'ИЗ ОСНОВЫ НОМЕНКЛАТУР'!D:H,5,0) -> C
A417: Кромочные материалы | C417: 45*1,5мм ПВХ Белый AN | D417: 444 | E417: 600 | F417: 212 | G417: 89 | H417: 0 | I417: 0 | J417: 0 | K417: 0 | L417: 44795.34 | M417: 60534.16 | N417: 23600.9 | O417: 9065.68 | P417: 0 | Q417: 0 | R417: 0 | S417: 0 | T417: =L417/12 -> 3732.945 | U417: =M417/12 -> 5044.5133 | V417: =N417/12 -> 1966.7417 | W417: =O417/12 -> 755.47333 | X417: =P417/12 -> 0 | Y417: =Q417/12 -> 0 | Z417: =R417/12 -> 0 | AA417: =S417/12 -> 0 | AB417: =T417+U417+V417+W417+X417+Y417+Z417+AA417 -> 11499.673 | AC417: =VLOOKUP(ПРОДАЖИ!C:C,'ИЗ ОСНОВЫ НОМЕНКЛАТУР'!D:E,2,0) -> Кромочные материалы | AD417: =VLOOKUP(C:C,'ИЗ ОСНОВЫ НОМЕНКЛАТУР'!D:F,3,0) -> Кромка ПВХ Китай | AE417: =VLOOKUP(C:C,'ИЗ ОСНОВЫ НОМЕНКЛАТУР'!D:H,5,0) -> C
A418: Кромочные материалы | C418: 45*1,5мм ПВХ Серый AN | D418: 636 | E418: 2 | F418: 343 | G418: 63 | H418: 0 | I418: 0 | J418: 0 | K418: 0 | L418: 63562.58 | M418: 199.88 | N418: 34568.72 | O418: 6355.92 | P418: 0 | Q418: 0 | R418: 0 | S418: 0 | T418: =L418/12 -> 5296.8817 | U418: =M418/12 -> 16.656667 | V418: =N418/12 -> 2880.7267 | W418: =O418/12 -> 529.66 | X418: =P418/12 -> 0 | Y418: =Q418/12 -> 0 | Z418: =R418/12 -> 0 | AA418: =S418/12 -> 0 | AB418: =T418+U418+V418+W418+X418+Y418+Z418+AA418 -> 8723.925 | AC418: =VLOOKUP(ПРОДАЖИ!C:C,'ИЗ ОСНОВЫ НОМЕНКЛАТУР'!D:E,2,0) -> Кромочные материалы | AD418: =VLOOKUP(C:C,'ИЗ ОСНОВЫ НОМЕНКЛАТУР'!D:F,3,0) -> Кромка ПВХ Китай | AE418: =VLOOKUP(C:C,'ИЗ ОСНОВЫ НОМЕНКЛАТУР'!D:H,5,0) -> C
A419: Кромочные материалы | C419: 45*1,5мм ПВХ Дуб сонома AN | D419: 463 | E419: 2 | F419: 70 | G419: 0 | H419: 0 | I419: 0 | J419: 0 | K419: 100 | L419: 54253.2 | M419: 233.72 | N419: 8330.44 | O419: 0 | P419: 0 | Q419: 0 | R419: 0 | S419: 11545 | T419: =L419/12 -> 4521.1 | U419: =M419/12 -> 19.476667 | V419: =N419/12 -> 694.20333 | W419: =O419/12 -> 0 | X419: =P419/12 -> 0 | Y419: =Q419/12 -> 0 | Z419: =R419/12 -> 0 | AA419: =S419/12 -> 962.08333 | AB419: =T419+U419+V419+W419+X419+Y419+Z419+AA419 -> 6196.8633 | AC419: =VLOOKUP(ПРОДАЖИ!C:C,'ИЗ ОСНОВЫ НОМЕНКЛАТУР'!D:E,2,0) -> Кромочные материалы | AD419: =VLOOKUP(C:C,'ИЗ ОСНОВЫ НОМЕНКЛАТУР'!D:F,3,0) -> Кромка ПВХ Китай | AE419: =VLOOKUP(C:C,'ИЗ ОСНОВЫ НОМЕНКЛАТУР'!D:H,5,0) -> C
A420: Кромочные материалы | C420: 45*1,5мм ПВХ Алюминий AN | D420: 115 | E420: 0 | F420: 42 | G420: 0 | H420: 0 | I420: 0 | J420: 0 | K420: 30 | L420: 14528.14 | M420: 0 | N420: 5659.03 | O420: 0 | P420: 0 | Q420: 0 | R420: 0 | S420: 3463.5 | T420: =L420/12 -> 1210.6783 | U420: =M420/12 -> 0 | V420: =N420/12 -> 471.58583 | W420: =O420/12 -> 0 | X420: =P420/12 -> 0 | Y420: =Q420/12 -> 0 | Z420: =R420/12 -> 0 | AA420: =S420/12 -> 288.625 | AB420: =T420+U420+V420+W420+X420+Y420+Z420+AA420 -> 1970.8892 | AC420: =VLOOKUP(ПРОДАЖИ!C:C,'ИЗ ОСНОВЫ НОМЕНКЛАТУР'!D:E,2,0) -> Кромочные материалы | AD420: =VLOOKUP(C:C,'ИЗ ОСНОВЫ НОМЕНКЛАТУР'!D:F,3,0) -> Кромка ПВХ Китай | AE420: =VLOOKUP(C:C,'ИЗ ОСНОВЫ НОМЕНКЛАТУР'!D:H,5,0) -> C
A421: Кромочные материалы | B421: 36*1,0мм ПВХ | D421: 0 | E421: 0 | F421: 0 | G421: 0 | H421: 0 | I421: 0 | J421: 0 | K421: 0 | L421: 0 | M421: 0 | N421: 0 | O421: 0 | P421: 0 | Q421: 0 | R421: 0 | S421: 0 | T421: =L421/12 -> 0 | U421: =M421/12 -> 0 | V421: =N421/12 -> 0 | W421: =O421/12 -> 0 | X421: =P421/12 -> 0 | Y421: =Q421/12 -> 0 | Z421: =R421/12 -> 0 | AA421: =S421/12 -> 0 | AB421: =T421+U421+V421+W421+X421+Y421+Z421+AA421 -> 0 | AC421: =VLOOKUP(ПРОДАЖИ!C:C,'ИЗ ОСНОВЫ НОМЕНКЛАТУР'!D:E,2,0) -> #N/A | AD421: =VLOOKUP(C:C,'ИЗ ОСНОВЫ НОМЕНКЛАТУР'!D:F,3,0) -> #N/A | AE421: =VLOOKUP(C:C,'ИЗ ОСНОВЫ НОМЕНКЛАТУР'!D:H,5,0) -> #N/A
A422: Кромочные материалы | C422: 36*1мм ПВХ Дуб Вотан SJ | D422: 1190 | E422: 700 | F422: 813 | G422: 0 | H422: 350 | I422: 0 | J422: 0 | K422: 0 | L422: 70210 | M422: 41300 | N422: 47967 | O422: 0 | P422: 20650 | Q422: 0 | R422: 0 | S422: 0 | T422: =L422/12 -> 5850.8333 | U422: =M422/12 -> 3441.6667 | V422: =N422/12 -> 3997.25 | W422: =O422/12 -> 0 | X422: =P422/12 -> 1720.8333 | Y422: =Q422/12 -> 0 | Z422: =R422/12 -> 0 | AA422: =S422/12 -> 0 | AB422: =T422+U422+V422+W422+X422+Y422+Z422+AA422 -> 15010.583 | AC422: =VLOOKUP(ПРОДАЖИ!C:C,'ИЗ ОСНОВЫ НОМЕНКЛАТУР'!D:E,2,0) -> Кромочные материалы | AD422: =VLOOKUP(C:C,'ИЗ ОСНОВЫ НОМЕНКЛАТУР'!D:F,3,0) -> Кромка ПВХ Китай | AE422: =VLOOKUP(C:C,'ИЗ ОСНОВЫ НОМЕНКЛАТУР'!D:H,5,0) -> C
A423: Кромочные материалы | C423: 36*1мм ПВХ Белый SJ | D423: 1196 | E423: 500 | F423: 1526 | G423: 0 | H423: 30 | I423: 780 | J423: 0 | K423: 0 | L423: 56256 | M423: 22500 | N423: 68670 | O423: 0 | P423: 1350 | Q423: 35100 | R423: 0 | S423: 0 | T423: =L423/12 -> 4688 | U423: =M423/12 -> 1875 | V423: =N423/12 -> 5722.5 | W423: =O423/12 -> 0 | X423: =P423/12 -> 112.5 | Y423: =Q423/12 -> 2925 | Z423: =R423/12 -> 0 | AA423: =S423/12 -> 0 | AB423: =T423+U423+V423+W423+X423+Y423+Z423+AA423 -> 15323 | AC423: =VLOOKUP(ПРОДАЖИ!C:C,'ИЗ ОСНОВЫ НОМЕНКЛАТУР'!D:E,2,0) -> Кромочные материалы | AD423: =VLOOKUP(C:C,'ИЗ ОСНОВЫ НОМЕНКЛАТУР'!D:F,3,0) -> Кромка ПВХ Китай | AE423: =VLOOKUP(C:C,'ИЗ ОСНОВЫ НОМЕНКЛАТУР'!D:H,5,0) -> C
A424: Кромочные материалы | C424: 36*1мм ПВХ Дуб Сонома SJ | D424: 1242 | E424: 200 | F424: 300 | G424: 0 | H424: 114 | I424: 200 | J424: 0 | K424: 0 | L424: 74494.36 | M424: 11800 | N424: 17700 | O424: 0 | P424: 6625 | Q424: 11800 | R424: 0 | S424: 0 | T424: =L424/12 -> 6207.8633 | U424: =M424/12 -> 983.33333 | V424: =N424/12 -> 1475 | W424: =O424/12 -> 0 | X424: =P424/12 -> 552.08333 | Y424: =Q424/12 -> 983.33333 | Z424: =R424/12 -> 0 | AA424: =S424/12 -> 0 | AB424: =T424+U424+V424+W424+X424+Y424+Z424+AA424 -> 10201.613 | AC424: =VLOOKUP(ПРОДАЖИ!C:C,'ИЗ ОСНОВЫ НОМЕНКЛАТУР'!D:E,2,0) -> Кромочные материалы | AD424: =VLOOKUP(C:C,'ИЗ ОСНОВЫ НОМЕНКЛАТУР'!D:F,3,0) -> Кромка ПВХ Китай | AE424: =VLOOKUP(C:C,'ИЗ ОСНОВЫ НОМЕНКЛАТУР'!D:H,5,0) -> C
...

Sheet ОБОРАЧИВ ПО СЕТИ+ABC
I1: A | M1: B | Q1: C
A2: КАТЕГОРИИ | B2: ПРОДАЖА ПО Себ.Ст | D2: ОСТАТОК по Себ.Ст. | F2: ОБОРАЧИВАЕМОСТЬ (дн.) | I2: ПРОД | J2: ОСТАТ | K2: % | L2: ОБОР | M2: ПРОД | N2: ОСТАТ | O2: % | P2: ОБОР | Q2: ПРОД | R2: ОСТАТ | S2: % | T2: ОБОР
A3: Кромочные материалы | B3: =SUM(B4:B14) -> 52874201 | C3: =B3/$B$139 -> 0.41280352 | D3: =SUM(D4:D14) -> 6.1765048e+08 | E3: =D3/$D$139 -> 0.35739611 | F3: =IFERROR(D3/B3*30.5,0) -> 356.28604 | G3: дн. | I3: =SUM(I4:I14) -> 38671825 | J3: =SUM(J4:J14) -> 2.4748929e+08 | K3: =J3/(J3+N3+R3) -> 0.40069472 | L3: =IFERROR(J3/I3*30.5,0) -> 195.1918 | M3: =SUM(M4:M14) -> 10292460 | N3: =SUM(N4:N14) -> 1.6642395e+08 | O3: =N3/(J3+N3+R3) -> 0.2694468 | P3: =IFERROR(N3/M3*30.5,0) -> 493.16982 | Q3: =SUM(Q4:Q14) -> 3909916.1 | R3: =SUM(R4:R14) -> 2.0373725e+08 | S3: =R3/(J3+N3+R3) -> 0.32985848 | T3: =IFERROR(R3/Q3*30.5,0) -> 1589.2889
A4: Кромка ПВХ Китай | B4: =SUMIFS(ПРОДАЖИ!AB:AB,ПРОДАЖИ!AD:AD,'ОБОРАЧИВ ПО СЕТИ+ABC'!A:A) -> 43046724 | C4: =B4/$B$3 -> 0.81413473 | D4: =SUMIFS(ОСТАТКИ!AE:AE,ОСТАТКИ!Q:Q,'ОБОРАЧИВ ПО СЕТИ+ABC'!A:A) -> 5.2001499e+08 | E4: =D4/$D$3 -> 0.84192437 | F4: =IFERROR(D4/B4*30.5,0) -> 368.44749 | G4: дн. | I4: =SUMIFS(ПРОДАЖИ!$AB:$AB,ПРОДАЖИ!$AD:$AD,'ОБОРАЧИВ ПО СЕТИ+ABC'!$A:$A,ПРОДАЖИ!$AE:$AE,'ОБОРАЧИВ ПО СЕТИ+ABC'!I$1) -> 32438557 | J4: =SUMIFS(ОСТАТКИ!$AE:$AE,ОСТАТКИ!$Q:$Q,'ОБОРАЧИВ ПО СЕТИ+ABC'!$A:$A,ОСТАТКИ!$S:$S,'ОБОРАЧИВ ПО СЕТИ+ABC'!I$1) -> 2.1725195e+08 | K4: =J4/(J4+N4+R4) -> 0.41778017 | L4: =IFERROR(J4/I4*30.5,0) -> 204.26878 | M4: =SUMIFS(ПРОДАЖИ!$AB:$AB,ПРОДАЖИ!$AD:$AD,'ОБОРАЧИВ ПО СЕТИ+ABC'!$A:$A,ПРОДАЖИ!$AE:$AE,'ОБОРАЧИВ ПО СЕТИ+ABC'!M$1) -> 8538770.6 | N4: =SUMIFS(ОСТАТКИ!$AE:$AE,ОСТАТКИ!$Q:$Q,'ОБОРАЧИВ ПО СЕТИ+ABC'!$A:$A,ОСТАТКИ!$S:$S,'ОБОРАЧИВ ПО СЕТИ+ABC'!M$1) -> 1.3592032e+08 | O4: =N4/(J4+N4+R4) -> 0.26137769 | P4: =IFERROR(N4/M4*30.5,0) -> 485.4996 | Q4: =SUMIFS(ПРОДАЖИ!$AB:$AB,ПРОДАЖИ!$AD:$AD,'ОБОРАЧИВ ПО СЕТИ+ABC'!$A:$A,ПРОДАЖИ!$AE:$AE,'ОБОРАЧИВ ПО СЕТИ+ABC'!Q$1) -> 2069395.5 | R4: =SUMIFS(ОСТАТКИ!$AE:$AE,ОСТАТКИ!$Q:$Q,'ОБОРАЧИВ ПО СЕТИ+ABC'!$A:$A,ОСТАТКИ!$S:$S,'ОБОРАЧИВ ПО СЕТИ+ABC'!Q$1) -> 1.6684272e+08 | S4: =R4/(J4+N4+R4) -> 0.32084214 | T4: =IFERROR(R4/Q4*30.5,0) -> 2459.0287
A5: Кромка ПВХ Казахстан | B5: =SUMIFS(ПРОДАЖИ!AB:AB,ПРОДАЖИ!AD:AD,'ОБОРАЧИВ ПО СЕТИ+ABC'!A:A) -> 205426.48 | C5: =B5/$B$3 -> 0.0038851932 | D5: =SUMIFS(ОСТАТКИ!AE:AE,ОСТАТКИ!Q:Q,'ОБОРАЧИВ ПО СЕТИ+ABC'!A:A) -> 97352.986 | E5: =D5/$D$3 -> 0.00015761825 | F5: =IFERROR(D5/B5*30.5,0) -> 14.454154 | G5: дн. | I5: =SUMIFS(ПРОДАЖИ!$AB:$AB,ПРОДАЖИ!$AD:$AD,'ОБОРАЧИВ ПО СЕТИ+ABC'!$A:$A,ПРОДАЖИ!$AE:$AE,'ОБОРАЧИВ ПО СЕТИ+ABC'!I$1) -> 0 | J5: =SUMIFS(ОСТАТКИ!$AE:$AE,ОСТАТКИ!$Q:$Q,'ОБОРАЧИВ ПО СЕТИ+ABC'!$A:$A,ОСТАТКИ!$S:$S,'ОБОРАЧИВ ПО СЕТИ+ABC'!I$1) -> 0 | K5: =J5/(J5+N5+R5) -> 0 | L5: =IFERROR(J5/I5*30.5,0) -> 0 | M5: =SUMIFS(ПРОДАЖИ!$AB:$AB,ПРОДАЖИ!$AD:$AD,'ОБОРАЧИВ ПО СЕТИ+ABC'!$A:$A,ПРОДАЖИ!$AE:$AE,'ОБОРАЧИВ ПО СЕТИ+ABC'!M$1) -> 205426.48 | N5: =SUMIFS(ОСТАТКИ!$AE:$AE,ОСТАТКИ!$Q:$Q,'ОБОРАЧИВ ПО СЕТИ+ABC'!$A:$A,ОСТАТКИ!$S:$S,'ОБОРАЧИВ ПО СЕТИ+ABC'!M$1) -> 97352.986 | O5: =N5/(J5+N5+R5) -> 1 | P5: =IFERROR(N5/M5*30.5,0) -> 14.454154 | Q5: =SUMIFS(ПРОДАЖИ!$AB:$AB,ПРОДАЖИ!$AD:$AD,'ОБОРАЧИВ ПО СЕТИ+ABC'!$A:$A,ПРОДАЖИ!$AE:$AE,'ОБОРАЧИВ ПО СЕТИ+ABC'!Q$1) -> 0 | R5: =SUMIFS(ОСТАТКИ!$AE:$AE,ОСТАТКИ!$Q:$Q,'ОБОРАЧИВ ПО СЕТИ+ABC'!$A:$A,ОСТАТКИ!$S:$S,'ОБОРАЧИВ ПО СЕТИ+ABC'!Q$1) -> 0 | S5: =R5/(J5+N5+R5) -> 0 | T5: =IFERROR(R5/Q5*30.5,0) -> 0
A6: Кромка Беларусь | B6: =SUMIFS(ПРОДАЖИ!AB:AB,ПРОДАЖИ!AD:AD,'ОБОРАЧИВ ПО СЕТИ+ABC'!A:A) -> 2139.1375 | C6: =B6/$B$3 -> 4.0457113e-05 | D6: =SUMIFS(ОСТАТКИ!AE:AE,ОСТАТКИ!Q:Q,'ОБОРАЧИВ ПО СЕТИ+ABC'!A:A) -> 319228.02 | E6: =D6/$D$3 -> 0.0005168425 | F6: =IFERROR(D6/B6*30.5,0) -> 4551.5796 | G6: дн. | I6: =SUMIFS(ПРОДАЖИ!$AB:$AB,ПРОДАЖИ!$AD:$AD,'ОБОРАЧИВ ПО СЕТИ+ABC'!$A:$A,ПРОДАЖИ!$AE:$AE,'ОБОРАЧИВ ПО СЕТИ+ABC'!I$1) -> 0 | J6: =SUMIFS(ОСТАТКИ!$AE:$AE,ОСТАТКИ!$Q:$Q,'ОБОРАЧИВ ПО СЕТИ+ABC'!$A:$A,ОСТАТКИ!$S:$S,'ОБОРАЧИВ ПО СЕТИ+ABC'!I$1) -> 0 | K6: =J6/(J6+N6+R6) -> 0 | L6: =IFERROR(J6/I6*30.5,0) -> 0 | M6: =SUMIFS(ПРОДАЖИ!$AB:$AB,ПРОДАЖИ!$AD:$AD,'ОБОРАЧИВ ПО СЕТИ+ABC'!$A:$A,ПРОДАЖИ!$AE:$AE,'ОБОРАЧИВ ПО СЕТИ+ABC'!M$1) -> 0 | N6: =SUMIFS(ОСТАТКИ!$AE:$AE,ОСТАТКИ!$Q:$Q,'ОБОРАЧИВ ПО СЕТИ+ABC'!$A:$A,ОСТАТКИ!$S:$S,'ОБОРАЧИВ ПО СЕТИ+ABC'!M$1) -> 0 | O6: =N6/(J6+N6+R6) -> 0 | P6: =IFERROR(N6/M6*30.5,0) -> 0 | Q6: =SUMIFS(ПРОДАЖИ!$AB:$AB,ПРОДАЖИ!$AD:$AD,'ОБОРАЧИВ ПО СЕТИ+ABC'!$A:$A,ПРОДАЖИ!$AE:$AE,'ОБОРАЧИВ ПО СЕТИ+ABC'!Q$1) -> 2139.1375 | R6: =SUMIFS(ОСТАТКИ!$AE:$AE,ОСТАТКИ!$Q:$Q,'ОБОРАЧИВ ПО СЕТИ+ABC'!$A:$A,ОСТАТКИ!$S:$S,'ОБОРАЧИВ ПО СЕТИ+ABC'!Q$1) -> 319228.02 | S6: =R6/(J6+N6+R6) -> 1 | T6: =IFERROR(R6/Q6*30.5,0) -> 4551.5796
A7: Кромка ПВХ Россия | B7: =SUMIFS(ПРОДАЖИ!AB:AB,ПРОДАЖИ!AD:AD,'ОБОРАЧИВ ПО СЕТИ+ABC'!A:A) -> 199194.16 | C7: =B7/$B$3 -> 0.0037673224 | D7: =SUMIFS(ОСТАТКИ!AE:AE,ОСТАТКИ!Q:Q,'ОБОРАЧИВ ПО СЕТИ+ABC'!A:A) -> 5753782 | E7: =D7/$D$3 -> 0.0093155954 | F7: =IFERROR(D7/B7*30.5,0) -> 881.00147 | G7: дн. | I7: =SUMIFS(ПРОДАЖИ!$AB:$AB,ПРОДАЖИ!$AD:$AD,'ОБОРАЧИВ ПО СЕТИ+ABC'!$A:$A,ПРОДАЖИ!$AE:$AE,'ОБОРАЧИВ ПО СЕТИ+ABC'!I$1) -> 0 | J7: =SUMIFS(ОСТАТКИ!$AE:$AE,ОСТАТКИ!$Q:$Q,'ОБОРАЧИВ ПО СЕТИ+ABC'!$A:$A,ОСТАТКИ!$S:$S,'ОБОРАЧИВ ПО СЕТИ+ABC'!I$1) -> 0 | K7: =J7/(J7+N7+R7) -> 0 | L7: =IFERROR(J7/I7*30.5,0) -> 0 | M7: =SUMIFS(ПРОДАЖИ!$AB:$AB,ПРОДАЖИ!$AD:$AD,'ОБОРАЧИВ ПО СЕТИ+ABC'!$A:$A,ПРОДАЖИ!$AE:$AE,'ОБОРАЧИВ ПО СЕТИ+ABC'!M$1) -> 85160.822 | N7: =SUMIFS(ОСТАТКИ!$AE:$AE,ОСТАТКИ!$Q:$Q,'ОБОРАЧИВ ПО СЕТИ+ABC'!$A:$A,ОСТАТКИ!$S:$S,'ОБОРАЧИВ ПО СЕТИ+ABC'!M$1) -> 74941.523 | O7: =N7/(J7+N7+R7) -> 0.013024742 | P7: =IFERROR(N7/M7*30.5,0) -> 26.84 | Q7: =SUMIFS(ПРОДАЖИ!$AB:$AB,ПРОДАЖИ!$AD:$AD,'ОБОРАЧИВ ПО СЕТИ+ABC'!$A:$A,ПРОДАЖИ!$AE:$AE,'ОБОРАЧИВ ПО СЕТИ+ABC'!Q$1) -> 114033.34 | R7: =SUMIFS(ОСТАТКИ!$AE:$AE,ОСТАТКИ!$Q:$Q,'ОБОРАЧИВ ПО СЕТИ+ABC'!$A:$A,ОСТАТКИ!$S:$S,'ОБОРАЧИВ ПО СЕТИ+ABC'!Q$1) -> 5678840.4 | S7: =R7/(J7+N7+R7) -> 0.98697526 | T7: =IFERROR(R7/Q7*30.5,0) -> 1518.8947
A8: Кромка ПВХ Турция | B8: =SUMIFS(ПРОДАЖИ!AB:AB,ПРОДАЖИ!AD:AD,'ОБОРАЧИВ ПО СЕТИ+ABC'!A:A) -> 1362512 | C8: =B8/$B$3 -> 0.025768937 | D8: =SUMIFS(ОСТАТКИ!AE:AE,ОСТАТКИ!Q:Q,'ОБОРАЧИВ ПО СЕТИ+ABC'!A:A) -> 6265837.7 | E8: =D8/$D$3 -> 0.010144633 | F8: =IFERROR(D8/B8*30.5,0) -> 140.26156 | G8: дн. | I8: =SUMIFS(ПРОДАЖИ!$AB:$AB,ПРОДАЖИ!$AD:$AD,'ОБОРАЧИВ ПО СЕТИ+ABC'!$A:$A,ПРОДАЖИ!$AE:$AE,'ОБОРАЧИВ ПО СЕТИ+ABC'!I$1) -> 0 | J8: =SUMIFS(ОСТАТКИ!$AE:$AE,ОСТАТКИ!$Q:$Q,'ОБОРАЧИВ ПО СЕТИ+ABC'!$A:$A,ОСТАТКИ!$S:$S,'ОБОРАЧИВ ПО СЕТИ+ABC'!I$1) -> 0 | K8: =J8/(J8+N8+R8) -> 0 | L8: =IFERROR(J8/I8*30.5,0) -> 0 | M8: =SUMIFS(ПРОДАЖИ!$AB:$AB,ПРОДАЖИ!$AD:$AD,'ОБОРАЧИВ ПО СЕТИ+ABC'!$A:$A,ПРОДАЖИ!$AE:$AE,'ОБОРАЧИВ ПО СЕТИ+ABC'!M$1) -> 187552.55 | N8: =SUMIFS(ОСТАТКИ!$AE:$AE,ОСТАТКИ!$Q:$Q,'ОБОРАЧИВ ПО СЕТИ+ABC'!$A:$A,ОСТАТКИ!$S:$S,'ОБОРАЧИВ ПО СЕТИ+ABC'!M$1) -> 198494.84 | O8: =N8/(J8+N8+R8) -> 0.031678899 | P8: =IFERROR(N8/M8*30.5,0) -> 32.279447 | Q8: =SUMIFS(ПРОДАЖИ!$AB:$AB,ПРОДАЖИ!$AD:$AD,'ОБОРАЧИВ ПО СЕТИ+ABC'!$A:$A,ПРОДАЖИ!$AE:$AE,'ОБОРАЧИВ ПО СЕТИ+ABC'!Q$1) -> 1174959.4 | R8: =SUMIFS(ОСТАТКИ!$AE:$AE,ОСТАТКИ!$Q:$Q,'ОБОРАЧИВ ПО СЕТИ+ABC'!$A:$A,ОСТАТКИ!$S:$S,'ОБОРАЧИВ ПО СЕТИ+ABC'!Q$1) -> 6067342.9 | S8: =R8/(J8+N8+R8) -> 0.9683211 | T8: =IFERROR(R8/Q8*30.5,0) -> 157.49817
A9: Кромка с клеем Польша | B9: =SUMIFS(ПРОДАЖИ!AB:AB,ПРОДАЖИ!AD:AD,'ОБОРАЧИВ ПО СЕТИ+ABC'!A:A) -> 7140972.5 | C9: =B9/$B$3 -> 0.13505589 | D9: =SUMIFS(ОСТАТКИ!AE:AE,ОСТАТКИ!Q:Q,'ОБОРАЧИВ ПО СЕТИ+ABC'!A:A) -> 61070694 | E9: =D9/$D$3 -> 0.098875813 | F9: =IFERROR(D9/B9*30.5,0) -> 260.84068 | G9: дн. | I9: =SUMIFS(ПРОДАЖИ!$AB:$AB,ПРОДАЖИ!$AD:$AD,'ОБОРАЧИВ ПО СЕТИ+ABC'!$A:$A,ПРОДАЖИ!$AE:$AE,'ОБОРАЧИВ ПО СЕТИ+ABC'!I$1) -> 6051401.5 | J9: =SUMIFS(ОСТАТКИ!$AE:$AE,ОСТАТКИ!$Q:$Q,'ОБОРАЧИВ ПО СЕТИ+ABC'!$A:$A,ОСТАТКИ!$S:$S,'ОБОРАЧИВ ПО СЕТИ+ABC'!I$1) -> 29051783 | K9: =J9/(J9+N9+R9) -> 0.47570744 | L9: =IFERROR(J9/I9*30.5,0) -> 146.42549 | M9: =SUMIFS(ПРОДАЖИ!$AB:$AB,ПРОДАЖИ!$AD:$AD,'ОБОРАЧИВ ПО СЕТИ+ABC'!$A:$A,ПРОДАЖИ!$AE:$AE,'ОБОРАЧИВ ПО СЕТИ+ABC'!M$1) -> 869628.94 | N9: =SUMIFS(ОСТАТКИ!$AE:$AE,ОСТАТКИ!$Q:$Q,'ОБОРАЧИВ ПО СЕТИ+ABC'!$A:$A,ОСТАТКИ!$S:$S,'ОБОРАЧИВ ПО СЕТИ+ABC'!M$1) -> 18470213 | O9: =N9/(J9+N9+R9) -> 0.30243987 | P9: =IFERROR(N9/M9*30.5,0) -> 647.79524 | Q9: =SUMIFS(ПРОДАЖИ!$AB:$AB,ПРОДАЖИ!$AD:$AD,'ОБОРАЧИВ ПО СЕТИ+ABC'!$A:$A,ПРОДАЖИ!$AE:$AE,'ОБОРАЧИВ ПО СЕТИ+ABC'!Q$1) -> 219942.11 | R9: =SUMIFS(ОСТАТКИ!$AE:$AE,ОСТАТКИ!$Q:$Q,'ОБОРАЧИВ ПО СЕТИ+ABC'!$A:$A,ОСТАТКИ!$S:$S,'ОБОРАЧИВ ПО СЕТИ+ABC'!Q$1) -> 13548698 | S9: =R9/(J9+N9+R9) -> 0.22185269 | T9: =IFERROR(R9/Q9*30.5,0) -> 1878.8366
A10: Кромка с клеем Россия | B10: =SUMIFS(ПРОДАЖИ!AB:AB,ПРОДАЖИ!AD:AD,'ОБОРАЧИВ ПО СЕТИ+ABC'!A:A) -> 28895.45 | C10: =B10/$B$3 -> 0.00054649431 | D10: =SUMIFS(ОСТАТКИ!AE:AE,ОСТАТКИ!Q:Q,'ОБОРАЧИВ ПО СЕТИ+ABC'!A:A) -> 367991.8 | E10: =D10/$D$3 -> 0.00059579295 | F10: =IFERROR(D10/B10*30.5,0) -> 388.4262 | G10: дн. | I10: =SUMIFS(ПРОДАЖИ!$AB:$AB,ПРОДАЖИ!$AD:$AD,'ОБОРАЧИВ ПО СЕТИ+ABC'!$A:$A,ПРОДАЖИ!$AE:$AE,'ОБОРАЧИВ ПО СЕТИ+ABC'!I$1) -> 24583.333 | J10: =SUMIFS(ОСТАТКИ!$AE:$AE,ОСТАТКИ!$Q:$Q,'ОБОРАЧИВ ПО СЕТИ+ABC'!$A:$A,ОСТАТКИ!$S:$S,'ОБОРАЧИВ ПО СЕТИ+ABC'!I$1) -> 264500 | K10: =J10/(J10+N10+R10) -> 0.71876602 | L10: =IFERROR(J10/I10*30.5,0) -> 328.15932 | M10: =SUMIFS(ПРОДАЖИ!$AB:$AB,ПРОДАЖИ!$AD:$AD,'ОБОРАЧИВ ПО СЕТИ+ABC'!$A:$A,ПРОДАЖИ!$AE:$AE,'ОБОРАЧИВ ПО СЕТИ+ABC'!M$1) -> 0 | N10: =SUMIFS(ОСТАТКИ!$AE:$AE,ОСТАТКИ!$Q:$Q,'ОБОРАЧИВ ПО СЕТИ+ABC'!$A:$A,ОСТАТКИ!$S:$S,'ОБОРАЧИВ ПО СЕТИ+ABC'!M$1) -> 0 | O10: =N10/(J10+N10+R10) -> 0 | P10: =IFERROR(N10/M10*30.5,0) -> 0 | Q10: =SUMIFS(ПРОДАЖИ!$AB:$AB,ПРОДАЖИ!$AD:$AD,'ОБОРАЧИВ ПО СЕТИ+ABC'!$A:$A,ПРОДАЖИ!$AE:$AE,'ОБОРАЧИВ ПО СЕТИ+ABC'!Q$1) -> 4312.1167 | R10: =SUMIFS(ОСТАТКИ!$AE:$AE,ОСТАТКИ!$Q:$Q,'ОБОРАЧИВ ПО СЕТИ+ABC'!$A:$A,ОСТАТКИ!$S:$S,'ОБОРАЧИВ ПО СЕТИ+ABC'!Q$1) -> 103491.8 | S10: =R10/(J10+N10+R10) -> 0.28123398 | T10: =IFERROR(R10/Q10*30.5,0) -> 732.00707
A11: Кромка с клеем Турция | B11: =SUMIFS(ПРОДАЖИ!AB:AB,ПРОДАЖИ!AD:AD,'ОБОРАЧИВ ПО СЕТИ+ABC'!A:A) -> 14026.028 | C11: =B11/$B$3 -> 0.00026527168 | D11: =SUMIFS(ОСТАТКИ!AE:AE,ОСТАТКИ!Q:Q,'ОБОРАЧИВ ПО СЕТИ+ABC'!A:A) -> 205819.04 | E11: =D11/$D$3 -> 0.00033322898 | F11: =IFERROR(D11/B11*30.5,0) -> 447.55939 | G11: дн. | I11: =SUMIFS(ПРОДАЖИ!$AB:$AB,ПРОДАЖИ!$AD:$AD,'ОБОРАЧИВ ПО СЕТИ+ABC'!$A:$A,ПРОДАЖИ!$AE:$AE,'ОБОРАЧИВ ПО СЕТИ+ABC'!I$1) -> 0 | J11: =SUMIFS(ОСТАТКИ!$AE:$AE,ОСТАТКИ!$Q:$Q,'ОБОРАЧИВ ПО СЕТИ+ABC'!$A:$A,ОСТАТКИ!$S:$S,'ОБОРАЧИВ ПО СЕТИ+ABC'!I$1) -> 0 | K11: =J11/(J11+N11+R11) -> 0 | L11: =IFERROR(J11/I11*30.5,0) -> 0 | M11: =SUMIFS(ПРОДАЖИ!$AB:$AB,ПРОДАЖИ!$AD:$AD,'ОБОРАЧИВ ПО СЕТИ+ABC'!$A:$A,ПРОДАЖИ!$AE:$AE,'ОБОРАЧИВ ПО СЕТИ+ABC'!M$1) -> 0 | N11: =SUMIFS(ОСТАТКИ!$AE:$AE,ОСТАТКИ!$Q:$Q,'ОБОРАЧИВ ПО СЕТИ+ABC'!$A:$A,ОСТАТКИ!$S:$S,'ОБОРАЧИВ ПО СЕТИ+ABC'!M$1) -> 0 | O11: =N11/(J11+N11+R11) -> 0 | P11: =IFERROR(N11/M11*30.5,0) -> 0 | Q11: =SUMIFS(ПРОДАЖИ!$AB:$AB,ПРОДАЖИ!$AD:$AD,'ОБОРАЧИВ ПО СЕТИ+ABC'!$A:$A,ПРОДАЖИ!$AE:$AE,'ОБОРАЧИВ ПО СЕТИ+ABC'!Q$1) -> 14026.028 | R11: =SUMIFS(ОСТАТКИ!$AE:$AE,ОСТАТКИ!$Q:$Q,'ОБОРАЧИВ ПО СЕТИ+ABC'!$A:$A,ОСТАТКИ!$S:$S,'ОБОРАЧИВ ПО СЕТИ+ABC'!Q$1) -> 205819.04 | S11: =R11/(J11+N11+R11) -> 1 | T11: =IFERROR(R11/Q11*30.5,0) -> 447.55939
A12: Кромка с клеем Украина | B12: =SUMIFS(ПРОДАЖИ!AB:AB,ПРОДАЖИ!AD:AD,'ОБОРАЧИВ ПО СЕТИ+ABC'!A:A) -> 642840.1 | C12: =B12/$B$3 -> 0.012157916 | D12: =SUMIFS(ОСТАТКИ!AE:AE,ОСТАТКИ!Q:Q,'ОБОРАЧИВ ПО СЕТИ+ABC'!A:A) -> 10902256 | E12: =D12/$D$3 -> 0.017651174 | F12: =IFERROR(D12/B12*30.5,0) -> 517.2652 | G12: дн. | I12: =SUMIFS(ПРОДАЖИ!$AB:$AB,ПРОДАЖИ!$AD:$AD,'ОБОРАЧИВ ПО СЕТИ+ABC'!$A:$A,ПРОДАЖИ!$AE:$AE,'ОБОРАЧИВ ПО СЕТИ+ABC'!I$1) -> 157283.06 | J12: =SUMIFS(ОСТАТКИ!$AE:$AE,ОСТАТКИ!$Q:$Q,'ОБОРАЧИВ ПО СЕТИ+ABC'!$A:$A,ОСТАТКИ!$S:$S,'ОБОРАЧИВ ПО СЕТИ+ABC'!I$1) -> 921053.79 | K12: =J12/(J12+N12+R12) -> 0.084482861 | L12: =IFERROR(J12/I12*30.5,0) -> 178.60881 | M12: =SUMIFS(ПРОДАЖИ!$AB:$AB,ПРОДАЖИ!$AD:$AD,'ОБОРАЧИВ ПО СЕТИ+ABC'!$A:$A,ПРОДАЖИ!$AE:$AE,'ОБОРАЧИВ ПО СЕТИ+ABC'!M$1) -> 342197.88 | N12: =SUMIFS(ОСТАТКИ!$AE:$AE,ОСТАТКИ!$Q:$Q,'ОБОРАЧИВ ПО СЕТИ+ABC'!$A:$A,ОСТАТКИ!$S:$S,'ОБОРАЧИВ ПО СЕТИ+ABC'!M$1) -> 7960769.4 | O12: =N12/(J12+N12+R12) -> 0.73019467 | P12: =IFERROR(N12/M12*30.5,0) -> 709.54111 | Q12: =SUMIFS(ПРОДАЖИ!$AB:$AB,ПРОДАЖИ!$AD:$AD,'ОБОРАЧИВ ПО СЕТИ+ABC'!$A:$A,ПРОДАЖИ!$AE:$AE,'ОБОРАЧИВ ПО СЕТИ+ABC'!Q$1) -> 143359.15 | R12: =SUMIFS(ОСТАТКИ!$AE:$AE,ОСТАТКИ!$Q:$Q,'ОБОРАЧИВ ПО СЕТИ+ABC'!$A:$A,ОСТАТКИ!$S:$S,'ОБОРАЧИВ ПО СЕТИ+ABC'!Q$1) -> 2020433 | S12: =R12/(J12+N12+R12) -> 0.18532247 | T12: =IFERROR(R12/Q12*30.5,0) -> 429.85192
A13: Кромка ABS | B13: =SUMIFS(ПРОДАЖИ!AB:AB,ПРОДАЖИ!AD:AD,'ОБОРАЧИВ ПО СЕТИ+ABC'!A:A) -> 21629.124 | C13: =B13/$B$3 -> 0.00040906763 | D13: =SUMIFS(ОСТАТКИ!AE:AE,ОСТАТКИ!Q:Q,'ОБОРАЧИВ ПО СЕТИ+ABC'!A:A) -> 532281.19 | E13: =D13/$D$3 -> 0.00086178381 | F13: =IFERROR(D13/B13*30.5,0) -> 750.5887 | G13: дн. | I13: =SUMIFS(ПРОДАЖИ!$AB:$AB,ПРОДАЖИ!$AD:$AD,'ОБОРАЧИВ ПО СЕТИ+ABC'!$A:$A,ПРОДАЖИ!$AE:$AE,'ОБОРАЧИВ ПО СЕТИ+ABC'!I$1) -> 0 | J13: =SUMIFS(ОСТАТКИ!$AE:$AE,ОСТАТКИ!$Q:$Q,'ОБОРАЧИВ ПО СЕТИ+ABC'!$A:$A,ОСТАТКИ!$S:$S,'ОБОРАЧИВ ПО СЕТИ+ABC'!I$1) -> 0 | K13: =J13/(J13+N13+R13) -> 0 | L13: =IFERROR(J13/I13*30.5,0) -> 0 | M13: =SUMIFS(ПРОДАЖИ!$AB:$AB,ПРОДАЖИ!$AD:$AD,'ОБОРАЧИВ ПО СЕТИ+ABC'!$A:$A,ПРОДАЖИ!$AE:$AE,'ОБОРАЧИВ ПО СЕТИ+ABC'!M$1) -> 0 | N13: =SUMIFS(ОСТАТКИ!$AE:$AE,ОСТАТКИ!$Q:$Q,'ОБОРАЧИВ ПО СЕТИ+ABC'!$A:$A,ОСТАТКИ!$S:$S,'ОБОРАЧИВ ПО СЕТИ+ABC'!M$1) -> 0 | O13: =N13/(J13+N13+R13) -> 0 | P13: =IFERROR(N13/M13*30.5,0) -> 0 | Q13: =SUMIFS(ПРОДАЖИ!$AB:$AB,ПРОДАЖИ!$AD:$AD,'ОБОРАЧИВ ПО СЕТИ+ABC'!$A:$A,ПРОДАЖИ!$AE:$AE,'ОБОРАЧИВ ПО СЕТИ+ABC'!Q$1) -> 21629.124 | R13: =SUMIFS(ОСТАТКИ!$AE:$AE,ОСТАТКИ!$Q:$Q,'ОБОРАЧИВ ПО СЕТИ+ABC'!$A:$A,ОСТАТКИ!$S:$S,'ОБОРАЧИВ ПО СЕТИ+ABC'!Q$1) -> 532281.19 | S13: =R13/(J13+N13+R13) -> 1 | T13: =IFERROR(R13/Q13*30.5,0) -> 750.5887
A14: Распродажа кромка | B14: =SUMIFS(ПРОДАЖИ!AB:AB,ПРОДАЖИ!AD:AD,'ОБОРАЧИВ ПО СЕТИ+ABC'!A:A) -> 209842.44 | C14: =B14/$B$3 -> 0.0039687113 | D14: =SUMIFS(ОСТАТКИ!AE:AE,ОСТАТКИ!Q:Q,'ОБОРАЧИВ ПО СЕТИ+ABC'!A:A) -> 12120249 | E14: =D14/$D$3 -> 0.019623151 | F14: =IFERROR(D14/B14*30.5,0) -> 1761.6436 | G14: дн. | I14: =SUMIFS(ПРОДАЖИ!$AB:$AB,ПРОДАЖИ!$AD:$AD,'ОБОРАЧИВ ПО СЕТИ+ABC'!$A:$A,ПРОДАЖИ!$AE:$AE,'ОБОРАЧИВ ПО СЕТИ+ABC'!I$1) -> 0 | J14: =SUMIFS(ОСТАТКИ!$AE:$AE,ОСТАТКИ!$Q:$Q,'ОБОРАЧИВ ПО СЕТИ+ABC'!$A:$A,ОСТАТКИ!$S:$S,'ОБОРАЧИВ ПО СЕТИ+ABC'!I$1) -> 0 | K14: =J14/(J14+N14+R14) -> 0 | L14: =IFERROR(J14/I14*30.5,0) -> 0 | M14: =SUMIFS(ПРОДАЖИ!$AB:$AB,ПРОДАЖИ!$AD:$AD,'ОБОРАЧИВ ПО СЕТИ+ABC'!$A:$A,ПРОДАЖИ!$AE:$AE,'ОБОРАЧИВ ПО СЕТИ+ABC'!M$1) -> 63722.322 | N14: =SUMIFS(ОСТАТКИ!$AE:$AE,ОСТАТКИ!$Q:$Q,'ОБОРАЧИВ ПО СЕТИ+ABC'!$A:$A,ОСТАТКИ!$S:$S,'ОБОРАЧИВ ПО СЕТИ+ABC'!M$1) -> 3701857.3 | O14: =N14/(J14+N14+R14) -> 0.3054275 | P14: =IFERROR(N14/M14*30.5,0) -> 1771.854 | Q14: =SUMIFS(ПРОДАЖИ!$AB:$AB,ПРОДАЖИ!$AD:$AD,'ОБОРАЧИВ ПО СЕТИ+ABC'!$A:$A,ПРОДАЖИ!$AE:$AE,'ОБОРАЧИВ ПО СЕТИ+ABC'!Q$1) -> 146120.12 | R14: =SUMIFS(ОСТАТКИ!$AE:$AE,ОСТАТКИ!$Q:$Q,'ОБОРАЧИВ ПО СЕТИ+ABC'!$A:$A,ОСТАТКИ!$S:$S,'ОБОРАЧИВ ПО СЕТИ+ABC'!Q$1) -> 8418391.6 | S14: =R14/(J14+N14+R14) -> 0.6945725 | T14: =IFERROR(R14/Q14*30.5,0) -> 1757.1909
A15: Аксессуары для кухни | B15: =SUM(B16:B31) -> 26942883 | C15: =B15/$B$139 -> 0.21035055 | D15: =SUM(D16:D31) -> 2.8209086e+08 | E15: =D15/$D$139 -> 0.16322852 | F15: =IFERROR(D15/B15*30.5,0) -> 319.33372 | G15: дн. | I15: =SUM(I16:I31) -> 17377868 | J15: =SUM(J16:J31) -> 1.5364853e+08 | K15: =J15/(J15+N15+R15) -> 0.54467745 | L15: =IFERROR(J15/I15*30.5,0) -> 269.66945 | M15: =SUM(M16:M31) -> 6703678.8 | N15: =SUM(N16:N31) -> 62343818 | O15: =N15/(J15+N15+R15) -> 0.22100616 | P15: =IFERROR(N15/M15*30.5,0) -> 283.64821 | Q15: =SUM(Q16:Q31) -> 2861336.4 | R15: =SUM(R16:R31) -> 66098512 | S15: =R15/(J15+N15+R15) -> 0.23431639 | T15: =IFERROR(R15/Q15*30.5,0) -> 704.5675
A16: Посудосушители сетчатые полимерное покрытие | B16: =SUMIFS(ПРОДАЖИ!AB:AB,ПРОДАЖИ!AD:AD,'ОБОРАЧИВ ПО СЕТИ+ABC'!A:A) -> 10909956 | C16: =B16/$B$15 -> 0.40492904 | D16: =SUMIFS(ОСТАТКИ!AE:AE,ОСТАТКИ!Q:Q,'ОБОРАЧИВ ПО СЕТИ+ABC'!A:A) -> 1.0265817e+08 | E16: =D16/$D$15 -> 0.36391881 | F16: =IFERROR(D16/B16*30.5,0) -> 286.99237 | G16: дн. | I16: =SUMIFS(ПРОДАЖИ!$AB:$AB,ПРОДАЖИ!$AD:$AD,'ОБОРАЧИВ ПО СЕТИ+ABC'!$A:$A,ПРОДАЖИ!$AE:$AE,'ОБОРАЧИВ ПО СЕТИ+ABC'!I$1) -> 10167136 | J16: =SUMIFS(ОСТАТКИ!$AE:$AE,ОСТАТКИ!$Q:$Q,'ОБОРАЧИВ ПО СЕТИ+ABC'!$A:$A,ОСТАТКИ!$S:$S,'ОБОРАЧИВ ПО СЕТИ+ABC'!I$1) -> 84555411 | K16: =J16/(J16+N16+R16) -> 0.82365983 | L16: =IFERROR(J16/I16*30.5,0) -> 253.65452 | M16: =SUMIFS(ПРОДАЖИ!$AB:$AB,ПРОДАЖИ!$AD:$AD,'ОБОРАЧИВ ПО СЕТИ+ABC'!$A:$A,ПРОДАЖИ!$AE:$AE,'ОБОРАЧИВ ПО СЕТИ+ABC'!M$1) -> 629129.24 | N16: =SUMIFS(ОСТАТКИ!$AE:$AE,ОСТАТКИ!$Q:$Q,'ОБОРАЧИВ ПО СЕТИ+ABC'!$A:$A,ОСТАТКИ!$S:$S,'ОБОРАЧИВ ПО СЕТИ+ABC'!M$1) -> 8491658.7 | O16: =N16/(J16+N16+R16) -> 0.082717807 | P16: =IFERROR(N16/M16*30.5,0) -> 411.67311 | Q16: =SUMIFS(ПРОДАЖИ!$AB:$AB,ПРОДАЖИ!$AD:$AD,'ОБОРАЧИВ ПО СЕТИ+ABC'!$A:$A,ПРОДАЖИ!$AE:$AE,'ОБОРАЧИВ ПО СЕТИ+ABC'!Q$1) -> 113690.57 | R16: =SUMIFS(ОСТАТКИ!$AE:$AE,ОСТАТКИ!$Q:$Q,'ОБОРАЧИВ ПО СЕТИ+ABC'!$A:$A,ОСТАТКИ!$S:$S,'ОБОРАЧИВ ПО СЕТИ+ABC'!Q$1) -> 9611100.3 | S16: =R16/(J16+N16+R16) -> 0.093622361 | T16: =IFERROR(R16/Q16*30.5,0) -> 2578.3894
A17: Посудосушители из нержавеющей стали | B17: =SUMIFS(ПРОДАЖИ!AB:AB,ПРОДАЖИ!AD:AD,'ОБОРАЧИВ ПО СЕТИ+ABC'!A:A) -> 4768282.7 | C17: =B17/$B$15 -> 0.17697745 | D17: =SUMIFS(ОСТАТКИ!AE:AE,ОСТАТКИ!Q:Q,'ОБОРАЧИВ ПО СЕТИ+ABC'!A:A) -> 37162536 | E17: =D17/$D$15 -> 0.1317396 | F17: =IFERROR(D17/B17*30.5,0) -> 237.70766 | G17: дн. | I17: =SUMIFS(ПРОДАЖИ!$AB:$AB,ПРОДАЖИ!$AD:$AD,'ОБОРАЧИВ ПО СЕТИ+ABC'!$A:$A,ПРОДАЖИ!$AE:$AE,'ОБОРАЧИВ ПО СЕТИ+ABC'!I$1) -> 3942912.6 | J17: =SUMIFS(ОСТАТКИ!$AE:$AE,ОСТАТКИ!$Q:$Q,'ОБОРАЧИВ ПО СЕТИ+ABC'!$A:$A,ОСТАТКИ!$S:$S,'ОБОРАЧИВ ПО СЕТИ+ABC'!I$1) -> 28780101 | K17: =J17/(J17+N17+R17) -> 0.77443856 | L17: =IFERROR(J17/I17*30.5,0) -> 222.62555 | M17: =SUMIFS(ПРОДАЖИ!$AB:$AB,ПРОДАЖИ!$AD:$AD,'ОБОРАЧИВ ПО СЕТИ+ABC'!$A:$A,ПРОДАЖИ!$AE:$AE,'ОБОРАЧИВ ПО СЕТИ+ABC'!M$1) -> 711790.98 | N17: =SUMIFS(ОСТАТКИ!$AE:$AE,ОСТАТКИ!$Q:$Q,'ОБОРАЧИВ ПО СЕТИ+ABC'!$A:$A,ОСТАТКИ!$S:$S,'ОБОРАЧИВ ПО СЕТИ+ABC'!M$1) -> 6991182.2 | O17: =N17/(J17+N17+R17) -> 0.18812447 | P17: =IFERROR(N17/M17*30.5,0) -> 299.56977 | Q17: =SUMIFS(ПРОДАЖИ!$AB:$AB,ПРОДАЖИ!$AD:$AD,'ОБОРАЧИВ ПО СЕТИ+ABC'!$A:$A,ПРОДАЖИ!$AE:$AE,'ОБОРАЧИВ ПО СЕТИ+ABC'!Q$1) -> 113579.14 | R17: =SUMIFS(ОСТАТКИ!$AE:$AE,ОСТАТКИ!$Q:$Q,'ОБОРАЧИВ ПО СЕТИ+ABC'!$A:$A,ОСТАТКИ!$S:$S,'ОБОРАЧИВ ПО СЕТИ+ABC'!Q$1) -> 1391252.8 | S17: =R17/(J17+N17+R17) -> 0.037436973 | T17: =IFERROR(R17/Q17*30.5,0) -> 373.60038
A18: Посудосушители из хромированной стали | B18: =SUMIFS(ПРОДАЖИ!AB:AB,ПРОДАЖИ!AD:AD,'ОБОРАЧИВ ПО СЕТИ+ABC'!A:A) -> 2218936 | C18: =B18/$B$15 -> 0.082357034 | D18: =SUMIFS(ОСТАТКИ!AE:AE,ОСТАТКИ!Q:Q,'ОБОРАЧИВ ПО СЕТИ+ABC'!A:A) -> 38462093 | E18: =D18/$D$15 -> 0.13634647 | F18: =IFERROR(D18/B18*30.5,0) -> 528.67403 | G18: дн. | I18: =SUMIFS(ПРОДАЖИ!$AB:$AB,ПРОДАЖИ!$AD:$AD,'ОБОРАЧИВ ПО СЕТИ+ABC'!$A:$A,ПРОДАЖИ!$AE:$AE,'ОБОРАЧИВ ПО СЕТИ+ABC'!I$1) -> 1885145.4 | J18: =SUMIFS(ОСТАТКИ!$AE:$AE,ОСТАТКИ!$Q:$Q,'ОБОРАЧИВ ПО СЕТИ+ABC'!$A:$A,ОСТАТКИ!$S:$S,'ОБОРАЧИВ ПО СЕТИ+ABC'!I$1) -> 31884579 | K18: =J18/(J18+N18+R18) -> 0.8289871 | L18: =IFERROR(J18/I18*30.5,0) -> 515.86452 | M18: =SUMIFS(ПРОДАЖИ!$AB:$AB,ПРОДАЖИ!$AD:$AD,'ОБОРАЧИВ ПО СЕТИ+ABC'!$A:$A,ПРОДАЖИ!$AE:$AE,'ОБОРАЧИВ ПО СЕТИ+ABC'!M$1) -> 256107.26 | N18: =SUMIFS(ОСТАТКИ!$AE:$AE,ОСТАТКИ!$Q:$Q,'ОБОРАЧИВ ПО СЕТИ+ABC'!$A:$A,ОСТАТКИ!$S:$S,'ОБОРАЧИВ ПО СЕТИ+ABC'!M$1) -> 4449863.6 | O18: =N18/(J18+N18+R18) -> 0.11569479 | P18: =IFERROR(N18/M18*30.5,0) -> 529.9375 | Q18: =SUMIFS(ПРОДАЖИ!$AB:$AB,ПРОДАЖИ!$AD:$AD,'ОБОРАЧИВ ПО СЕТИ+ABC'!$A:$A,ПРОДАЖИ!$AE:$AE,'ОБОРАЧИВ ПО СЕТИ+ABC'!Q$1) -> 77683.268 | R18: =SUMIFS(ОСТАТКИ!$AE:$AE,ОСТАТКИ!$Q:$Q,'ОБОРАЧИВ ПО СЕТИ+ABC'!$A:$A,ОСТАТКИ!$S:$S,'ОБОРАЧИВ ПО СЕТИ+ABC'!Q$1) -> 2127650.4 | S18: =R18/(J18+N18+R18) -> 0.055318114 | T18: =IFERROR(R18/Q18*30.5,0) -> 835.35798
A19: Поддоны | B19: =SUMIFS(ПРОДАЖИ!AB:AB,ПРОДАЖИ!AD:AD,'ОБОРАЧИВ ПО СЕТИ+ABC'!A:A) -> 31755.429 | C19: =B19/$B$15 -> 0.0011786203 | D19: =SUMIFS(ОСТАТКИ!AE:AE,ОСТАТКИ!Q:Q,'ОБОРАЧИВ ПО СЕТИ+ABC'!A:A) -> 4589373 | E19: =D19/$D$15 -> 0.01626913 | F19: =IFERROR(D19/B19*30.5,0) -> 4407.9353 | G19: дн. | I19: =SUMIFS(ПРОДАЖИ!$AB:$AB,ПРОДАЖИ!$AD:$AD,'ОБОРАЧИВ ПО СЕТИ+ABC'!$A:$A,ПРОДАЖИ!$AE:$AE,'ОБОРАЧИВ ПО СЕТИ+ABC'!I$1) -> 0 | J19: =SUMIFS(ОСТАТКИ!$AE:$AE,ОСТАТКИ!$Q:$Q,'ОБОРАЧИВ ПО СЕТИ+ABC'!$A:$A,ОСТАТКИ!$S:$S,'ОБОРАЧИВ ПО СЕТИ+ABC'!I$1) -> 0 | K19: =J19/(J19+N19+R19) -> 0 | L19: =IFERROR(J19/I19*30.5,0) -> 0 | M19: =SUMIFS(ПРОДАЖИ!$AB:$AB,ПРОДАЖИ!$AD:$AD,'ОБОРАЧИВ ПО СЕТИ+ABC'!$A:$A,ПРОДАЖИ!$AE:$AE,'ОБОРАЧИВ ПО СЕТИ+ABC'!M$1) -> 9263.735 | N19: =SUMIFS(ОСТАТКИ!$AE:$AE,ОСТАТКИ!$Q:$Q,'ОБОРАЧИВ ПО СЕТИ+ABC'!$A:$A,ОСТАТКИ!$S:$S,'ОБОРАЧИВ ПО СЕТИ+ABC'!M$1) -> 484826.26 | O19: =N19/(J19+N19+R19) -> 0.10564107 | P19: =IFERROR(N19/M19*30.5,0) -> 1596.2461 | Q19: =SUMIFS(ПРОДАЖИ!$AB:$AB,ПРОДАЖИ!$AD:$AD,'ОБОРАЧИВ ПО СЕТИ+ABC'!$A:$A,ПРОДАЖИ!$AE:$AE,'ОБОРАЧИВ ПО СЕТИ+ABC'!Q$1) -> 22491.694 | R19: =SUMIFS(ОСТАТКИ!$AE:$AE,ОСТАТКИ!$Q:$Q,'ОБОРАЧИВ ПО СЕТИ+ABC'!$A:$A,ОСТАТКИ!$S:$S,'ОБОРАЧИВ ПО СЕТИ+ABC'!Q$1) -> 4104546.7 | S19: =R19/(J19+N19+R19) -> 0.89435893 | T19: =IFERROR(R19/Q19*30.5,0) -> 5565.9958
A20: Корзины встраиваемые выкатные | B20: =SUMIFS(ПРОДАЖИ!AB:AB,ПРОДАЖИ!AD:AD,'ОБОРАЧИВ ПО СЕТИ+ABC'!A:A) -> 6974989.4 | C20: =B20/$B$15 -> 0.25888058 | D20: =SUMIFS(ОСТАТКИ!AE:AE,ОСТАТКИ!Q:Q,'ОБОРАЧИВ ПО СЕТИ+ABC'!A:A) -> 82678770 | E20: =D20/$D$15 -> 0.29309269 | F20: =IFERROR(D20/B20*30.5,0) -> 361.53496 | G20: дн. | I20: =SUMIFS(ПРОДАЖИ!$AB:$AB,ПРОДАЖИ!$AD:$AD,'ОБОРАЧИВ ПО СЕТИ+ABC'!$A:$A,ПРОДАЖИ!$AE:$AE,'ОБОРАЧИВ ПО СЕТИ+ABC'!I$1) -> 1382674 | J20: =SUMIFS(ОСТАТКИ!$AE:$AE,ОСТАТКИ!$Q:$Q,'ОБОРАЧИВ ПО СЕТИ+ABC'!$A:$A,ОСТАТКИ!$S:$S,'ОБОРАЧИВ ПО СЕТИ+ABC'!I$1) -> 8428439.5 | K20: =J20/(J20+N20+R20) -> 0.10194201 | L20: =IFERROR(J20/I20*30.5,0) -> 185.92048 | M20: =SUMIFS(ПРОДАЖИ!$AB:$AB,ПРОДАЖИ!$AD:$AD,'ОБОРАЧИВ ПО СЕТИ+ABC'!$A:$A,ПРОДАЖИ!$AE:$AE,'ОБОРАЧИВ ПО СЕТИ+ABC'!M$1) -> 4895026.8 | N20: =SUMIFS(ОСТАТКИ!$AE:$AE,ОСТАТКИ!$Q:$Q,'ОБОРАЧИВ ПО СЕТИ+ABC'!$A:$A,ОСТАТКИ!$S:$S,'ОБОРАЧИВ ПО СЕТИ+ABC'!M$1) -> 41545214 | O20: =N20/(J20+N20+R20) -> 0.50248951 | P20: =IFERROR(N20/M20*30.5,0) -> 258.86049 | Q20: =SUMIFS(ПРОДАЖИ!$AB:$AB,ПРОДАЖИ!$AD:$AD,'ОБОРАЧИВ ПО СЕТИ+ABC'!$A:$A,ПРОДАЖИ!$AE:$AE,'ОБОРАЧИВ ПО СЕТИ+ABC'!Q$1) -> 697288.58 | R20: =SUMIFS(ОСТАТКИ!$AE:$AE,ОСТАТКИ!$Q:$Q,'ОБОРАЧИВ ПО СЕТИ+ABC'!$A:$A,ОСТАТКИ!$S:$S,'ОБОРАЧИВ ПО СЕТИ+ABC'!Q$1) -> 32705116 | S20: =R20/(J20+N20+R20) -> 0.39556849 | T20: =IFERROR(R20/Q20*30.5,0) -> 1430.5498
A21: Корзины для хранения | B21: =SUMIFS(ПРОДАЖИ!AB:AB,ПРОДАЖИ!AD:AD,'ОБОРАЧИВ ПО СЕТИ+ABC'!A:A) -> 11318.551 | C21: =B21/$B$15 -> 0.00042009427 | D21: =SUMIFS(ОСТАТКИ!AE:AE,ОСТАТКИ!Q:Q,'ОБОРАЧИВ ПО СЕТИ+ABC'!A:A) -> 1064141.5 | E21: =D21/$D$15 -> 0.0037723359 | F21: =IFERROR(D21/B21*30.5,0) -> 2867.5327 | G21: дн. | I21: =SUMIFS(ПРОДАЖИ!$AB:$AB,ПРОДАЖИ!$AD:$AD,'ОБОРАЧИВ ПО СЕТИ+ABC'!$A:$A,ПРОДАЖИ!$AE:$AE,'ОБОРАЧИВ ПО СЕТИ+ABC'!I$1) -> 0 | J21: =SUMIFS(ОСТАТКИ!$AE:$AE,ОСТАТКИ!$Q:$Q,'ОБОРАЧИВ ПО СЕТИ+ABC'!$A:$A,ОСТАТКИ!$S:$S,'ОБОРАЧИВ ПО СЕТИ+ABC'!I$1) -> 0 | K21: =J21/(J21+N21+R21) -> 0 | L21: =IFERROR(J21/I21*30.5,0) -> 0 | M21: =SUMIFS(ПРОДАЖИ!$AB:$AB,ПРОДАЖИ!$AD:$AD,'ОБОРАЧИВ ПО СЕТИ+ABC'!$A:$A,ПРОДАЖИ!$AE:$AE,'ОБОРАЧИВ ПО СЕТИ+ABC'!M$1) -> 0 | N21: =SUMIFS(ОСТАТКИ!$AE:$AE,ОСТАТКИ!$Q:$Q,'ОБОРАЧИВ ПО СЕТИ+ABC'!$A:$A,ОСТАТКИ!$S:$S,'ОБОРАЧИВ ПО СЕТИ+ABC'!M$1) -> 0 | O21: =N21/(J21+N21+R21) -> 0 | P21: =IFERROR(N21/M21*30.5,0) -> 0 | Q21: =SUMIFS(ПРОДАЖИ!$AB:$AB,ПРОДАЖИ!$AD:$AD,'ОБОРАЧИВ ПО СЕТИ+ABC'!$A:$A,ПРОДАЖИ!$AE:$AE,'ОБОРАЧИВ ПО СЕТИ+ABC'!Q$1) -> 11318.551 | R21: =SUMIFS(ОСТАТКИ!$AE:$AE,ОСТАТКИ!$Q:$Q,'ОБОРАЧИВ ПО СЕТИ+ABC'!$A:$A,ОСТАТКИ!$S:$S,'ОБОРАЧИВ ПО СЕТИ+ABC'!Q$1) -> 1064141.5 | S21: =R21/(J21+N21+R21) -> 1 | T21: =IFERROR(R21/Q21*30.5,0) -> 2867.5327
A22: 1 чаша | B22: =SUMIFS(ПРОДАЖИ!AB:AB,ПРОДАЖИ!AD:AD,'ОБОРАЧИВ ПО СЕТИ+ABC'!A:A) -> 800979.42 | C22: =B22/$B$15 -> 0.029728794 | D22: =SUMIFS(ОСТАТКИ!AE:AE,ОСТАТКИ!Q:Q,'ОБОРАЧИВ ПО СЕТИ+ABC'!A:A) -> 4628521.6 | E22: =D22/$D$15 -> 0.01640791 | F22: =IFERROR(D22/B22*30.5,0) -> 176.24661 | G22: дн. | I22: =SUMIFS(ПРОДАЖИ!$AB:$AB,ПРОДАЖИ!$AD:$AD,'ОБОРАЧИВ ПО СЕТИ+ABC'!$A:$A,ПРОДАЖИ!$AE:$AE,'ОБОРАЧИВ ПО СЕТИ+ABC'!I$1) -> 0 | J22: =SUMIFS(ОСТАТКИ!$AE:$AE,ОСТАТКИ!$Q:$Q,'ОБОРАЧИВ ПО СЕТИ+ABC'!$A:$A,ОСТАТКИ!$S:$S,'ОБОРАЧИВ ПО СЕТИ+ABC'!I$1) -> 0 | K22: =J22/(J22+N22+R22) -> 0 | L22: =IFERROR(J22/I22*30.5,0) -> 0 | M22: =SUMIFS(ПРОДАЖИ!$AB:$AB,ПРОДАЖИ!$AD:$AD,'ОБОРАЧИВ ПО СЕТИ+ABC'!$A:$A,ПРОДАЖИ!$AE:$AE,'ОБОРАЧИВ ПО СЕТИ+ABC'!M$1) -> 202360.79 | N22: =SUMIFS(ОСТАТКИ!$AE:$AE,ОСТАТКИ!$Q:$Q,'ОБОРАЧИВ ПО СЕТИ+ABC'!$A:$A,ОСТАТКИ!$S:$S,'ОБОРАЧИВ ПО СЕТИ+ABC'!M$1) -> 381073.41 | O22: =N22/(J22+N22+R22) -> 0.082331562 | P22: =IFERROR(N22/M22*30.5,0) -> 57.435726 | Q22: =SUMIFS(ПРОДАЖИ!$AB:$AB,ПРОДАЖИ!$AD:$AD,'ОБОРАЧИВ ПО СЕТИ+ABC'!$A:$A,ПРОДАЖИ!$AE:$AE,'ОБОРАЧИВ ПО СЕТИ+ABC'!Q$1) -> 598618.63 | R22: =SUMIFS(ОСТАТКИ!$AE:$AE,ОСТАТКИ!$Q:$Q,'ОБОРАЧИВ ПО СЕТИ+ABC'!$A:$A,ОСТАТКИ!$S:$S,'ОБОРАЧИВ ПО СЕТИ+ABC'!Q$1) -> 4247448.2 | S22: =R22/(J22+N22+R22) -> 0.91766844 | T22: =IFERROR(R22/Q22*30.5,0) -> 216.41019
A23: 2 чаши | B23: =SUMIFS(ПРОДАЖИ!AB:AB,ПРОДАЖИ!AD:AD,'ОБОРАЧИВ ПО СЕТИ+ABC'!A:A) -> 44806.667 | C23: =B23/$B$15 -> 0.0016630242 | D23: =SUMIFS(ОСТАТКИ!AE:AE,ОСТАТКИ!Q:Q,'ОБОРАЧИВ ПО СЕТИ+ABC'!A:A) -> 685486.5 | E23: =D23/$D$15 -> 0.0024300202 | F23: =IFERROR(D23/B23*30.5,0) -> 466.61222 | G23: дн. | I23: =SUMIFS(ПРОДАЖИ!$AB:$AB,ПРОДАЖИ!$AD:$AD,'ОБОРАЧИВ ПО СЕТИ+ABC'!$A:$A,ПРОДАЖИ!$AE:$AE,'ОБОРАЧИВ ПО СЕТИ+ABC'!I$1) -> 0 | J23: =SUMIFS(ОСТАТКИ!$AE:$AE,ОСТАТКИ!$Q:$Q,'ОБОРАЧИВ ПО СЕТИ+ABC'!$A:$A,ОСТАТКИ!$S:$S,'ОБОРАЧИВ ПО СЕТИ+ABC'!I$1) -> 0 | K23: =J23/(J23+N23+R23) -> 0 | L23: =IFERROR(J23/I23*30.5,0) -> 0 | M23: =SUMIFS(ПРОДАЖИ!$AB:$AB,ПРОДАЖИ!$AD:$AD,'ОБОРАЧИВ ПО СЕТИ+ABC'!$A:$A,ПРОДАЖИ!$AE:$AE,'ОБОРАЧИВ ПО СЕТИ+ABC'!M$1) -> 0 | N23: =SUMIFS(ОСТАТКИ!$AE:$AE,ОСТАТКИ!$Q:$Q,'ОБОРАЧИВ ПО СЕТИ+ABC'!$A:$A,ОСТАТКИ!$S:$S,'ОБОРАЧИВ ПО СЕТИ+ABC'!M$1) -> 0 | O23: =N23/(J23+N23+R23) -> 0 | P23: =IFERROR(N23/M23*30.5,0) -> 0 | Q23: =SUMIFS(ПРОДАЖИ!$AB:$AB,ПРОДАЖИ!$AD:$AD,'ОБОРАЧИВ ПО СЕТИ+ABC'!$A:$A,ПРОДАЖИ!$AE:$AE,'ОБОРАЧИВ ПО СЕТИ+ABC'!Q$1) -> 44806.667 | R23: =SUMIFS(ОСТАТКИ!$AE:$AE,ОСТАТКИ!$Q:$Q,'ОБОРАЧИВ ПО СЕТИ+ABC'!$A:$A,ОСТАТКИ!$S:$S,'ОБОРАЧИВ ПО СЕТИ+ABC'!Q$1) -> 685486.5 | S23: =R23/(J23+N23+R23) -> 1 | T23: =IFERROR(R23/Q23*30.5,0) -> 466.61222
A24: Мойки из камня | B24: =SUMIFS(ПРОДАЖИ!AB:AB,ПРОДАЖИ!AD:AD,'ОБОРАЧИВ ПО СЕТИ+ABC'!A:A) -> 613129.14 | C24: =B24/$B$15 -> 0.022756627 | D24: =SUMIFS(ОСТАТКИ!AE:AE,ОСТАТКИ!Q:Q,'ОБОРАЧИВ ПО СЕТИ+ABC'!A:A) -> 3267457.9 | E24: =D24/$D$15 -> 0.011582998 | F24: =IFERROR(D24/B24*30.5,0) -> 162.53911 | G24: дн. | I24: =SUMIFS(ПРОДАЖИ!$AB:$AB,ПРОДАЖИ!$AD:$AD,'ОБОРАЧИВ ПО СЕТИ+ABC'!$A:$A,ПРОДАЖИ!$AE:$AE,'ОБОРАЧИВ ПО СЕТИ+ABC'!I$1) -> 0 | J24: =SUMIFS(ОСТАТКИ!$AE:$AE,ОСТАТКИ!$Q:$Q,'ОБОРАЧИВ ПО СЕТИ+ABC'!$A:$A,ОСТАТКИ!$S:$S,'ОБОРАЧИВ ПО СЕТИ+ABC'!I$1) -> 0 | K24: =J24/(J24+N24+R24) -> 0 | L24: =IFERROR(J24/I24*30.5,0) -> 0 | M24: =SUMIFS(ПРОДАЖИ!$AB:$AB,ПРОДАЖИ!$AD:$AD,'ОБОРАЧИВ ПО СЕТИ+ABC'!$A:$A,ПРОДАЖИ!$AE:$AE,'ОБОРАЧИВ ПО СЕТИ+ABC'!M$1) -> 0 | N24: =SUMIFS(ОСТАТКИ!$AE:$AE,ОСТАТКИ!$Q:$Q,'ОБОРАЧИВ ПО СЕТИ+ABC'!$A:$A,ОСТАТКИ!$S:$S,'ОБОРАЧИВ ПО СЕТИ+ABC'!M$1) -> 0 | O24: =N24/(J24+N24+R24) -> 0 | P24: =IFERROR(N24/M24*30.5,0) -> 0 | Q24: =SUMIFS(ПРОДАЖИ!$AB:$AB,ПРОДАЖИ!$AD:$AD,'ОБОРАЧИВ ПО СЕТИ+ABC'!$A:$A,ПРОДАЖИ!$AE:$AE,'ОБОРАЧИВ ПО СЕТИ+ABC'!Q$1) -> 613129.14 | R24: =SUMIFS(ОСТАТКИ!$AE:$AE,ОСТАТКИ!$Q:$Q,'ОБОРАЧИВ ПО СЕТИ+ABC'!$A:$A,ОСТАТКИ!$S:$S,'ОБОРАЧИВ ПО СЕТИ+ABC'!Q$1) -> 3267457.9 | S24: =R24/(J24+N24+R24) -> 1 | T24: =IFERROR(R24/Q24*30.5,0) -> 162.53911
A25: Мойки со стеклянной поверхностью | B25: =SUMIFS(ПРОДАЖИ!AB:AB,ПРОДАЖИ!AD:AD,'ОБОРАЧИВ ПО СЕТИ+ABC'!A:A) -> 20016.667 | C25: =B25/$B$15 -> 0.00074292964 | D25: =SUMIFS(ОСТАТКИ!AE:AE,ОСТАТКИ!Q:Q,'ОБОРАЧИВ ПО СЕТИ+ABC'!A:A) -> 809050 | E25: =D25/$D$15 -> 0.0028680475 | F25: =IFERROR(D25/B25*30.5,0) -> 1232.7739 | G25: дн. | I25: =SUMIFS(ПРОДАЖИ!$AB:$AB,ПРОДАЖИ!$AD:$AD,'ОБОРАЧИВ ПО СЕТИ+ABC'!$A:$A,ПРОДАЖИ!$AE:$AE,'ОБОРАЧИВ ПО СЕТИ+ABC'!I$1) -> 0 | J25: =SUMIFS(ОСТАТКИ!$AE:$AE,ОСТАТКИ!$Q:$Q,'ОБОРАЧИВ ПО СЕТИ+ABC'!$A:$A,ОСТАТКИ!$S:$S,'ОБОРАЧИВ ПО СЕТИ+ABC'!I$1) -> 0 | K25: =J25/(J25+N25+R25) -> 0 | L25: =IFERROR(J25/I25*30.5,0) -> 0 | M25: =SUMIFS(ПРОДАЖИ!$AB:$AB,ПРОДАЖИ!$AD:$AD,'ОБОРАЧИВ ПО СЕТИ+ABC'!$A:$A,ПРОДАЖИ!$AE:$AE,'ОБОРАЧИВ ПО СЕТИ+ABC'!M$1) -> 0 | N25: =SUMIFS(ОСТАТКИ!$AE:$AE,ОСТАТКИ!$Q:$Q,'ОБОРАЧИВ ПО СЕТИ+ABC'!$A:$A,ОСТАТКИ!$S:$S,'ОБОРАЧИВ ПО СЕТИ+ABC'!M$1) -> 0 | O25: =N25/(J25+N25+R25) -> 0 | P25: =IFERROR(N25/M25*30.5,0) -> 0 | Q25: =SUMIFS(ПРОДАЖИ!$AB:$AB,ПРОДАЖИ!$AD:$AD,'ОБОРАЧИВ ПО СЕТИ+ABC'!$A:$A,ПРОДАЖИ!$AE:$AE,'ОБОРАЧИВ ПО СЕТИ+ABC'!Q$1) -> 20016.667 | R25: =SUMIFS(ОСТАТКИ!$AE:$AE,ОСТАТКИ!$Q:$Q,'ОБОРАЧИВ ПО СЕТИ+ABC'!$A:$A,ОСТАТКИ!$S:$S,'ОБОРАЧИВ ПО СЕТИ+ABC'!Q$1) -> 809050 | S25: =R25/(J25+N25+R25) -> 1 | T25: =IFERROR(R25/Q25*30.5,0) -> 1232.7739
A26: Мойки со смесителями водопад | B26: =SUMIFS(ПРОДАЖИ!AB:AB,ПРОДАЖИ!AD:AD,'ОБОРАЧИВ ПО СЕТИ+ABC'!A:A) -> 10539.167 | C26: =B26/$B$15 -> 0.00039116699 | D26: =SUMIFS(ОСТАТКИ!AE:AE,ОСТАТКИ!Q:Q,'ОБОРАЧИВ ПО СЕТИ+ABC'!A:A) -> 257910 | E26: =D26/$D$15 -> 0.00091427989 | F26: =IFERROR(D26/B26*30.5,0) -> 746.38302 | G26: дн. | I26: =SUMIFS(ПРОДАЖИ!$AB:$AB,ПРОДАЖИ!$AD:$AD,'ОБОРАЧИВ ПО СЕТИ+ABC'!$A:$A,ПРОДАЖИ!$AE:$AE,'ОБОРАЧИВ ПО СЕТИ+ABC'!I$1) -> 0 | J26: =SUMIFS(ОСТАТКИ!$AE:$AE,ОСТАТКИ!$Q:$Q,'ОБОРАЧИВ ПО СЕТИ+ABC'!$A:$A,ОСТАТКИ!$S:$S,'ОБОРАЧИВ ПО СЕТИ+ABC'!I$1) -> 0 | K26: =J26/(J26+N26+R26) -> 0 | L26: =IFERROR(J26/I26*30.5,0) -> 0 | M26: =SUMIFS(ПРОДАЖИ!$AB:$AB,ПРОДАЖИ!$AD:$AD,'ОБОРАЧИВ ПО СЕТИ+ABC'!$A:$A,ПРОДАЖИ!$AE:$AE,'ОБОРАЧИВ ПО СЕТИ+ABC'!M$1) -> 0 | N26: =SUMIFS(ОСТАТКИ!$AE:$AE,ОСТАТКИ!$Q:$Q,'ОБОРАЧИВ ПО СЕТИ+ABC'!$A:$A,ОСТАТКИ!$S:$S,'ОБОРАЧИВ ПО СЕТИ+ABC'!M$1) -> 0 | O26: =N26/(J26+N26+R26) -> 0 | P26: =IFERROR(N26/M26*30.5,0) -> 0 | Q26: =SUMIFS(ПРОДАЖИ!$AB:$AB,ПРОДАЖИ!$AD:$AD,'ОБОРАЧИВ ПО СЕТИ+ABC'!$A:$A,ПРОДАЖИ!$AE:$AE,'ОБОРАЧИВ ПО СЕТИ+ABC'!Q$1) -> 10539.167 | R26: =SUMIFS(ОСТАТКИ!$AE:$AE,ОСТАТКИ!$Q:$Q,'ОБОРАЧИВ ПО СЕТИ+ABC'!$A:$A,ОСТАТКИ!$S:$S,'ОБОРАЧИВ ПО СЕТИ+ABC'!Q$1) -> 257910 | S26: =R26/(J26+N26+R26) -> 1 | T26: =IFERROR(R26/Q26*30.5,0) -> 746.38302
A27: Смесители для кухни | B27: =SUMIFS(ПРОДАЖИ!AB:AB,ПРОДАЖИ!AD:AD,'ОБОРАЧИВ ПО СЕТИ+ABC'!A:A) -> 146438.96 | C27: =B27/$B$15 -> 0.0054351628 | D27: =SUMIFS(ОСТАТКИ!AE:AE,ОСТАТКИ!Q:Q,'ОБОРАЧИВ ПО СЕТИ+ABC'!A:A) -> 3595411.3 | E27: =D27/$D$15 -> 0.012745579 | F27: =IFERROR(D27/B27*30.5,0) -> 748.84475 | G27: дн. | I27: =SUMIFS(ПРОДАЖИ!$AB:$AB,ПРОДАЖИ!$AD:$AD,'ОБОРАЧИВ ПО СЕТИ+ABC'!$A:$A,ПРОДАЖИ!$AE:$AE,'ОБОРАЧИВ ПО СЕТИ+ABC'!I$1) -> 0 | J27: =SUMIFS(ОСТАТКИ!$AE:$AE,ОСТАТКИ!$Q:$Q,'ОБОРАЧИВ ПО СЕТИ+ABC'!$A:$A,ОСТАТКИ!$S:$S,'ОБОРАЧИВ ПО СЕТИ+ABC'!I$1) -> 0 | K27: =J27/(J27+N27+R27) -> 0 | L27: =IFERROR(J27/I27*30.5,0) -> 0 | M27: =SUMIFS(ПРОДАЖИ!$AB:$AB,ПРОДАЖИ!$AD:$AD,'ОБОРАЧИВ ПО СЕТИ+ABC'!$A:$A,ПРОДАЖИ!$AE:$AE,'ОБОРАЧИВ ПО СЕТИ+ABC'!M$1) -> 0 | N27: =SUMIFS(ОСТАТКИ!$AE:$AE,ОСТАТКИ!$Q:$Q,'ОБОРАЧИВ ПО СЕТИ+ABC'!$A:$A,ОСТАТКИ!$S:$S,'ОБОРАЧИВ ПО СЕТИ+ABC'!M$1) -> 0 | O27: =N27/(J27+N27+R27) -> 0 | P27: =IFERROR(N27/M27*30.5,0) -> 0 | Q27: =SUMIFS(ПРОДАЖИ!$AB:$AB,ПРОДАЖИ!$AD:$AD,'ОБОРАЧИВ ПО СЕТИ+ABC'!$A:$A,ПРОДАЖИ!$AE:$AE,'ОБОРАЧИВ ПО СЕТИ+ABC'!Q$1) -> 146438.96 | R27: =SUMIFS(ОСТАТКИ!$AE:$AE,ОСТАТКИ!$Q:$Q,'ОБОРАЧИВ ПО СЕТИ+ABC'!$A:$A,ОСТАТКИ!$S:$S,'ОБОРАЧИВ ПО СЕТИ+ABC'!Q$1) -> 3595411.3 | S27: =R27/(J27+N27+R27) -> 1 | T27: =IFERROR(R27/Q27*30.5,0) -> 748.84475
... A31: Вентиляционные решетки | B31: =SUMIFS(ПРОДАЖИ!AB:AB,ПРОДАЖИ!AD:AD,'ОБОРАЧИВ ПО СЕТИ+ABC'!A:A) -> 155945.79 | C31: =B31/$B$15 -> 0.005788014 | D31: =SUMIFS(ОСТАТКИ!AE:AE,ОСТАТКИ!Q:Q,'ОБОРАЧИВ ПО СЕТИ+ABC'!A:A) -> 1407374.3 | E31: =D31/$D$15 -> 0.0049890814 | F31: =IFERROR(D31/B31*30.5,0) -> 275.25537 | G31: дн. | I31: =SUMIFS(ПРОДАЖИ!$AB:$AB,ПРОДАЖИ!$AD:$AD,'ОБОРАЧИВ ПО СЕТИ+ABC'!$A:$A,ПРОДАЖИ!$AE:$AE,'ОБОРАЧИВ ПО СЕТИ+ABC'!I$1) -> 0 | J31: =SUMIFS(ОСТАТКИ!$AE:$AE,ОСТАТКИ!$Q:$Q,'ОБОРАЧИВ ПО СЕТИ+ABC'!$A:$A,ОСТАТКИ!$S:$S,'ОБОРАЧИВ ПО СЕТИ+ABC'!I$1) -> 0 | K31: =J31/(J31+N31+R31) -> 0 | L31: =IFERROR(J31/I31*30.5,0) -> 0 | M31: =SUMIFS(ПРОДАЖИ!$AB:$AB,ПРОДАЖИ!$AD:$AD,'ОБОРАЧИВ ПО СЕТИ+ABC'!$A:$A,ПРОДАЖИ!$AE:$AE,'ОБОРАЧИВ ПО СЕТИ+ABC'!M$1) -> 0 | N31: =SUMIFS(ОСТАТКИ!$AE:$AE,ОСТАТКИ!$Q:$Q,'ОБОРАЧИВ ПО СЕТИ+ABC'!$A:$A,ОСТАТКИ!$S:$S,'ОБОРАЧИВ ПО СЕТИ+ABC'!M$1) -> 0 | O31: =N31/(J31+N31+R31) -> 0 | P31: =IFERROR(N31/M31*30.5,0) -> 0 | Q31: =SUMIFS(ПРОДАЖИ!$AB:$AB,ПРОДАЖИ!$AD:$AD,'ОБОРАЧИВ ПО СЕТИ+ABC'!$A:$A,ПРОДАЖИ!$AE:$AE,'ОБОРАЧИВ ПО СЕТИ+ABC'!Q$1) -> 155945.79 | R31: =SUMIFS(ОСТАТКИ!$AE:$AE,ОСТАТКИ!$Q:$Q,'ОБОРАЧИВ ПО СЕТИ+ABC'!$A:$A,ОСТАТКИ!$S:$S,'ОБОРАЧИВ ПО СЕТИ+ABC'!Q$1) -> 1407374.3 | S31: =R31/(J31+N31+R31) -> 1 | T31: =IFERROR(R31/Q31*30.5,0) -> 275.25537
A32: Аксессуары для столешниц | B32: =SUM(B33:B39) -> 14793710 | C32: =B32/$B$139 -> 0.11549859 | D32: =SUM(D33:D39) -> 2.4210882e+08 | E32: =D32/$D$139 -> 0.14009339 | F32: =IFERROR(D32/B32*30.5,0) -> 499.15261 | G32: дн. | I32: =SUM(I33:I39) -> 7695856.9 | J32: =SUM(J33:J39) -> 70843081 | K32: =J32/(J32+N32+R32) -> 0.29260843 | L32: =IFERROR(J32/I32*30.5,0) -> 280.76327 | M32: =SUM(M33:M39) -> 5860619 | N32: =SUM(N33:N39) -> 97841694 | O32: =N32/(J32+N32+R32) -> 0.4041228 | P32: =IFERROR(N32/M32*30.5,0) -> 509.19053 | Q32: =SUM(Q33:Q39) -> 1237234.2 | R32: =SUM(R33:R39) -> 73424044 | S32: =R32/(J32+N32+R32) -> 0.30326877 | T32: =IFERROR(R32/Q32*30.5,0) -> 1810.0319
A33: Плинтус пластиковый 4,2м | B33: =SUMIFS(ПРОДАЖИ!AB:AB,ПРОДАЖИ!AD:AD,'ОБОРАЧИВ ПО СЕТИ+ABC'!A:A) -> 4965729.1 | C33: =B33/$B$32 -> 0.33566489 | D33: =SUMIFS(ОСТАТКИ!AE:AE,ОСТАТКИ!Q:Q,'ОБОРАЧИВ ПО СЕТИ+ABC'!A:A) -> 89221772 | E33: =D33/$D$32 -> 0.3685193 | F33: =IFERROR(D33/B33*30.5,0) -> 548.00897 | G33: дн. | I33: =SUMIFS(ПРОДАЖИ!$AB:$AB,ПРОДАЖИ!$AD:$AD,'ОБОРАЧИВ ПО СЕТИ+ABC'!$A:$A,ПРОДАЖИ!$AE:$AE,'ОБОРАЧИВ ПО СЕТИ+ABC'!I$1) -> 1922468.5 | J33: =SUMIFS(ОСТАТКИ!$AE:$AE,ОСТАТКИ!$Q:$Q,'ОБОРАЧИВ ПО СЕТИ+ABC'!$A:$A,ОСТАТКИ!$S:$S,'ОБОРАЧИВ ПО СЕТИ+ABC'!I$1) -> 19150952 | K33: =J33/(J33+N33+R33) -> 0.21464438 | L33: =IFERROR(J33/I33*30.5,0) -> 303.83023 | M33: =SUMIFS(ПРОДАЖИ!$AB:$AB,ПРОДАЖИ!$AD:$AD,'ОБОРАЧИВ ПО СЕТИ+ABC'!$A:$A,ПРОДАЖИ!$AE:$AE,'ОБОРАЧИВ ПО СЕТИ+ABC'!M$1) -> 2560409.6 | N33: =SUMIFS(ОСТАТКИ!$AE:$AE,ОСТАТКИ!$Q:$Q,'ОБОРАЧИВ ПО СЕТИ+ABC'!$A:$A,ОСТАТКИ!$S:$S,'ОБОРАЧИВ ПО СЕТИ+ABC'!M$1) -> 36079329 | O33: =N33/(J33+N33+R33) -> 0.40437809 | P33: =IFERROR(N33/M33*30.5,0) -> 429.78263 | Q33: =SUMIFS(ПРОДАЖИ!$AB:$AB,ПРОДАЖИ!$AD:$AD,'ОБОРАЧИВ ПО СЕТИ+ABC'!$A:$A,ПРОДАЖИ!$AE:$AE,'ОБОРАЧИВ ПО СЕТИ+ABC'!Q$1) -> 482851.02 | R33: =SUMIFS(ОСТАТКИ!$AE:$AE,ОСТАТКИ!$Q:$Q,'ОБОРАЧИВ ПО СЕТИ+ABC'!$A:$A,ОСТАТКИ!$S:$S,'ОБОРАЧИВ ПО СЕТИ+ABC'!Q$1) -> 33991491 | S33: =R33/(J33+N33+R33) -> 0.38097753 | T33: =IFERROR(R33/Q33*30.5,0) -> 2147.1229
A34: Плинтус алюминиевый | B34: =SUMIFS(ПРОДАЖИ!AB:AB,ПРОДАЖИ!AD:AD,'ОБОРАЧИВ ПО СЕТИ+ABC'!A:A) -> 4092646.5 | C34: =B34/$B$32 -> 0.27664775 | D34: =SUMIFS(ОСТАТКИ!AE:AE,ОСТАТКИ!Q:Q,'ОБОРАЧИВ ПО СЕТИ+ABC'!A:A) -> 21802479 | E34: =D34/$D$32 -> 0.090052395 | F34: =IFERROR(D34/B34*30.5,0) -> 162.48059 | G34: дн. | I34: =SUMIFS(ПРОДАЖИ!$AB:$AB,ПРОДАЖИ!$AD:$AD,'ОБОРАЧИВ ПО СЕТИ+ABC'!$A:$A,ПРОДАЖИ!$AE:$AE,'ОБОРАЧИВ ПО СЕТИ+ABC'!I$1) -> 3459494.7 | J34: =SUMIFS(ОСТАТКИ!$AE:$AE,ОСТАТКИ!$Q:$Q,'ОБОРАЧИВ ПО СЕТИ+ABC'!$A:$A,ОСТАТКИ!$S:$S,'ОБОРАЧИВ ПО СЕТИ+ABC'!I$1) -> 18113642 | K34: =J34/(J34+N34+R34) -> 0.83080653 | L34: =IFERROR(J34/I34*30.5,0) -> 159.6956 | M34: =SUMIFS(ПРОДАЖИ!$AB:$AB,ПРОДАЖИ!$AD:$AD,'ОБОРАЧИВ ПО СЕТИ+ABC'!$A:$A,ПРОДАЖИ!$AE:$AE,'ОБОРАЧИВ ПО СЕТИ+ABC'!M$1) -> 568867.32 | N34: =SUMIFS(ОСТАТКИ!$AE:$AE,ОСТАТКИ!$Q:$Q,'ОБОРАЧИВ ПО СЕТИ+ABC'!$A:$A,ОСТАТКИ!$S:$S,'ОБОРАЧИВ ПО СЕТИ+ABC'!M$1) -> 3425586.1 | O34: =N34/(J34+N34+R34) -> 0.15711911 | P34: =IFERROR(N34/M34*30.5,0) -> 183.66388 | Q34: =SUMIFS(ПРОДАЖИ!$AB:$AB,ПРОДАЖИ!$AD:$AD,'ОБОРАЧИВ ПО СЕТИ+ABC'!$A:$A,ПРОДАЖИ!$AE:$AE,'ОБОРАЧИВ ПО СЕТИ+ABC'!Q$1) -> 64284.502 | R34: =SUMIFS(ОСТАТКИ!$AE:$AE,ОСТАТКИ!$Q:$Q,'ОБОРАЧИВ ПО СЕТИ+ABC'!$A:$A,ОСТАТКИ!$S:$S,'ОБОРАЧИВ ПО СЕТИ+ABC'!Q$1) -> 263250.99 | S34: =R34/(J34+N34+R34) -> 0.01207436 | T34: =IFERROR(R34/Q34*30.5,0) -> 124.90032
A35: Плинтус пластиковый 3м | B35: =SUMIFS(ПРОДАЖИ!AB:AB,ПРОДАЖИ!AD:AD,'ОБОРАЧИВ ПО СЕТИ+ABC'!A:A) -> 3256960.8 | C35: =B35/$B$32 -> 0.22015849 | D35: =SUMIFS(ОСТАТКИ!AE:AE,ОСТАТКИ!Q:Q,'ОБОРАЧИВ ПО СЕТИ+ABC'!A:A) -> 58139559 | E35: =D35/$D$32 -> 0.24013813 | F35: =IFERROR(D35/B35*30.5,0) -> 544.4513 | G35: дн. | I35: =SUMIFS(ПРОДАЖИ!$AB:$AB,ПРОДАЖИ!$AD:$AD,'ОБОРАЧИВ ПО СЕТИ+ABC'!$A:$A,ПРОДАЖИ!$AE:$AE,'ОБОРАЧИВ ПО СЕТИ+ABC'!I$1) -> 708178.1 | J35: =SUMIFS(ОСТАТКИ!$AE:$AE,ОСТАТКИ!$Q:$Q,'ОБОРАЧИВ ПО СЕТИ+ABC'!$A:$A,ОСТАТКИ!$S:$S,'ОБОРАЧИВ ПО СЕТИ+ABC'!I$1) -> 7349278.9 | K35: =J35/(J35+N35+R35) -> 0.12640754 | L35: =IFERROR(J35/I35*30.5,0) -> 316.52067 | M35: =SUMIFS(ПРОДАЖИ!$AB:$AB,ПРОДАЖИ!$AD:$AD,'ОБОРАЧИВ ПО СЕТИ+ABC'!$A:$A,ПРОДАЖИ!$AE:$AE,'ОБОРАЧИВ ПО СЕТИ+ABC'!M$1) -> 2070612.4 | N35: =SUMIFS(ОСТАТКИ!$AE:$AE,ОСТАТКИ!$Q:$Q,'ОБОРАЧИВ ПО СЕТИ+ABC'!$A:$A,ОСТАТКИ!$S:$S,'ОБОРАЧИВ ПО СЕТИ+ABC'!M$1) -> 33939162 | O35: =N35/(J35+N35+R35) -> 0.58375335 | P35: =IFERROR(N35/M35*30.5,0) -> 499.92188 | Q35: =SUMIFS(ПРОДАЖИ!$AB:$AB,ПРОДАЖИ!$AD:$AD,'ОБОРАЧИВ ПО СЕТИ+ABC'!$A:$A,ПРОДАЖИ!$AE:$AE,'ОБОРАЧИВ ПО СЕТИ+ABC'!Q$1) -> 478170.3 | R35: =SUMIFS(ОСТАТКИ!$AE:$AE,ОСТАТКИ!$Q:$Q,'ОБОРАЧИВ ПО СЕТИ+ABC'!$A:$A,ОСТАТКИ!$S:$S,'ОБОРАЧИВ ПО СЕТИ+ABC'!Q$1) -> 16851118 | S35: =R35/(J35+N35+R35) -> 0.2898391 | T35: =IFERROR(R35/Q35*30.5,0) -> 1074.8453
A36: Комплектующие для плинтуса к столешнице | B36: =SUMIFS(ПРОДАЖИ!AB:AB,ПРОДАЖИ!AD:AD,'ОБОРАЧИВ ПО СЕТИ+ABC'!A:A) -> 1307804.3 | C36: =B36/$B$32 -> 0.088402729 | D36: =SUMIFS(ОСТАТКИ!AE:AE,ОСТАТКИ!Q:Q,'ОБОРАЧИВ ПО СЕТИ+ABC'!A:A) -> 40542605 | E36: =D36/$D$32 -> 0.16745613 | F36: =IFERROR(D36/B36*30.5,0) -> 945.51563 | G36: дн. | I36: =SUMIFS(ПРОДАЖИ!$AB:$AB,ПРОДАЖИ!$AD:$AD,'ОБОРАЧИВ ПО СЕТИ+ABC'!$A:$A,ПРОДАЖИ!$AE:$AE,'ОБОРАЧИВ ПО СЕТИ+ABC'!I$1) -> 1047043.1 | J36: =SUMIFS(ОСТАТКИ!$AE:$AE,ОСТАТКИ!$Q:$Q,'ОБОРАЧИВ ПО СЕТИ+ABC'!$A:$A,ОСТАТКИ!$S:$S,'ОБОРАЧИВ ПО СЕТИ+ABC'!I$1) -> 16125574 | K36: =J36/(J36+N36+R36) -> 0.39774391 | L36: =IFERROR(J36/I36*30.5,0) -> 469.73237 | M36: =SUMIFS(ПРОДАЖИ!$AB:$AB,ПРОДАЖИ!$AD:$AD,'ОБОРАЧИВ ПО СЕТИ+ABC'!$A:$A,ПРОДАЖИ!$AE:$AE,'ОБОРАЧИВ ПО СЕТИ+ABC'!M$1) -> 232582.23 | N36: =SUMIFS(ОСТАТКИ!$AE:$AE,ОСТАТКИ!$Q:$Q,'ОБОРАЧИВ ПО СЕТИ+ABC'!$A:$A,ОСТАТКИ!$S:$S,'ОБОРАЧИВ ПО СЕТИ+ABC'!M$1) -> 16943418 | O36: =N36/(J36+N36+R36) -> 0.41791636 | P36: =IFERROR(N36/M36*30.5,0) -> 2221.8991 | Q36: =SUMIFS(ПРОДАЖИ!$AB:$AB,ПРОДАЖИ!$AD:$AD,'ОБОРАЧИВ ПО СЕТИ+ABC'!$A:$A,ПРОДАЖИ!$AE:$AE,'ОБОРАЧИВ ПО СЕТИ+ABC'!Q$1) -> 28179.057 | R36: =SUMIFS(ОСТАТКИ!$AE:$AE,ОСТАТКИ!$Q:$Q,'ОБОРАЧИВ ПО СЕТИ+ABC'!$A:$A,ОСТАТКИ!$S:$S,'ОБОРАЧИВ ПО СЕТИ+ABC'!Q$1) -> 7473612.8 | S36: =R36/(J36+N36+R36) -> 0.18433973 | T36: =IFERROR(R36/Q36*30.5,0) -> 8089.1701
A37: Планки торцевые, соеденительные, угловые для столешницы | B37: =SUMIFS(ПРОДАЖИ!AB:AB,ПРОДАЖИ!AD:AD,'ОБОРАЧИВ ПО СЕТИ+ABC'!A:A) -> 974377.55 | C37: =B37/$B$32 -> 0.065864313 | D37: =SUMIFS(ОСТАТКИ!AE:AE,ОСТАТКИ!Q:Q,'ОБОРАЧИВ ПО СЕТИ+ABC'!A:A) -> 20554969 | E37: =D37/$D$32 -> 0.08489971 | F37: =IFERROR(D37/B37*30.5,0) -> 643.41234 | G37: дн. | I37: =SUMIFS(ПРОДАЖИ!$AB:$AB,ПРОДАЖИ!$AD:$AD,'ОБОРАЧИВ ПО СЕТИ+ABC'!$A:$A,ПРОДАЖИ!$AE:$AE,'ОБОРАЧИВ ПО СЕТИ+ABC'!I$1) -> 558672.55 | J37: =SUMIFS(ОСТАТКИ!$AE:$AE,ОСТАТКИ!$Q:$Q,'ОБОРАЧИВ ПО СЕТИ+ABC'!$A:$A,ОСТАТКИ!$S:$S,'ОБОРАЧИВ ПО СЕТИ+ABC'!I$1) -> 10103634 | K37: =J37/(J37+N37+R37) -> 0.49154219 | L37: =IFERROR(J37/I37*30.5,0) -> 551.59476 | M37: =SUMIFS(ПРОДАЖИ!$AB:$AB,ПРОДАЖИ!$AD:$AD,'ОБОРАЧИВ ПО СЕТИ+ABC'!$A:$A,ПРОДАЖИ!$AE:$AE,'ОБОРАЧИВ ПО СЕТИ+ABC'!M$1) -> 352806.95 | N37: =SUMIFS(ОСТАТКИ!$AE:$AE,ОСТАТКИ!$Q:$Q,'ОБОРАЧИВ ПО СЕТИ+ABC'!$A:$A,ОСТАТКИ!$S:$S,'ОБОРАЧИВ ПО СЕТИ+ABC'!M$1) -> 6221778.2 | O37: =N37/(J37+N37+R37) -> 0.30268974 | P37: =IFERROR(N37/M37*30.5,0) -> 537.86989 | Q37: =SUMIFS(ПРОДАЖИ!$AB:$AB,ПРОДАЖИ!$AD:$AD,'ОБОРАЧИВ ПО СЕТИ+ABC'!$A:$A,ПРОДАЖИ!$AE:$AE,'ОБОРАЧИВ ПО СЕТИ+ABC'!Q$1) -> 62898.055 | R37: =SUMIFS(ОСТАТКИ!$AE:$AE,ОСТАТКИ!$Q:$Q,'ОБОРАЧИВ ПО СЕТИ+ABC'!$A:$A,ОСТАТКИ!$S:$S,'ОБОРАЧИВ ПО СЕТИ+ABC'!Q$1) -> 4229556.1 | S37: =R37/(J37+N37+R37) -> 0.20576806 | T37: =IFERROR(R37/Q37*30.5,0) -> 2050.961
A38: Профиль уплотнительный | B38: =SUMIFS(ПРОДАЖИ!AB:AB,ПРОДАЖИ!AD:AD,'ОБОРАЧИВ ПО СЕТИ+ABC'!A:A) -> 126829.61 | C38: =B38/$B$32 -> 0.0085732118 | D38: =SUMIFS(ОСТАТКИ!AE:AE,ОСТАТКИ!Q:Q,'ОБОРАЧИВ ПО СЕТИ+ABC'!A:A) -> 9811615.6 | E38: =D38/$D$32 -> 0.040525643 | F38: =IFERROR(D38/B38*30.5,0) -> 2359.4985 | G38: дн. | I38: =SUMIFS(ПРОДАЖИ!$AB:$AB,ПРОДАЖИ!$AD:$AD,'ОБОРАЧИВ ПО СЕТИ+ABC'!$A:$A,ПРОДАЖИ!$AE:$AE,'ОБОРАЧИВ ПО СЕТИ+ABC'!I$1) -> 0 | J38: =SUMIFS(ОСТАТКИ!$AE:$AE,ОСТАТКИ!$Q:$Q,'ОБОРАЧИВ ПО СЕТИ+ABC'!$A:$A,ОСТАТКИ!$S:$S,'ОБОРАЧИВ ПО СЕТИ+ABC'!I$1) -> 0 | K38: =J38/(J38+N38+R38) -> 0 | L38: =IFERROR(J38/I38*30.5,0) -> 0 | M38: =SUMIFS(ПРОДАЖИ!$AB:$AB,ПРОДАЖИ!$AD:$AD,'ОБОРАЧИВ ПО СЕТИ+ABC'!$A:$A,ПРОДАЖИ!$AE:$AE,'ОБОРАЧИВ ПО СЕТИ+ABC'!M$1) -> 75340.486 | N38: =SUMIFS(ОСТАТКИ!$AE:$AE,ОСТАТКИ!$Q:$Q,'ОБОРАЧИВ ПО СЕТИ+ABC'!$A:$A,ОСТАТКИ!$S:$S,'ОБОРАЧИВ ПО СЕТИ+ABC'!M$1) -> 1232419.7 | O38: =N38/(J38+N38+R38) -> 0.12560823 | P38: =IFERROR(N38/M38*30.5,0) -> 498.91899 | Q38: =SUMIFS(ПРОДАЖИ!$AB:$AB,ПРОДАЖИ!$AD:$AD,'ОБОРАЧИВ ПО СЕТИ+ABC'!$A:$A,ПРОДАЖИ!$AE:$AE,'ОБОРАЧИВ ПО СЕТИ+ABC'!Q$1) -> 51489.124 | R38: =SUMIFS(ОСТАТКИ!$AE:$AE,ОСТАТКИ!$Q:$Q,'ОБОРАЧИВ ПО СЕТИ+ABC'!$A:$A,ОСТАТКИ!$S:$S,'ОБОРАЧИВ ПО СЕТИ+ABC'!Q$1) -> 8579195.9 | S38: =R38/(J38+N38+R38) -> 0.87439177 | T38: =IFERROR(R38/Q38*30.5,0) -> 5081.9562
A39: Цоколь | B39: =SUMIFS(ПРОДАЖИ!AB:AB,ПРОДАЖИ!AD:AD,'ОБОРАЧИВ ПО СЕТИ+ABC'!A:A) -> 69362.141 | C39: =B39/$B$32 -> 0.0046886238 | D39: =SUMIFS(ОСТАТКИ!AE:AE,ОСТАТКИ!Q:Q,'ОБОРАЧИВ ПО СЕТИ+ABC'!A:A) -> 2035820 | E39: =D39/$D$32 -> 0.0084086981 | F39: =IFERROR(D39/B39*30.5,0) -> 895.19309 | G39: дн. | I39: =SUMIFS(ПРОДАЖИ!$AB:$AB,ПРОДАЖИ!$AD:$AD,'ОБОРАЧИВ ПО СЕТИ+ABC'!$A:$A,ПРОДАЖИ!$AE:$AE,'ОБОРАЧИВ ПО СЕТИ+ABC'!I$1) -> 0 | J39: =SUMIFS(ОСТАТКИ!$AE:$AE,ОСТАТКИ!$Q:$Q,'ОБОРАЧИВ ПО СЕТИ+ABC'!$A:$A,ОСТАТКИ!$S:$S,'ОБОРАЧИВ ПО СЕТИ+ABC'!I$1) -> 0 | K39: =J39/(J39+N39+R39) -> 0 | L39: =IFERROR(J39/I39*30.5,0) -> 0 | M39: =SUMIFS(ПРОДАЖИ!$AB:$AB,ПРОДАЖИ!$AD:$AD,'ОБОРАЧИВ ПО СЕТИ+ABC'!$A:$A,ПРОДАЖИ!$AE:$AE,'ОБОРАЧИВ ПО СЕТИ+ABC'!M$1) -> 0 | N39: =SUMIFS(ОСТАТКИ!$AE:$AE,ОСТАТКИ!$Q:$Q,'ОБОРАЧИВ ПО СЕТИ+ABC'!$A:$A,ОСТАТКИ!$S:$S,'ОБОРАЧИВ ПО СЕТИ+ABC'!M$1) -> 0 | O39: =N39/(J39+N39+R39) -> 0 | P39: =IFERROR(N39/M39*30.5,0) -> 0 | Q39: =SUMIFS(ПРОДАЖИ!$AB:$AB,ПРОДАЖИ!$AD:$AD,'ОБОРАЧИВ ПО СЕТИ+ABC'!$A:$A,ПРОДАЖИ!$AE:$AE,'ОБОРАЧИВ ПО СЕТИ+ABC'!Q$1) -> 69362.141 | R39: =SUMIFS(ОСТАТКИ!$AE:$AE,ОСТАТКИ!$Q:$Q,'ОБОРАЧИВ ПО СЕТИ+ABC'!$A:$A,ОСТАТКИ!$S:$S,'ОБОРАЧИВ ПО СЕТИ+ABC'!Q$1) -> 2035820 | S39: =R39/(J39+N39+R39) -> 1 | T39: =IFERROR(R39/Q39*30.5,0) -> 895.19309
A40: Крепежные системы | B40: =SUM(B41:B59) -> 8207982.5 | C40: =B40/$B$139 -> 0.064081991 | D40: =SUM(D41:D59) -> 1.628772e+08 | E40: =D40/$D$139 -> 0.094246959 | F40: =IFERROR(D40/B40*30.5,0) -> 605.23456 | G40: дн. | I40: =SUM(I41:I59) -> 3417099.3 | J40: =SUM(J41:J59) -> 51228537 | K40: =J40/(J40+N40+R40) -> 0.31452245 | L40: =IFERROR(J40/I40*30.5,0) -> 457.25049 | M40: =SUM(M41:M59) -> 1552451.9 | N40: =SUM(N41:N59) -> 47968511 | O40: =N40/(J40+N40+R40) -> 0.29450721 | P40: =IFERROR(N40/M40*30.5,0) -> 942.40576 | Q40: =SUM(Q41:Q59) -> 3238431.3 | R40: =SUM(R41:R59) -> 63680157 | S40: =R40/(J40+N40+R40) -> 0.39097035 | T40: =IFERROR(R40/Q40*30.5,0) -> 599.74864
A41: Конфирматы шурупы дюбель | B41: =SUMIFS(ПРОДАЖИ!AB:AB,ПРОДАЖИ!AD:AD,'ОБОРАЧИВ ПО СЕТИ+ABC'!A:A) -> 4413743.9 | C41: =B41/$B$40 -> 0.53773797 | D41: =SUMIFS(ОСТАТКИ!AE:AE,ОСТАТКИ!Q:Q,'ОБОРАЧИВ ПО СЕТИ+ABC'!A:A) -> 68050416 | E41: =D41/$D$40 -> 0.41780196 | F41: =IFERROR(D41/B41*30.5,0) -> 470.24425 | G41: дн. | I41: =SUMIFS(ПРОДАЖИ!$AB:$AB,ПРОДАЖИ!$AD:$AD,'ОБОРАЧИВ ПО СЕТИ+ABC'!$A:$A,ПРОДАЖИ!$AE:$AE,'ОБОРАЧИВ ПО СЕТИ+ABC'!I$1) -> 2686163.8 | J41: =SUMIFS(ОСТАТКИ!$AE:$AE,ОСТАТКИ!$Q:$Q,'ОБОРАЧИВ ПО СЕТИ+ABC'!$A:$A,ОСТАТКИ!$S:$S,'ОБОРАЧИВ ПО СЕТИ+ABC'!I$1) -> 48287650 | K41: =J41/(J41+N41+R41) -> 0.70958641 | L41: =IFERROR(J41/I41*30.5,0) -> 548.28127 | M41: =SUMIFS(ПРОДАЖИ!$AB:$AB,ПРОДАЖИ!$AD:$AD,'ОБОРАЧИВ ПО СЕТИ+ABC'!$A:$A,ПРОДАЖИ!$AE:$AE,'ОБОРАЧИВ ПО СЕТИ+ABC'!M$1) -> 221806.21 | N41: =SUMIFS(ОСТАТКИ!$AE:$AE,ОСТАТКИ!$Q:$Q,'ОБОРАЧИВ ПО СЕТИ+ABC'!$A:$A,ОСТАТКИ!$S:$S,'ОБОРАЧИВ ПО СЕТИ+ABC'!M$1) -> 12098037 | O41: =N41/(J41+N41+R41) -> 0.17778049 | P41: =IFERROR(N41/M41*30.5,0) -> 1663.5698 | Q41: =SUMIFS(ПРОДАЖИ!$AB:$AB,ПРОДАЖИ!$AD:$AD,'ОБОРАЧИВ ПО СЕТИ+ABC'!$A:$A,ПРОДАЖИ!$AE:$AE,'ОБОРАЧИВ ПО СЕТИ+ABC'!Q$1) -> 1505773.8 | R41: =SUMIFS(ОСТАТКИ!$AE:$AE,ОСТАТКИ!$Q:$Q,'ОБОРАЧИВ ПО СЕТИ+ABC'!$A:$A,ОСТАТКИ!$S:$S,'ОБОРАЧИВ ПО СЕТИ+ABC'!Q$1) -> 7664729.1 | S41: =R41/(J41+N41+R41) -> 0.1126331 | T41: =IFERROR(R41/Q41*30.5,0) -> 155.25189
A42: Держатели угловые | B42: =SUMIFS(ПРОДАЖИ!AB:AB,ПРОДАЖИ!AD:AD,'ОБОРАЧИВ ПО СЕТИ+ABC'!A:A) -> 1149897.6 | C42: =B42/$B$40 -> 0.14009503 | D42: =SUMIFS(ОСТАТКИ!AE:AE,ОСТАТКИ!Q:Q,'ОБОРАЧИВ ПО СЕТИ+ABC'!A:A) -> 23231589 | E42: =D42/$D$40 -> 0.14263254 | F42: =IFERROR(D42/B42*30.5,0) -> 616.19702 | G42: дн. | I42: =SUMIFS(ПРОДАЖИ!$AB:$AB,ПРОДАЖИ!$AD:$AD,'ОБОРАЧИВ ПО СЕТИ+ABC'!$A:$A,ПРОДАЖИ!$AE:$AE,'ОБОРАЧИВ ПО СЕТИ+ABC'!I$1) -> 352893.64 | J42: =SUMIFS(ОСТАТКИ!$AE:$AE,ОСТАТКИ!$Q:$Q,'ОБОРАЧИВ ПО СЕТИ+ABC'!$A:$A,ОСТАТКИ!$S:$S,'ОБОРАЧИВ ПО СЕТИ+ABC'!I$1) -> 1104122.2 | K42: =J42/(J42+N42+R42) -> 0.04752676 | L42: =IFERROR(J42/I42*30.5,0) -> 95.42741 | M42: =SUMIFS(ПРОДАЖИ!$AB:$AB,ПРОДАЖИ!$AD:$AD,'ОБОРАЧИВ ПО СЕТИ+ABC'!$A:$A,ПРОДАЖИ!$AE:$AE,'ОБОРАЧИВ ПО СЕТИ+ABC'!M$1) -> 558918.19 | N42: =SUMIFS(ОСТАТКИ!$AE:$AE,ОСТАТКИ!$Q:$Q,'ОБОРАЧИВ ПО СЕТИ+ABC'!$A:$A,ОСТАТКИ!$S:$S,'ОБОРАЧИВ ПО СЕТИ+ABC'!M$1) -> 10587220 | O42: =N42/(J42+N42+R42) -> 0.45572517 | P42: =IFERROR(N42/M42*30.5,0) -> 577.74145 | Q42: =SUMIFS(ПРОДАЖИ!$AB:$AB,ПРОДАЖИ!$AD:$AD,'ОБОРАЧИВ ПО СЕТИ+ABC'!$A:$A,ПРОДАЖИ!$AE:$AE,'ОБОРАЧИВ ПО СЕТИ+ABC'!Q$1) -> 238085.74 | R42: =SUMIFS(ОСТАТКИ!$AE:$AE,ОСТАТКИ!$Q:$Q,'ОБОРАЧИВ ПО СЕТИ+ABC'!$A:$A,ОСТАТКИ!$S:$S,'ОБОРАЧИВ ПО СЕТИ+ABC'!Q$1) -> 11540247 | S42: =R42/(J42+N42+R42) -> 0.49674807 | T42: =IFERROR(R42/Q42*30.5,0) -> 1478.3646
A43: Полкодержатели | B43: =SUMIFS(ПРОДАЖИ!AB:AB,ПРОДАЖИ!AD:AD,'ОБОРАЧИВ ПО СЕТИ+ABC'!A:A) -> 592917.68 | C43: =B43/$B$40 -> 0.072236713 | D43: =SUMIFS(ОСТАТКИ!AE:AE,ОСТАТКИ!Q:Q,'ОБОРАЧИВ ПО СЕТИ+ABC'!A:A) -> 4596422.2 | E43: =D43/$D$40 -> 0.028220169 | F43: =IFERROR(D43/B43*30.5,0) -> 236.4424 | G43: дн. | I43: =SUMIFS(ПРОДАЖИ!$AB:$AB,ПРОДАЖИ!$AD:$AD,'ОБОРАЧИВ ПО СЕТИ+ABC'!$A:$A,ПРОДАЖИ!$AE:$AE,'ОБОРАЧИВ ПО СЕТИ+ABC'!I$1) -> 341648.81 | J43: =SUMIFS(ОСТАТКИ!$AE:$AE,ОСТАТКИ!$Q:$Q,'ОБОРАЧИВ ПО СЕТИ+ABC'!$A:$A,ОСТАТКИ!$S:$S,'ОБОРАЧИВ ПО СЕТИ+ABC'!I$1) -> 1669023.9 | K43: =J43/(J43+N43+R43) -> 0.36311371 | L43: =IFERROR(J43/I43*30.5,0) -> 148.9987 | M43: =SUMIFS(ПРОДАЖИ!$AB:$AB,ПРОДАЖИ!$AD:$AD,'ОБОРАЧИВ ПО СЕТИ+ABC'!$A:$A,ПРОДАЖИ!$AE:$AE,'ОБОРАЧИВ ПО СЕТИ+ABC'!M$1) -> 37918.034 | N43: =SUMIFS(ОСТАТКИ!$AE:$AE,ОСТАТКИ!$Q:$Q,'ОБОРАЧИВ ПО СЕТИ+ABC'!$A:$A,ОСТАТКИ!$S:$S,'ОБОРАЧИВ ПО СЕТИ+ABC'!M$1) -> 624160.43 | O43: =N43/(J43+N43+R43) -> 0.13579267 | P43: =IFERROR(N43/M43*30.5,0) -> 502.0538 | Q43: =SUMIFS(ПРОДАЖИ!$AB:$AB,ПРОДАЖИ!$AD:$AD,'ОБОРАЧИВ ПО СЕТИ+ABC'!$A:$A,ПРОДАЖИ!$AE:$AE,'ОБОРАЧИВ ПО СЕТИ+ABC'!Q$1) -> 213350.83 | R43: =SUMIFS(ОСТАТКИ!$AE:$AE,ОСТАТКИ!$Q:$Q,'ОБОРАЧИВ ПО СЕТИ+ABC'!$A:$A,ОСТАТКИ!$S:$S,'ОБОРАЧИВ ПО СЕТИ+ABC'!Q$1) -> 2303237.9 | S43: =R43/(J43+N43+R43) -> 0.50109362 | T43: =IFERROR(R43/Q43*30.5,0) -> 329.26403
A44: Шкант | B44: =SUMIFS(ПРОДАЖИ!AB:AB,ПРОДАЖИ!AD:AD,'ОБОРАЧИВ ПО СЕТИ+ABC'!A:A) -> 36493.631 | C44: =B44/$B$40 -> 0.0044461146 | D44: =SUMIFS(ОСТАТКИ!AE:AE,ОСТАТКИ!Q:Q,'ОБОРАЧИВ ПО СЕТИ+ABC'!A:A) -> 168475.2 | E44: =D44/$D$40 -> 0.0010343694 | F44: =IFERROR(D44/B44*30.5,0) -> 140.80522 | G44: дн. | I44: =SUMIFS(ПРОДАЖИ!$AB:$AB,ПРОДАЖИ!$AD:$AD,'ОБОРАЧИВ ПО СЕТИ+ABC'!$A:$A,ПРОДАЖИ!$AE:$AE,'ОБОРАЧИВ ПО СЕТИ+ABC'!I$1) -> 36393.047 | J44: =SUMIFS(ОСТАТКИ!$AE:$AE,ОСТАТКИ!$Q:$Q,'ОБОРАЧИВ ПО СЕТИ+ABC'!$A:$A,ОСТАТКИ!$S:$S,'ОБОРАЧИВ ПО СЕТИ+ABC'!I$1) -> 167740.41 | K44: =J44/(J44+N44+R44) -> 0.99563857 | L44: =IFERROR(J44/I44*30.5,0) -> 140.57857 | M44: =SUMIFS(ПРОДАЖИ!$AB:$AB,ПРОДАЖИ!$AD:$AD,'ОБОРАЧИВ ПО СЕТИ+ABC'!$A:$A,ПРОДАЖИ!$AE:$AE,'ОБОРАЧИВ ПО СЕТИ+ABC'!M$1) -> 0 | N44: =SUMIFS(ОСТАТКИ!$AE:$AE,ОСТАТКИ!$Q:$Q,'ОБОРАЧИВ ПО СЕТИ+ABC'!$A:$A,ОСТАТКИ!$S:$S,'ОБОРАЧИВ ПО СЕТИ+ABC'!M$1) -> 0 | O44: =N44/(J44+N44+R44) -> 0 | P44: =IFERROR(N44/M44*30.5,0) -> 0 | Q44: =SUMIFS(ПРОДАЖИ!$AB:$AB,ПРОДАЖИ!$AD:$AD,'ОБОРАЧИВ ПО СЕТИ+ABC'!$A:$A,ПРОДАЖИ!$AE:$AE,'ОБОРАЧИВ ПО СЕТИ+ABC'!Q$1) -> 100.58417 | R44: =SUMIFS(ОСТАТКИ!$AE:$AE,ОСТАТКИ!$Q:$Q,'ОБОРАЧИВ ПО СЕТИ+ABC'!$A:$A,ОСТАТКИ!$S:$S,'ОБОРАЧИВ ПО СЕТИ+ABC'!Q$1) -> 734.79291 | S44: =R44/(J44+N44+R44) -> 0.0043614307 | T44: =IFERROR(R44/Q44*30.5,0) -> 222.81025
